Workbook
Name HERBICIDA: LISTA!$B$2:$B$1000
Name FUNGICIDA: LISTA!$A$2:$A$1000
Name TS: LISTA!$D$2:$D$1000
Name TL01_IMPRESSAO: 'TL01'!$A$1:$L$226
Name CORRETIVOS: LISTA!$I$2:$I$1000
Name FERTILIZANTES: LISTA!$H$2:$H$1000
Name INSETICIDA: LISTA!$C$2:$C$1000
Name SEMENTE: LISTA!$F$2:$F$1000

Sheet LISTA
A1: FUNGICIDA | B1: HERBICIDA | C1: INSETICIDA | D1: TS | E1: BIOLÓGICOS | F1: SEMENTE | G1: ADJUVANTE | H1: FERTILIZANTES | I1: CORRETIVOS | J1: NUTRIÇÃO | K1: MÁQUINAS | L1: EMPEENDIMENTO | M1: ÁREAS | N1: HECTARES
A2: =IFERROR(__xludf.DUMMYFUNCTION("UNIQUE(FILTER('PORTIFÓLIO'!C:C, 'PORTIFÓLIO'!B:B=""FUNGICIDA""))"),"ACROSS") -> ACROSS | B2: =IFERROR(__xludf.DUMMYFUNCTION("UNIQUE(FILTER('PORTIFÓLIO'!C:C, 'PORTIFÓLIO'!B:B=""HERBICIDA""))"),"AMINOL 806") -> AMINOL 806 | C2: =IFERROR(__xludf.DUMMYFUNCTION("UNIQUE(FILTER('PORTIFÓLIO'!C:C, 'PORTIFÓLIO'!B:B=""INSETICIDA""))"),"GALIL SC") -> GALIL SC | D2: =IFERROR(__xludf.DUMMYFUNCTION("UNIQUE(FILTER('PORTIFÓLIO'!C:C, 'PORTIFÓLIO'!B:B=""TS""))"),"ENDOFUSE") -> ENDOFUSE | E2: =IFERROR(__xludf.DUMMYFUNCTION("UNIQUE(FILTER('PORTIFÓLIO'!C:C, 'PORTIFÓLIO'!B:B=""biológicos""))"),"UTRISHA N") -> UTRISHA N | F2: =IFERROR(__xludf.DUMMYFUNCTION("UNIQUE(FILTER('PORTIFÓLIO'!C:C, 'PORTIFÓLIO'!B:B=""SEMENTE""))"),"FEIJÃO") -> FEIJÃO | G2: =IFERROR(__xludf.DUMMYFUNCTION("UNIQUE(FILTER('PORTIFÓLIO'!C:C, 'PORTIFÓLIO'!B:B=""ADJUVANTE""))"),"RUMBA") -> RUMBA | H2: =IFERROR(__xludf.DUMMYFUNCTION("UNIQUE(FILTER('PORTIFÓLIO'!C:C, 'PORTIFÓLIO'!B:B=""fertilizantes""))"),"I-ACTIVE") -> I-ACTIVE | I2: =IFERROR(__xludf.DUMMYFUNCTION("UNIQUE(FILTER('PORTIFÓLIO'!C:C, 'PORTIFÓLIO'!B:B=""corretivos""))"),"CALCÁRIO DOLOMITICO") -> CALCÁRIO DOLOMITICO | J2: =IFERROR(__xludf.DUMMYFUNCTION("UNIQUE(FILTER('PORTIFÓLIO'!C:C, 'PORTIFÓLIO'!B:B=""NUTRIÇÃO""))"),"RADIFARM") -> RADIFARM | K2: =IFERROR(__xludf.DUMMYFUNCTION("UNIQUE(FILTER('PORTIFÓLIO'!C:C, 'PORTIFÓLIO'!B:B=""MÁQUINAS""))"),"CASE STEIGER 420 + HORSCH MAESTRO DUO 36.50") -> CASE STEIGER 420 + HORSCH MAESTRO DUO 36.50 | L2: FA-SOJA SEQUEIRO-26/27 | M2: ÁREA 1 | N2: 273
A3: =IFERROR(__xludf.DUMMYFUNCTION("""COMPUTED_VALUE"""),"AZIMUT") -> AZIMUT | B3: =IFERROR(__xludf.DUMMYFUNCTION("""COMPUTED_VALUE"""),"APRESA") -> APRESA | C3: =IFERROR(__xludf.DUMMYFUNCTION("""COMPUTED_VALUE"""),"MAGNUM") -> MAGNUM | D3: =IFERROR(__xludf.DUMMYFUNCTION("""COMPUTED_VALUE"""),"ENDOMAXX") -> ENDOMAXX | E3: =IFERROR(__xludf.DUMMYFUNCTION("""COMPUTED_VALUE"""),"PRESENCE FULL") -> PRESENCE FULL | F3: =IFERROR(__xludf.DUMMYFUNCTION("""COMPUTED_VALUE"""),"SEMENTE TRIGO") -> SEMENTE TRIGO | G3: =IFERROR(__xludf.DUMMYFUNCTION("""COMPUTED_VALUE"""),"ASSIST") -> ASSIST | H3: =IFERROR(__xludf.DUMMYFUNCTION("""COMPUTED_VALUE"""),"MAP") -> MAP | I3: =IFERROR(__xludf.DUMMYFUNCTION("""COMPUTED_VALUE"""),"GESSO AGRICOLA") -> GESSO AGRICOLA | J3: =IFERROR(__xludf.DUMMYFUNCTION("""COMPUTED_VALUE"""),"MEGAFOL") -> MEGAFOL | K3: =IFERROR(__xludf.DUMMYFUNCTION("""COMPUTED_VALUE"""),"CASE MAGNUM 340 + - CASE ASM 1213") -> CASE MAGNUM 340 + - CASE ASM 1213 | L3: FA-SOJA-IRRIGADO-26/27 | M3: ESTEVÃO | N3: 103
A4: =IFERROR(__xludf.DUMMYFUNCTION("""COMPUTED_VALUE"""),"BLINDADO TOV") -> BLINDADO TOV | B4: =IFERROR(__xludf.DUMMYFUNCTION("""COMPUTED_VALUE"""),"ARADDO") -> ARADDO | C4: =IFERROR(__xludf.DUMMYFUNCTION("""COMPUTED_VALUE"""),"PLETHORA BR") -> PLETHORA BR | D4: =IFERROR(__xludf.DUMMYFUNCTION("""COMPUTED_VALUE"""),"RIZOLIQ LLI") -> RIZOLIQ LLI | E4: =IFERROR(__xludf.DUMMYFUNCTION("""COMPUTED_VALUE"""),"Now Lock") -> Now Lock | F4: =IFERROR(__xludf.DUMMYFUNCTION("""COMPUTED_VALUE"""),"SEMENTE MILHO") -> SEMENTE MILHO | G4: =IFERROR(__xludf.DUMMYFUNCTION("""COMPUTED_VALUE"""),"MEES") -> MEES | H4: =IFERROR(__xludf.DUMMYFUNCTION("""COMPUTED_VALUE"""),"KCL 60%") -> KCL 60% | J4: =IFERROR(__xludf.DUMMYFUNCTION("""COMPUTED_VALUE"""),"OCTABORATO") -> OCTABORATO | K4: =IFERROR(__xludf.DUMMYFUNCTION("""COMPUTED_VALUE"""),"CR 8.90 NEW HOLLAND + 880 CF45") -> CR 8.90 NEW HOLLAND + 880 CF45 | L4: FA-MILHO SEQUEIRO-26/27 | M4: ÁREA 2 | N4: 110
A5: =IFERROR(__xludf.DUMMYFUNCTION("""COMPUTED_VALUE"""),"ABACUS HC") -> ABACUS HC | B5: =IFERROR(__xludf.DUMMYFUNCTION("""COMPUTED_VALUE"""),"CHEVAL") -> CHEVAL | C5: =IFERROR(__xludf.DUMMYFUNCTION("""COMPUTED_VALUE"""),"RIMON SUPRA") -> RIMON SUPRA | D5: =IFERROR(__xludf.DUMMYFUNCTION("""COMPUTED_VALUE"""),"PROVILAR") -> PROVILAR | E5: =IFERROR(__xludf.DUMMYFUNCTION("""COMPUTED_VALUE"""),"Now Guard") -> Now Guard | F5: =IFERROR(__xludf.DUMMYFUNCTION("""COMPUTED_VALUE"""),"MG540PWU") -> MG540PWU | G5: =IFERROR(__xludf.DUMMYFUNCTION("""COMPUTED_VALUE"""),"AUREO") -> AUREO | H5: =IFERROR(__xludf.DUMMYFUNCTION("""COMPUTED_VALUE"""),"05-37-00") -> 05-37-00 | J5: =IFERROR(__xludf.DUMMYFUNCTION("""COMPUTED_VALUE"""),"BOP") -> BOP | K5: =IFERROR(__xludf.DUMMYFUNCTION("""COMPUTED_VALUE"""),"COLHETADEIRA - NH-CR9060 + 740 CF30 AGRIDREPER") -> COLHETADEIRA - NH-CR9060 + 740 CF30 AGRIDREPER | L5: FA-SORGO SEQUEIRO-27/27 | M5: ÁREA 2 B | N5: 47
A6: =IFERROR(__xludf.DUMMYFUNCTION("""COMPUTED_VALUE"""),"BELYAN") -> BELYAN | B6: =IFERROR(__xludf.DUMMYFUNCTION("""COMPUTED_VALUE"""),"POQUER") -> POQUER | C6: =IFERROR(__xludf.DUMMYFUNCTION("""COMPUTED_VALUE"""),"SQUAD") -> SQUAD | D6: =IFERROR(__xludf.DUMMYFUNCTION("""COMPUTED_VALUE"""),"REVERB") -> REVERB | E6: =IFERROR(__xludf.DUMMYFUNCTION("""COMPUTED_VALUE"""),"Now Force") -> Now Force | F6: =IFERROR(__xludf.DUMMYFUNCTION("""COMPUTED_VALUE"""),"MG711PWU") -> MG711PWU | G6: =IFERROR(__xludf.DUMMYFUNCTION("""COMPUTED_VALUE"""),"JOINT ULTRA") -> JOINT ULTRA | H6: =IFERROR(__xludf.DUMMYFUNCTION("""COMPUTED_VALUE"""),"10-46-00 + S") -> 10-46-00 + S | J6: =IFERROR(__xludf.DUMMYFUNCTION("""COMPUTED_VALUE"""),"METAL NUTRE") -> METAL NUTRE | K6: =IFERROR(__xludf.DUMMYFUNCTION("""COMPUTED_VALUE"""),"COLHETADEIRA CR7.80 + MACDON 35F") -> COLHETADEIRA CR7.80 + MACDON 35F | L6: FA-MILHO SEMENTE-27/27 | M6: ÁREA 3 | N6: 60
A7: =IFERROR(__xludf.DUMMYFUNCTION("""COMPUTED_VALUE"""),"BLAVITY") -> BLAVITY | B7: =IFERROR(__xludf.DUMMYFUNCTION("""COMPUTED_VALUE"""),"PREMERLIN 600 EC") -> PREMERLIN 600 EC | C7: =IFERROR(__xludf.DUMMYFUNCTION("""COMPUTED_VALUE"""),"TRIVOR") -> TRIVOR | D7: =IFERROR(__xludf.DUMMYFUNCTION("""COMPUTED_VALUE"""),"ARVATICO") -> ARVATICO | E7: =IFERROR(__xludf.DUMMYFUNCTION("""COMPUTED_VALUE"""),"Now Raze") -> Now Raze | F7: =IFERROR(__xludf.DUMMYFUNCTION("""COMPUTED_VALUE"""),"MG616PWU") -> MG616PWU | G7: =IFERROR(__xludf.DUMMYFUNCTION("""COMPUTED_VALUE"""),"ADGREEN") -> ADGREEN | H7: =IFERROR(__xludf.DUMMYFUNCTION("""COMPUTED_VALUE"""),"08-42-00") -> 08-42-00 | J7: =IFERROR(__xludf.DUMMYFUNCTION("""COMPUTED_VALUE"""),"MONIC") -> MONIC | K7: =IFERROR(__xludf.DUMMYFUNCTION("""COMPUTED_VALUE"""),"TRATOR-JD 7500 + BRUTUS 12000") -> TRATOR-JD 7500 + BRUTUS 12000 | L7: FE-SOJA IRRIGADO-26/27 | M7: CAPOEIRINHA | N7: 312
A8: =IFERROR(__xludf.DUMMYFUNCTION("""COMPUTED_VALUE"""),"CANTUS") -> CANTUS | B8: =IFERROR(__xludf.DUMMYFUNCTION("""COMPUTED_VALUE"""),"AMPLO") -> AMPLO | C8: =IFERROR(__xludf.DUMMYFUNCTION("""COMPUTED_VALUE"""),"EFFICON") -> EFFICON | D8: =IFERROR(__xludf.DUMMYFUNCTION("""COMPUTED_VALUE"""),"VERANGO PRIME") -> VERANGO PRIME | E8: =IFERROR(__xludf.DUMMYFUNCTION("""COMPUTED_VALUE"""),"Now Bolt") -> Now Bolt | F8: =IFERROR(__xludf.DUMMYFUNCTION("""COMPUTED_VALUE"""),"P3707PWU") -> P3707PWU | G8: =IFERROR(__xludf.DUMMYFUNCTION("""COMPUTED_VALUE"""),"ENERGIC") -> ENERGIC | H8: =IFERROR(__xludf.DUMMYFUNCTION("""COMPUTED_VALUE"""),"SSP 21") -> SSP 21 | J8: =IFERROR(__xludf.DUMMYFUNCTION("""COMPUTED_VALUE"""),"AP MAGNÉSIO") -> AP MAGNÉSIO | K8: =IFERROR(__xludf.DUMMYFUNCTION("""COMPUTED_VALUE"""),"TRATOR-JD 7500 + ADUBADORA HERCULES 10000") -> TRATOR-JD 7500 + ADUBADORA HERCULES 10000 | L8: FE-BRACHIARIA-26/27 | M8: RONCADOR | N8: 313
A9: =IFERROR(__xludf.DUMMYFUNCTION("""COMPUTED_VALUE"""),"KEYRA") -> KEYRA | B9: =IFERROR(__xludf.DUMMYFUNCTION("""COMPUTED_VALUE"""),"BASAGRAN 600") -> BASAGRAN 600 | C9: =IFERROR(__xludf.DUMMYFUNCTION("""COMPUTED_VALUE"""),"NOMOLT 150") -> NOMOLT 150 | D9: =IFERROR(__xludf.DUMMYFUNCTION("""COMPUTED_VALUE"""),"FIPRONIL NORTOX MAX") -> FIPRONIL NORTOX MAX | E9: =IFERROR(__xludf.DUMMYFUNCTION("""COMPUTED_VALUE"""),"Now Active") -> Now Active | F9: =IFERROR(__xludf.DUMMYFUNCTION("""COMPUTED_VALUE"""),"P39209PWU") -> P39209PWU | G9: =IFERROR(__xludf.DUMMYFUNCTION("""COMPUTED_VALUE"""),"EXTRAVON") -> EXTRAVON | H9: =IFERROR(__xludf.DUMMYFUNCTION("""COMPUTED_VALUE"""),"03-15-07 +14%CO") -> 03-15-07 +14%CO | J9: =IFERROR(__xludf.DUMMYFUNCTION("""COMPUTED_VALUE"""),"GRANO KMG") -> GRANO KMG | K9: =IFERROR(__xludf.DUMMYFUNCTION("""COMPUTED_VALUE"""),"VOLVO NH380 + CAÇAMBA 430SC") -> VOLVO NH380 + CAÇAMBA 430SC | L9: FE-SOJA SEQUEIRO-26/27 | M9: RONCADOR 2 | N9: 0
A10: =IFERROR(__xludf.DUMMYFUNCTION("""COMPUTED_VALUE"""),"MELYRA") -> MELYRA | B10: =IFERROR(__xludf.DUMMYFUNCTION("""COMPUTED_VALUE"""),"FINALE") -> FINALE | C10: =IFERROR(__xludf.DUMMYFUNCTION("""COMPUTED_VALUE"""),"PIRATE") -> PIRATE | D10: =IFERROR(__xludf.DUMMYFUNCTION("""COMPUTED_VALUE"""),"MAXIM ADVANCED") -> MAXIM ADVANCED | E10: =IFERROR(__xludf.DUMMYFUNCTION("""COMPUTED_VALUE"""),"Now React") -> Now React | F10: =IFERROR(__xludf.DUMMYFUNCTION("""COMPUTED_VALUE"""),"P40537PWU") -> P40537PWU | G10: =IFERROR(__xludf.DUMMYFUNCTION("""COMPUTED_VALUE"""),"OCHIMA") -> OCHIMA | H10: =IFERROR(__xludf.DUMMYFUNCTION("""COMPUTED_VALUE"""),"URÉIA") -> URÉIA | J10: =IFERROR(__xludf.DUMMYFUNCTION("""COMPUTED_VALUE"""),"AP MANGANÊS") -> AP MANGANÊS | K10: =IFERROR(__xludf.DUMMYFUNCTION("""COMPUTED_VALUE"""),"CASE MAGNUM 340 + SUBSOLADOR 11 ASTES") -> CASE MAGNUM 340 + SUBSOLADOR 11 ASTES | L10: FE-SORGO IRRIGADO-26/27 | M10: P200 | N10: 200
A11: =IFERROR(__xludf.DUMMYFUNCTION("""COMPUTED_VALUE"""),"ORKESTRA SC") -> ORKESTRA SC | B11: =IFERROR(__xludf.DUMMYFUNCTION("""COMPUTED_VALUE"""),"HEAT") -> HEAT | C11: =IFERROR(__xludf.DUMMYFUNCTION("""COMPUTED_VALUE"""),"BELT") -> BELT | D11: =IFERROR(__xludf.DUMMYFUNCTION("""COMPUTED_VALUE"""),"MAXIM XL") -> MAXIM XL | E11: =IFERROR(__xludf.DUMMYFUNCTION("""COMPUTED_VALUE"""),"Now Cover") -> Now Cover | F11: =IFERROR(__xludf.DUMMYFUNCTION("""COMPUTED_VALUE"""),"FS650PWU") -> FS650PWU | H11: =IFERROR(__xludf.DUMMYFUNCTION("""COMPUTED_VALUE"""),"SULFATO DE AMÔNIO") -> SULFATO DE AMÔNIO | J11: =IFERROR(__xludf.DUMMYFUNCTION("""COMPUTED_VALUE"""),"AMINOS Mn") -> AMINOS Mn | K11: =IFERROR(__xludf.DUMMYFUNCTION("""COMPUTED_VALUE"""),"PULVERIZADOR- JD4730 + PULVERIZADOR- JD4730") -> PULVERIZADOR- JD4730 + PULVERIZADOR- JD4730 | L11: FE-SORGO SEQUEIRO-26/27 | M11: P120 | N11: 120
A12: =IFERROR(__xludf.DUMMYFUNCTION("""COMPUTED_VALUE"""),"SPOT SC") -> SPOT SC | B12: =IFERROR(__xludf.DUMMYFUNCTION("""COMPUTED_VALUE"""),"LIBERTY") -> LIBERTY | C12: =IFERROR(__xludf.DUMMYFUNCTION("""COMPUTED_VALUE"""),"BULLDOCK 125 SC") -> BULLDOCK 125 SC | D12: =IFERROR(__xludf.DUMMYFUNCTION("""COMPUTED_VALUE"""),"VICTRATO") -> VICTRATO | E12: =IFERROR(__xludf.DUMMYFUNCTION("""COMPUTED_VALUE"""),"Now Pulse") -> Now Pulse | F12: =IFERROR(__xludf.DUMMYFUNCTION("""COMPUTED_VALUE"""),"SEMENTE SOJA CV") -> SEMENTE SOJA CV | H12: =IFERROR(__xludf.DUMMYFUNCTION("""COMPUTED_VALUE"""),"BOROGRAN") -> BOROGRAN | J12: =IFERROR(__xludf.DUMMYFUNCTION("""COMPUTED_VALUE"""),"MICROBOX") -> MICROBOX | K12: =IFERROR(__xludf.DUMMYFUNCTION("""COMPUTED_VALUE"""),"AIR TRATOR AT-502B + AIR TRATOR AT-502B") -> AIR TRATOR AT-502B + AIR TRATOR AT-502B | M12: BARRO BRANCO | N12: 220
A13: =IFERROR(__xludf.DUMMYFUNCTION("""COMPUTED_VALUE"""),"ATTILA") -> ATTILA | B13: =IFERROR(__xludf.DUMMYFUNCTION("""COMPUTED_VALUE"""),"PROWL H2O") -> PROWL H2O | C13: =IFERROR(__xludf.DUMMYFUNCTION("""COMPUTED_VALUE"""),"CERTERO") -> CERTERO | D13: =IFERROR(__xludf.DUMMYFUNCTION("""COMPUTED_VALUE"""),"SPECTRO") -> SPECTRO | E13: =IFERROR(__xludf.DUMMYFUNCTION("""COMPUTED_VALUE"""),"Now Sprint") -> Now Sprint | F13: =IFERROR(__xludf.DUMMYFUNCTION("""COMPUTED_VALUE"""),"OLIMPO") -> OLIMPO | H13: =IFERROR(__xludf.DUMMYFUNCTION("""COMPUTED_VALUE"""),"SUPER DUO") -> SUPER DUO | J13: =IFERROR(__xludf.DUMMYFUNCTION("""COMPUTED_VALUE"""),"ACRESECENT ALGA") -> ACRESECENT ALGA | K13: =IFERROR(__xludf.DUMMYFUNCTION("""COMPUTED_VALUE"""),"COLHETADEIRA - NH-CR9060 + MILHO BRAVA 11") -> COLHETADEIRA - NH-CR9060 + MILHO BRAVA 11 | M13: P 01 | N13: 60
A14: =IFERROR(__xludf.DUMMYFUNCTION("""COMPUTED_VALUE"""),"FOX SUPRA") -> FOX SUPRA | B14: =IFERROR(__xludf.DUMMYFUNCTION("""COMPUTED_VALUE"""),"ADENGO") -> ADENGO | C14: =IFERROR(__xludf.DUMMYFUNCTION("""COMPUTED_VALUE"""),"CONNECT") -> CONNECT | D14: =IFERROR(__xludf.DUMMYFUNCTION("""COMPUTED_VALUE"""),"STANDAK TOP") -> STANDAK TOP | E14: =IFERROR(__xludf.DUMMYFUNCTION("""COMPUTED_VALUE"""),"Bio Az") -> Bio Az | F14: =IFERROR(__xludf.DUMMYFUNCTION("""COMPUTED_VALUE"""),"M8349") -> M8349 | H14: =IFERROR(__xludf.DUMMYFUNCTION("""COMPUTED_VALUE"""),"08-40-00 - 100M") -> 08-40-00 - 100M | J14: =IFERROR(__xludf.DUMMYFUNCTION("""COMPUTED_VALUE"""),"RAIZ F") -> RAIZ F | K14: =IFERROR(__xludf.DUMMYFUNCTION("""COMPUTED_VALUE"""),"NH T7.260 + JAN 20000") -> NH T7.260 + JAN 20000 | M14: P 02 | N14: 80
A15: =IFERROR(__xludf.DUMMYFUNCTION("""COMPUTED_VALUE"""),"FOX XPRO") -> FOX XPRO | B15: =IFERROR(__xludf.DUMMYFUNCTION("""COMPUTED_VALUE"""),"ROUNDUP WG") -> ROUNDUP WG | C15: =IFERROR(__xludf.DUMMYFUNCTION("""COMPUTED_VALUE"""),"CURBIX 200 SC") -> CURBIX 200 SC | D15: =IFERROR(__xludf.DUMMYFUNCTION("""COMPUTED_VALUE"""),"CRUISER ADVANCED") -> CRUISER ADVANCED | E15: =IFERROR(__xludf.DUMMYFUNCTION("""COMPUTED_VALUE"""),"Bio ND") -> Bio ND | F15: =IFERROR(__xludf.DUMMYFUNCTION("""COMPUTED_VALUE"""),"CORDIUS C2795 CE") -> CORDIUS C2795 CE | H15: =IFERROR(__xludf.DUMMYFUNCTION("""COMPUTED_VALUE"""),"AURUS 500") -> AURUS 500 | J15: =IFERROR(__xludf.DUMMYFUNCTION("""COMPUTED_VALUE"""),"ACRESCENTE SOLUS F") -> ACRESCENTE SOLUS F | K15: =IFERROR(__xludf.DUMMYFUNCTION("""COMPUTED_VALUE"""),"NH T8.355 + - JD2122") -> NH T8.355 + - JD2122 | M15: P 03 | N15: 120
A16: =IFERROR(__xludf.DUMMYFUNCTION("""COMPUTED_VALUE"""),"NATIVO") -> NATIVO | B16: =IFERROR(__xludf.DUMMYFUNCTION("""COMPUTED_VALUE"""),"SOBERAN") -> SOBERAN | C16: =IFERROR(__xludf.DUMMYFUNCTION("""COMPUTED_VALUE"""),"OBERON") -> OBERON | D16: =IFERROR(__xludf.DUMMYFUNCTION("""COMPUTED_VALUE"""),"PLUST") -> PLUST | E16: =IFERROR(__xludf.DUMMYFUNCTION("""COMPUTED_VALUE"""),"Tec Catp Pro") -> Tec Catp Pro | F16: =IFERROR(__xludf.DUMMYFUNCTION("""COMPUTED_VALUE"""),"HERA I2X") -> HERA I2X | H16: =IFERROR(__xludf.DUMMYFUNCTION("""COMPUTED_VALUE"""),"00-01-00+Cu2 Mn8 Zn7 ") -> 00-01-00+Cu2 Mn8 Zn7 | J16: =IFERROR(__xludf.DUMMYFUNCTION("""COMPUTED_VALUE"""),"SALUT") -> SALUT | K16: =IFERROR(__xludf.DUMMYFUNCTION("""COMPUTED_VALUE"""),"COLHETADEIRA - CASE 2388 + CASE 30PES") -> COLHETADEIRA - CASE 2388 + CASE 30PES | M16: P 04 | N16: 130
A17: =IFERROR(__xludf.DUMMYFUNCTION("""COMPUTED_VALUE"""),"NATIVO PLUS") -> NATIVO PLUS | B17: =IFERROR(__xludf.DUMMYFUNCTION("""COMPUTED_VALUE"""),"2,4-D 806+PICLORAM 64") -> 2,4-D 806+PICLORAM 64 | C17: =IFERROR(__xludf.DUMMYFUNCTION("""COMPUTED_VALUE"""),"ACETAMIPRID CCAB 200 SP") -> ACETAMIPRID CCAB 200 SP | D17: =IFERROR(__xludf.DUMMYFUNCTION("""COMPUTED_VALUE"""),"SOMBRERO") -> SOMBRERO | E17: =IFERROR(__xludf.DUMMYFUNCTION("""COMPUTED_VALUE"""),"Bio Elipso") -> Bio Elipso | F17: =IFERROR(__xludf.DUMMYFUNCTION("""COMPUTED_VALUE"""),"SPARTA 8.0") -> SPARTA 8.0 | J17: =IFERROR(__xludf.DUMMYFUNCTION("""COMPUTED_VALUE"""),"MATRIZ D") -> MATRIZ D | K17: =IFERROR(__xludf.DUMMYFUNCTION("""COMPUTED_VALUE"""),"JACTO UNIPORT 2000 + JACTO UNIPORT 2000") -> JACTO UNIPORT 2000 + JACTO UNIPORT 2000 | M17: P 05 | N17: 120
A18: =IFERROR(__xludf.DUMMYFUNCTION("""COMPUTED_VALUE"""),"SPHERE MAX") -> SPHERE MAX | B18: =IFERROR(__xludf.DUMMYFUNCTION("""COMPUTED_VALUE"""),"FOMESAFEN CCAB 250 SL") -> FOMESAFEN CCAB 250 SL | C18: =IFERROR(__xludf.DUMMYFUNCTION("""COMPUTED_VALUE"""),"DIFLUBENZURON CCAB 480 SC") -> DIFLUBENZURON CCAB 480 SC | D18: =IFERROR(__xludf.DUMMYFUNCTION("""COMPUTED_VALUE"""),"CROPSTAR") -> CROPSTAR | E18: =IFERROR(__xludf.DUMMYFUNCTION("""COMPUTED_VALUE"""),"Tec Bug") -> Tec Bug | F18: =IFERROR(__xludf.DUMMYFUNCTION("""COMPUTED_VALUE"""),"CORDIUS C2795 CE 7.9") -> CORDIUS C2795 CE 7.9 | J18: =IFERROR(__xludf.DUMMYFUNCTION("""COMPUTED_VALUE"""),"BRAVERO") -> BRAVERO | K18: =IFERROR(__xludf.DUMMYFUNCTION("""COMPUTED_VALUE"""),"NH T7.260 + CASE 2213") -> NH T7.260 + CASE 2213 | M18: P 06 | N18: 40
A19: =IFERROR(__xludf.DUMMYFUNCTION("""COMPUTED_VALUE"""),"AZOXISTROBIN 200 + CIPROCONAZOL 80 SC CCAB") -> AZOXISTROBIN 200 + CIPROCONAZOL 80 SC CCAB | B19: =IFERROR(__xludf.DUMMYFUNCTION("""COMPUTED_VALUE"""),"GLUFOSINATO CCAB 200 SL") -> GLUFOSINATO CCAB 200 SL | C19: =IFERROR(__xludf.DUMMYFUNCTION("""COMPUTED_VALUE"""),"FIPRONIL 800 WG CCAB") -> FIPRONIL 800 WG CCAB | D19: =IFERROR(__xludf.DUMMYFUNCTION("""COMPUTED_VALUE"""),"DERMACOR") -> DERMACOR | E19: =IFERROR(__xludf.DUMMYFUNCTION("""COMPUTED_VALUE"""),"Solu Shield") -> Solu Shield | F19: =IFERROR(__xludf.DUMMYFUNCTION("""COMPUTED_VALUE"""),"IMPETO") -> IMPETO | J19: =IFERROR(__xludf.DUMMYFUNCTION("""COMPUTED_VALUE"""),"Glyfort") -> Glyfort | K19: =IFERROR(__xludf.DUMMYFUNCTION("""COMPUTED_VALUE""")," + ") -> + | M19: T01 | N19: 220
A20: =IFERROR(__xludf.DUMMYFUNCTION("""COMPUTED_VALUE"""),"MANCOZEB CCAB 750 WG") -> MANCOZEB CCAB 750 WG | B20: =IFERROR(__xludf.DUMMYFUNCTION("""COMPUTED_VALUE"""),"MESOTRIONA CCAB 480 SC") -> MESOTRIONA CCAB 480 SC | C20: =IFERROR(__xludf.DUMMYFUNCTION("""COMPUTED_VALUE"""),"INDOXACARB CCAB 150 SC") -> INDOXACARB CCAB 150 SC | D20: =IFERROR(__xludf.DUMMYFUNCTION("""COMPUTED_VALUE"""),"OPTERASEED") -> OPTERASEED | E20: =IFERROR(__xludf.DUMMYFUNCTION("""COMPUTED_VALUE"""),"Solu Strong") -> Solu Strong | F20: =IFERROR(__xludf.DUMMYFUNCTION("""COMPUTED_VALUE"""),"NEO 790") -> NEO 790 | J20: =IFERROR(__xludf.DUMMYFUNCTION("""COMPUTED_VALUE"""),"Fergsum") -> Fergsum | M20: T02 | N20: 220
A21: =IFERROR(__xludf.DUMMYFUNCTION("""COMPUTED_VALUE"""),"APROACH POWER") -> APROACH POWER | B21: =IFERROR(__xludf.DUMMYFUNCTION("""COMPUTED_VALUE"""),"TRICLOPIR CCAB 480 EC") -> TRICLOPIR CCAB 480 EC | C21: =IFERROR(__xludf.DUMMYFUNCTION("""COMPUTED_VALUE"""),"EXALT") -> EXALT | D21: =IFERROR(__xludf.DUMMYFUNCTION("""COMPUTED_VALUE"""),"AVICTA 500 FS") -> AVICTA 500 FS | E21: =IFERROR(__xludf.DUMMYFUNCTION("""COMPUTED_VALUE"""),"Solu Leaf") -> Solu Leaf | F21: =IFERROR(__xludf.DUMMYFUNCTION("""COMPUTED_VALUE"""),"APORÉ 7.3") -> APORÉ 7.3 | J21: =IFERROR(__xludf.DUMMYFUNCTION("""COMPUTED_VALUE"""),"Spander") -> Spander
A22: =IFERROR(__xludf.DUMMYFUNCTION("""COMPUTED_VALUE"""),"APROACH PREMIUM") -> APROACH PREMIUM | B22: =IFERROR(__xludf.DUMMYFUNCTION("""COMPUTED_VALUE"""),"ACCENT") -> ACCENT | C22: =IFERROR(__xludf.DUMMYFUNCTION("""COMPUTED_VALUE"""),"EXPEDITION") -> EXPEDITION | D22: =IFERROR(__xludf.DUMMYFUNCTION("""COMPUTED_VALUE"""),"CRUISER 350 FS") -> CRUISER 350 FS | E22: =IFERROR(__xludf.DUMMYFUNCTION("""COMPUTED_VALUE"""),"Bio Hidric") -> Bio Hidric | F22: =IFERROR(__xludf.DUMMYFUNCTION("""COMPUTED_VALUE"""),"GUAPÓ 7.7") -> GUAPÓ 7.7 | J22: =IFERROR(__xludf.DUMMYFUNCTION("""COMPUTED_VALUE"""),"Halattus") -> Halattus
A23: =IFERROR(__xludf.DUMMYFUNCTION("""COMPUTED_VALUE"""),"BIM 750 BR") -> BIM 750 BR | B23: =IFERROR(__xludf.DUMMYFUNCTION("""COMPUTED_VALUE"""),"CLASSIC") -> CLASSIC | C23: =IFERROR(__xludf.DUMMYFUNCTION("""COMPUTED_VALUE"""),"INTREPID 240 SC") -> INTREPID 240 SC | D23: =IFERROR(__xludf.DUMMYFUNCTION("""COMPUTED_VALUE"""),"FORTENZA 600 FS") -> FORTENZA 600 FS | E23: =IFERROR(__xludf.DUMMYFUNCTION("""COMPUTED_VALUE"""),"Bio Bokashi") -> Bio Bokashi | F23: =IFERROR(__xludf.DUMMYFUNCTION("""COMPUTED_VALUE"""),"MITICA 7.7") -> MITICA 7.7 | J23: =IFERROR(__xludf.DUMMYFUNCTION("""COMPUTED_VALUE"""),"Sallvare Complex") -> Sallvare Complex
A24: =IFERROR(__xludf.DUMMYFUNCTION("""COMPUTED_VALUE"""),"BIM MAX") -> BIM MAX | B24: =IFERROR(__xludf.DUMMYFUNCTION("""COMPUTED_VALUE"""),"CLINCHER") -> CLINCHER | C24: =IFERROR(__xludf.DUMMYFUNCTION("""COMPUTED_VALUE"""),"INTREPID EDGE") -> INTREPID EDGE | D24: =IFERROR(__xludf.DUMMYFUNCTION("""COMPUTED_VALUE"""),"ILEVO") -> ILEVO | E24: =IFERROR(__xludf.DUMMYFUNCTION("""COMPUTED_VALUE"""),"Bio Oil") -> Bio Oil | F24: =IFERROR(__xludf.DUMMYFUNCTION("""COMPUTED_VALUE"""),"TMG MURICI I2X 7.6") -> TMG MURICI I2X 7.6 | J24: =IFERROR(__xludf.DUMMYFUNCTION("""COMPUTED_VALUE"""),"Zinctaus Complex") -> Zinctaus Complex
A25: =IFERROR(__xludf.DUMMYFUNCTION("""COMPUTED_VALUE"""),"ORANIS") -> ORANIS | B25: =IFERROR(__xludf.DUMMYFUNCTION("""COMPUTED_VALUE"""),"ELEVORE") -> ELEVORE | C25: =IFERROR(__xludf.DUMMYFUNCTION("""COMPUTED_VALUE"""),"LANNATE BR") -> LANNATE BR | D25: =IFERROR(__xludf.DUMMYFUNCTION("""COMPUTED_VALUE"""),"PERMIT STAR") -> PERMIT STAR | E25: =IFERROR(__xludf.DUMMYFUNCTION("""COMPUTED_VALUE"""),"Carbon Pro") -> Carbon Pro | F25: =IFERROR(__xludf.DUMMYFUNCTION("""COMPUTED_VALUE"""),"DOMÍNIO 8.4") -> DOMÍNIO 8.4 | J25: =IFERROR(__xludf.DUMMYFUNCTION("""COMPUTED_VALUE"""),"Emezine Complex") -> Emezine Complex
A26: =IFERROR(__xludf.DUMMYFUNCTION("""COMPUTED_VALUE"""),"VESSARYA") -> VESSARYA | B26: =IFERROR(__xludf.DUMMYFUNCTION("""COMPUTED_VALUE"""),"ENLIST COLEX-D") -> ENLIST COLEX-D | C26: =IFERROR(__xludf.DUMMYFUNCTION("""COMPUTED_VALUE"""),"ACETAMIPRID 250 G/KG + BIFENTHRIN 250G/KG WG") -> ACETAMIPRID 250 G/KG + BIFENTHRIN 250G/KG WG | E26: =IFERROR(__xludf.DUMMYFUNCTION("""COMPUTED_VALUE"""),"Essencial Mg") -> Essencial Mg | F26: =IFERROR(__xludf.DUMMYFUNCTION("""COMPUTED_VALUE"""),"LENDA") -> LENDA | J26: =IFERROR(__xludf.DUMMYFUNCTION("""COMPUTED_VALUE"""),"Boratus Complex") -> Boratus Complex
A27: =IFERROR(__xludf.DUMMYFUNCTION("""COMPUTED_VALUE"""),"CHARRUA 430 SC") -> CHARRUA 430 SC | B27: =IFERROR(__xludf.DUMMYFUNCTION("""COMPUTED_VALUE"""),"GAPPER") -> GAPPER | C27: =IFERROR(__xludf.DUMMYFUNCTION("""COMPUTED_VALUE"""),"BAKANA 400 SC") -> BAKANA 400 SC | E27: =IFERROR(__xludf.DUMMYFUNCTION("""COMPUTED_VALUE"""),"Expelir") -> Expelir | F27: =IFERROR(__xludf.DUMMYFUNCTION("""COMPUTED_VALUE"""),"BRASMAX HERA") -> BRASMAX HERA | J27: =IFERROR(__xludf.DUMMYFUNCTION("""COMPUTED_VALUE"""),"Magmill Complex") -> Magmill Complex
A28: =IFERROR(__xludf.DUMMYFUNCTION("""COMPUTED_VALUE"""),"SEVARE 250 EC") -> SEVARE 250 EC | B28: =IFERROR(__xludf.DUMMYFUNCTION("""COMPUTED_VALUE"""),"PACTO") -> PACTO | C28: =IFERROR(__xludf.DUMMYFUNCTION("""COMPUTED_VALUE"""),"KRATON 100 EC") -> KRATON 100 EC | E28: =IFERROR(__xludf.DUMMYFUNCTION("""COMPUTED_VALUE"""),"Primafert") -> Primafert | F28: =IFERROR(__xludf.DUMMYFUNCTION("""COMPUTED_VALUE"""),"BRASMAX OLIMPO") -> BRASMAX OLIMPO | J28: =IFERROR(__xludf.DUMMYFUNCTION("""COMPUTED_VALUE"""),"Brave K") -> Brave K
A29: =IFERROR(__xludf.DUMMYFUNCTION("""COMPUTED_VALUE"""),"VENCER DUO") -> VENCER DUO | B29: =IFERROR(__xludf.DUMMYFUNCTION("""COMPUTED_VALUE"""),"PAXEO") -> PAXEO | C29: =IFERROR(__xludf.DUMMYFUNCTION("""COMPUTED_VALUE"""),"TAURA 200 EC") -> TAURA 200 EC | E29: =IFERROR(__xludf.DUMMYFUNCTION("""COMPUTED_VALUE"""),"Reserva") -> Reserva | F29: =IFERROR(__xludf.DUMMYFUNCTION("""COMPUTED_VALUE"""),"S6525 I2X") -> S6525 I2X | J29: =IFERROR(__xludf.DUMMYFUNCTION("""COMPUTED_VALUE"""),"Brave Max Up") -> Brave Max Up
A30: =IFERROR(__xludf.DUMMYFUNCTION("""COMPUTED_VALUE"""),"ONSUVA") -> ONSUVA | B30: =IFERROR(__xludf.DUMMYFUNCTION("""COMPUTED_VALUE"""),"SPIDER 840 WG") -> SPIDER 840 WG | C30: =IFERROR(__xludf.DUMMYFUNCTION("""COMPUTED_VALUE"""),"BENEVIA") -> BENEVIA | E30: =IFERROR(__xludf.DUMMYFUNCTION("""COMPUTED_VALUE"""),"Tec Catp Pro Kit On-farm") -> Tec Catp Pro Kit On-farm | F30: =IFERROR(__xludf.DUMMYFUNCTION("""COMPUTED_VALUE"""),"TMG ITAÚBA I2X") -> TMG ITAÚBA I2X | J30: =IFERROR(__xludf.DUMMYFUNCTION("""COMPUTED_VALUE"""),"MAX RAIZ") -> MAX RAIZ
A31: =IFERROR(__xludf.DUMMYFUNCTION("""COMPUTED_VALUE"""),"BOSCALID NORTOX 500 WG") -> BOSCALID NORTOX 500 WG | B31: =IFERROR(__xludf.DUMMYFUNCTION("""COMPUTED_VALUE"""),"VERDICT ULTRA") -> VERDICT ULTRA | C31: =IFERROR(__xludf.DUMMYFUNCTION("""COMPUTED_VALUE"""),"HERO") -> HERO | E31: =IFERROR(__xludf.DUMMYFUNCTION("""COMPUTED_VALUE"""),"Tec Bug Kit On-farm") -> Tec Bug Kit On-farm | J31: =IFERROR(__xludf.DUMMYFUNCTION("""COMPUTED_VALUE"""),"Polyamine") -> Polyamine
A32: =IFERROR(__xludf.DUMMYFUNCTION("""COMPUTED_VALUE"""),"DIFENOCONAZOL NORTOX 250 SC") -> DIFENOCONAZOL NORTOX 250 SC | B32: =IFERROR(__xludf.DUMMYFUNCTION("""COMPUTED_VALUE"""),"BLOWOUT") -> BLOWOUT | C32: =IFERROR(__xludf.DUMMYFUNCTION("""COMPUTED_VALUE"""),"MALATHION UL") -> MALATHION UL | E32: =IFERROR(__xludf.DUMMYFUNCTION("""COMPUTED_VALUE"""),"Solu Shield Kit On-farm") -> Solu Shield Kit On-farm | F32: =IFERROR(__xludf.DUMMYFUNCTION("""COMPUTED_VALUE"""),"SEMENTE SOJA RR") -> SEMENTE SOJA RR | J32: =IFERROR(__xludf.DUMMYFUNCTION("""COMPUTED_VALUE"""),"Sulfato de Magnésio") -> Sulfato de Magnésio
A33: =IFERROR(__xludf.DUMMYFUNCTION("""COMPUTED_VALUE"""),"FLUAZINAM NORTOX 500 SC") -> FLUAZINAM NORTOX 500 SC | B33: =IFERROR(__xludf.DUMMYFUNCTION("""COMPUTED_VALUE"""),"CLETODIM 240 EC BRILLIANCE") -> CLETODIM 240 EC BRILLIANCE | C33: =IFERROR(__xludf.DUMMYFUNCTION("""COMPUTED_VALUE"""),"MUSTANG 350 EC") -> MUSTANG 350 EC | E33: =IFERROR(__xludf.DUMMYFUNCTION("""COMPUTED_VALUE"""),"Solu Strong Kit On-farm") -> Solu Strong Kit On-farm | F33: =IFERROR(__xludf.DUMMYFUNCTION("""COMPUTED_VALUE"""),"BRACHIARIA RUZIZIENCES") -> BRACHIARIA RUZIZIENCES | J33: =IFERROR(__xludf.DUMMYFUNCTION("""COMPUTED_VALUE"""),"Map Purificado") -> Map Purificado
A34: =IFERROR(__xludf.DUMMYFUNCTION("""COMPUTED_VALUE"""),"FLUTRIAFOL NORTOX") -> FLUTRIAFOL NORTOX | B34: =IFERROR(__xludf.DUMMYFUNCTION("""COMPUTED_VALUE"""),"GLUFOS-WYN 880") -> GLUFOS-WYN 880 | C34: =IFERROR(__xludf.DUMMYFUNCTION("""COMPUTED_VALUE"""),"PREMIO") -> PREMIO | E34: =IFERROR(__xludf.DUMMYFUNCTION("""COMPUTED_VALUE"""),"Solu Leaf Kit On-farm") -> Solu Leaf Kit On-farm | F34: =IFERROR(__xludf.DUMMYFUNCTION("""COMPUTED_VALUE"""),"CAPIM MIAGE") -> CAPIM MIAGE | J34: =IFERROR(__xludf.DUMMYFUNCTION("""COMPUTED_VALUE"""),"MANGAN 10") -> MANGAN 10
A35: =IFERROR(__xludf.DUMMYFUNCTION("""COMPUTED_VALUE"""),"PROPICONAZOLE NORTOX 500 EC") -> PROPICONAZOLE NORTOX 500 EC | B35: =IFERROR(__xludf.DUMMYFUNCTION("""COMPUTED_VALUE"""),"GINETE 212 SL") -> GINETE 212 SL | C35: =IFERROR(__xludf.DUMMYFUNCTION("""COMPUTED_VALUE"""),"TALISMAN") -> TALISMAN | E35: =IFERROR(__xludf.DUMMYFUNCTION("""COMPUTED_VALUE"""),"Bio Hidric Kit On-farm") -> Bio Hidric Kit On-farm | F35: =IFERROR(__xludf.DUMMYFUNCTION("""COMPUTED_VALUE"""),"TMG INGÁ I2X 6.9") -> TMG INGÁ I2X 6.9 | J35: =IFERROR(__xludf.DUMMYFUNCTION("""COMPUTED_VALUE"""),"NHT ZINCO") -> NHT ZINCO
A36: =IFERROR(__xludf.DUMMYFUNCTION("""COMPUTED_VALUE"""),"PROTECTION NORTOX") -> PROTECTION NORTOX | B36: =IFERROR(__xludf.DUMMYFUNCTION("""COMPUTED_VALUE"""),"AURORA 400 EC") -> AURORA 400 EC | C36: =IFERROR(__xludf.DUMMYFUNCTION("""COMPUTED_VALUE"""),"TALSTAR 400") -> TALSTAR 400 | E36: =IFERROR(__xludf.DUMMYFUNCTION("""COMPUTED_VALUE"""),"Bio Bokashi Kit On-farm") -> Bio Bokashi Kit On-farm | F36: =IFERROR(__xludf.DUMMYFUNCTION("""COMPUTED_VALUE"""),"TMG 2383 IPRO 8.3") -> TMG 2383 IPRO 8.3 | J36: =IFERROR(__xludf.DUMMYFUNCTION("""COMPUTED_VALUE"""),"KELLUS CUPPER") -> KELLUS CUPPER
A37: =IFERROR(__xludf.DUMMYFUNCTION("""COMPUTED_VALUE"""),"TEBUCO 430 SC NORTOX") -> TEBUCO 430 SC NORTOX | B37: =IFERROR(__xludf.DUMMYFUNCTION("""COMPUTED_VALUE"""),"AZUGRO") -> AZUGRO | C37: =IFERROR(__xludf.DUMMYFUNCTION("""COMPUTED_VALUE"""),"VERIMARK") -> VERIMARK | E37: =IFERROR(__xludf.DUMMYFUNCTION("""COMPUTED_VALUE"""),"Tec White Kit On-farm") -> Tec White Kit On-farm | F37: =IFERROR(__xludf.DUMMYFUNCTION("""COMPUTED_VALUE"""),"BRACHIARIA BASICA") -> BRACHIARIA BASICA | J37: =IFERROR(__xludf.DUMMYFUNCTION("""COMPUTED_VALUE"""),"MOLIBIDENIO 16") -> MOLIBIDENIO 16
A38: =IFERROR(__xludf.DUMMYFUNCTION("""COMPUTED_VALUE"""),"TEBUCO A NORTOX") -> TEBUCO A NORTOX | B38: =IFERROR(__xludf.DUMMYFUNCTION("""COMPUTED_VALUE"""),"BORAL") -> BORAL | C38: =IFERROR(__xludf.DUMMYFUNCTION("""COMPUTED_VALUE"""),"ABAMECTIN 72 EC NORTOX") -> ABAMECTIN 72 EC NORTOX | E38: =IFERROR(__xludf.DUMMYFUNCTION("""COMPUTED_VALUE"""),"Bio Solubilize Kit On-farm") -> Bio Solubilize Kit On-farm | F38: =IFERROR(__xludf.DUMMYFUNCTION("""COMPUTED_VALUE"""),"GH 2478 IPRO 8.1") -> GH 2478 IPRO 8.1 | J38: =IFERROR(__xludf.DUMMYFUNCTION("""COMPUTED_VALUE"""),"ZINCO 10") -> ZINCO 10
A39: =IFERROR(__xludf.DUMMYFUNCTION("""COMPUTED_VALUE"""),"TIOFANATO NORTOX") -> TIOFANATO NORTOX | B39: =IFERROR(__xludf.DUMMYFUNCTION("""COMPUTED_VALUE"""),"REATOR 360 CS") -> REATOR 360 CS | C39: =IFERROR(__xludf.DUMMYFUNCTION("""COMPUTED_VALUE"""),"CIPERMETRINA NORTOX") -> CIPERMETRINA NORTOX | E39: =IFERROR(__xludf.DUMMYFUNCTION("""COMPUTED_VALUE"""),"Bio Release Kit On-farm") -> Bio Release Kit On-farm | F39: =IFERROR(__xludf.DUMMYFUNCTION("""COMPUTED_VALUE"""),"HO COCARI I2X 8.2") -> HO COCARI I2X 8.2 | J39: =IFERROR(__xludf.DUMMYFUNCTION("""COMPUTED_VALUE"""),"Potenza NiCoMo") -> Potenza NiCoMo
A40: =IFERROR(__xludf.DUMMYFUNCTION("""COMPUTED_VALUE"""),"ACADEMIC") -> ACADEMIC | B40: =IFERROR(__xludf.DUMMYFUNCTION("""COMPUTED_VALUE"""),"STONE") -> STONE | C40: =IFERROR(__xludf.DUMMYFUNCTION("""COMPUTED_VALUE"""),"CLORANTRANILIPROLE NORTOX 400 SC") -> CLORANTRANILIPROLE NORTOX 400 SC | E40: =IFERROR(__xludf.DUMMYFUNCTION("""COMPUTED_VALUE"""),"Bio Raiz Plus Kit On-farm") -> Bio Raiz Plus Kit On-farm | F40: =IFERROR(__xludf.DUMMYFUNCTION("""COMPUTED_VALUE"""),"SEMENTE DE SORGO") -> SEMENTE DE SORGO
A41: =IFERROR(__xludf.DUMMYFUNCTION("""COMPUTED_VALUE"""),"BRISA WG") -> BRISA WG | B41: =IFERROR(__xludf.DUMMYFUNCTION("""COMPUTED_VALUE"""),"ARKEIRO NORTOX") -> ARKEIRO NORTOX | C41: =IFERROR(__xludf.DUMMYFUNCTION("""COMPUTED_VALUE"""),"CLORFENAPIR NORTOX") -> CLORFENAPIR NORTOX | E41: =IFERROR(__xludf.DUMMYFUNCTION("""COMPUTED_VALUE"""),"Bio Balance Kit On-farm") -> Bio Balance Kit On-farm
A42: =IFERROR(__xludf.DUMMYFUNCTION("""COMPUTED_VALUE"""),"CUPROZEB") -> CUPROZEB | B42: =IFERROR(__xludf.DUMMYFUNCTION("""COMPUTED_VALUE"""),"CLETODIM OLEUM NORTOX") -> CLETODIM OLEUM NORTOX | C42: =IFERROR(__xludf.DUMMYFUNCTION("""COMPUTED_VALUE"""),"CLORPIRIFÓS NORTOX EC") -> CLORPIRIFÓS NORTOX EC | E42: =IFERROR(__xludf.DUMMYFUNCTION("""COMPUTED_VALUE"""),"SoluBio Raiz Performance Kit On-farm,") -> SoluBio Raiz Performance Kit On-farm,
A43: =IFERROR(__xludf.DUMMYFUNCTION("""COMPUTED_VALUE"""),"SUPPORT WG") -> SUPPORT WG | B43: =IFERROR(__xludf.DUMMYFUNCTION("""COMPUTED_VALUE"""),"CLORIMUROM MAX NORTOX") -> CLORIMUROM MAX NORTOX | C43: =IFERROR(__xludf.DUMMYFUNCTION("""COMPUTED_VALUE"""),"DIAFENTIURON NORTOX") -> DIAFENTIURON NORTOX | E43: =IFERROR(__xludf.DUMMYFUNCTION("""COMPUTED_VALUE"""),"Tec Isaria Kit On-farm") -> Tec Isaria Kit On-farm
A44: =IFERROR(__xludf.DUMMYFUNCTION("""COMPUTED_VALUE"""),"VITENE") -> VITENE | B44: =IFERROR(__xludf.DUMMYFUNCTION("""COMPUTED_VALUE"""),"FLUROXIPIR NORTOX") -> FLUROXIPIR NORTOX | C44: =IFERROR(__xludf.DUMMYFUNCTION("""COMPUTED_VALUE"""),"IMIDACLOPRID NORTOX 480 SC") -> IMIDACLOPRID NORTOX 480 SC
A45: =IFERROR(__xludf.DUMMYFUNCTION("""COMPUTED_VALUE"""),"CARTAP BR 500") -> CARTAP BR 500 | B45: =IFERROR(__xludf.DUMMYFUNCTION("""COMPUTED_VALUE"""),"GLUFOSINATO NORTOX 880 SG") -> GLUFOSINATO NORTOX 880 SG | C45: =IFERROR(__xludf.DUMMYFUNCTION("""COMPUTED_VALUE"""),"METOMIL 215 SL NORTOX") -> METOMIL 215 SL NORTOX
A46: =IFERROR(__xludf.DUMMYFUNCTION("""COMPUTED_VALUE"""),"CURADO") -> CURADO | B46: =IFERROR(__xludf.DUMMYFUNCTION("""COMPUTED_VALUE"""),"IMAZETAPIR NORTOX") -> IMAZETAPIR NORTOX | C46: =IFERROR(__xludf.DUMMYFUNCTION("""COMPUTED_VALUE"""),"PIRIPROXIFEN NORTOX") -> PIRIPROXIFEN NORTOX
A47: =IFERROR(__xludf.DUMMYFUNCTION("""COMPUTED_VALUE"""),"EXCALIA MAX") -> EXCALIA MAX | B47: =IFERROR(__xludf.DUMMYFUNCTION("""COMPUTED_VALUE"""),"MESOTRIONA NORTOX") -> MESOTRIONA NORTOX | C47: =IFERROR(__xludf.DUMMYFUNCTION("""COMPUTED_VALUE"""),"TEMPUS NORTOX") -> TEMPUS NORTOX
A48: =IFERROR(__xludf.DUMMYFUNCTION("""COMPUTED_VALUE"""),"PLADIUS") -> PLADIUS | B48: =IFERROR(__xludf.DUMMYFUNCTION("""COMPUTED_VALUE"""),"TRIFLURALINA NORTOX GOLD") -> TRIFLURALINA NORTOX GOLD | C48: =IFERROR(__xludf.DUMMYFUNCTION("""COMPUTED_VALUE"""),"TYPHOON NORTOX") -> TYPHOON NORTOX
A49: =IFERROR(__xludf.DUMMYFUNCTION("""COMPUTED_VALUE"""),"SIALEX 500") -> SIALEX 500 | B49: =IFERROR(__xludf.DUMMYFUNCTION("""COMPUTED_VALUE"""),"CLICK") -> CLICK | C49: =IFERROR(__xludf.DUMMYFUNCTION("""COMPUTED_VALUE"""),"ABADAY") -> ABADAY
A50: =IFERROR(__xludf.DUMMYFUNCTION("""COMPUTED_VALUE"""),"TAMIZ") -> TAMIZ | B50: =IFERROR(__xludf.DUMMYFUNCTION("""COMPUTED_VALUE"""),"VOLCANE") -> VOLCANE | C50: =IFERROR(__xludf.DUMMYFUNCTION("""COMPUTED_VALUE"""),"CARNADINE") -> CARNADINE
A51: =IFERROR(__xludf.DUMMYFUNCTION("""COMPUTED_VALUE"""),"TROIA") -> TROIA | B51: =IFERROR(__xludf.DUMMYFUNCTION("""COMPUTED_VALUE"""),"CRUCIAL") -> CRUCIAL | C51: =IFERROR(__xludf.DUMMYFUNCTION("""COMPUTED_VALUE"""),"CARTAP BR 500") -> CARTAP BR 500
A52: =IFERROR(__xludf.DUMMYFUNCTION("""COMPUTED_VALUE"""),"ALADE") -> ALADE | B52: =IFERROR(__xludf.DUMMYFUNCTION("""COMPUTED_VALUE"""),"SUMYZIN 500 SC") -> SUMYZIN 500 SC | C52: =IFERROR(__xludf.DUMMYFUNCTION("""COMPUTED_VALUE"""),"INSIDE FS") -> INSIDE FS
A53: =IFERROR(__xludf.DUMMYFUNCTION("""COMPUTED_VALUE"""),"AMISTAR TOP") -> AMISTAR TOP | B53: =IFERROR(__xludf.DUMMYFUNCTION("""COMPUTED_VALUE"""),"U 46 BR") -> U 46 BR | C53: =IFERROR(__xludf.DUMMYFUNCTION("""COMPUTED_VALUE"""),"KAISO MAX") -> KAISO MAX
A54: =IFERROR(__xludf.DUMMYFUNCTION("""COMPUTED_VALUE"""),"AUGE") -> AUGE | B54: =IFERROR(__xludf.DUMMYFUNCTION("""COMPUTED_VALUE"""),"ZETHAMAXX") -> ZETHAMAXX | C54: =IFERROR(__xludf.DUMMYFUNCTION("""COMPUTED_VALUE"""),"KLORPAN 480 EC") -> KLORPAN 480 EC
A55: =IFERROR(__xludf.DUMMYFUNCTION("""COMPUTED_VALUE"""),"BRAVONIL 720") -> BRAVONIL 720 | B55: =IFERROR(__xludf.DUMMYFUNCTION("""COMPUTED_VALUE"""),"ZETHAMAXX EVO") -> ZETHAMAXX EVO | C55: =IFERROR(__xludf.DUMMYFUNCTION("""COMPUTED_VALUE"""),"LEGION") -> LEGION
A56: =IFERROR(__xludf.DUMMYFUNCTION("""COMPUTED_VALUE"""),"BRAVONIL TOP") -> BRAVONIL TOP | B56: =IFERROR(__xludf.DUMMYFUNCTION("""COMPUTED_VALUE"""),"CALARIS") -> CALARIS | C56: =IFERROR(__xludf.DUMMYFUNCTION("""COMPUTED_VALUE"""),"OPTERADUO") -> OPTERADUO
A57: =IFERROR(__xludf.DUMMYFUNCTION("""COMPUTED_VALUE"""),"CYPRESS 400 EC") -> CYPRESS 400 EC | B57: =IFERROR(__xludf.DUMMYFUNCTION("""COMPUTED_VALUE"""),"DUAL GOLD") -> DUAL GOLD | C57: =IFERROR(__xludf.DUMMYFUNCTION("""COMPUTED_VALUE"""),"SUMIRODY") -> SUMIRODY
A58: =IFERROR(__xludf.DUMMYFUNCTION("""COMPUTED_VALUE"""),"ELATUS") -> ELATUS | B58: =IFERROR(__xludf.DUMMYFUNCTION("""COMPUTED_VALUE"""),"EDDUS") -> EDDUS | C58: =IFERROR(__xludf.DUMMYFUNCTION("""COMPUTED_VALUE"""),"XENTARI") -> XENTARI
A59: =IFERROR(__xludf.DUMMYFUNCTION("""COMPUTED_VALUE"""),"MERTIN 400") -> MERTIN 400 | B59: =IFERROR(__xludf.DUMMYFUNCTION("""COMPUTED_VALUE"""),"FLEX") -> FLEX | C59: =IFERROR(__xludf.DUMMYFUNCTION("""COMPUTED_VALUE"""),"ACTARA 250 WG") -> ACTARA 250 WG
A60: =IFERROR(__xludf.DUMMYFUNCTION("""COMPUTED_VALUE"""),"MIRAVIS") -> MIRAVIS | B60: =IFERROR(__xludf.DUMMYFUNCTION("""COMPUTED_VALUE"""),"FUSILADE") -> FUSILADE | C60: =IFERROR(__xludf.DUMMYFUNCTION("""COMPUTED_VALUE"""),"AMPLIGO") -> AMPLIGO
A61: =IFERROR(__xludf.DUMMYFUNCTION("""COMPUTED_VALUE"""),"MIRAVIS DUO") -> MIRAVIS DUO | B61: =IFERROR(__xludf.DUMMYFUNCTION("""COMPUTED_VALUE"""),"GESAPRIM GRDA") -> GESAPRIM GRDA | C61: =IFERROR(__xludf.DUMMYFUNCTION("""COMPUTED_VALUE"""),"CURYOM 550 EC") -> CURYOM 550 EC
A62: =IFERROR(__xludf.DUMMYFUNCTION("""COMPUTED_VALUE"""),"MIRAVIS PRO") -> MIRAVIS PRO | B62: =IFERROR(__xludf.DUMMYFUNCTION("""COMPUTED_VALUE"""),"PRIMESTRA GOLD") -> PRIMESTRA GOLD | C62: =IFERROR(__xludf.DUMMYFUNCTION("""COMPUTED_VALUE"""),"ELESTAL NEO") -> ELESTAL NEO
A63: =IFERROR(__xludf.DUMMYFUNCTION("""COMPUTED_VALUE"""),"MITRION EC") -> MITRION EC | B63: =IFERROR(__xludf.DUMMYFUNCTION("""COMPUTED_VALUE"""),"PROOF") -> PROOF | C63: =IFERROR(__xludf.DUMMYFUNCTION("""COMPUTED_VALUE"""),"ENGEO PLENO S") -> ENGEO PLENO S
A64: =IFERROR(__xludf.DUMMYFUNCTION("""COMPUTED_VALUE"""),"PRIORI TOP") -> PRIORI TOP | B64: =IFERROR(__xludf.DUMMYFUNCTION("""COMPUTED_VALUE"""),"REGLONE") -> REGLONE | C64: =IFERROR(__xludf.DUMMYFUNCTION("""COMPUTED_VALUE"""),"KARATE ZEON 250 CS") -> KARATE ZEON 250 CS
A65: =IFERROR(__xludf.DUMMYFUNCTION("""COMPUTED_VALUE"""),"RIDOMIL GOLD BRAVO") -> RIDOMIL GOLD BRAVO | B65: =IFERROR(__xludf.DUMMYFUNCTION("""COMPUTED_VALUE"""),"TOPIK 240 EC") -> TOPIK 240 EC | C65: =IFERROR(__xludf.DUMMYFUNCTION("""COMPUTED_VALUE"""),"MINECTO PRO") -> MINECTO PRO
A66: =IFERROR(__xludf.DUMMYFUNCTION("""COMPUTED_VALUE"""),"SCORE FLEXI®") -> SCORE FLEXI® | B66: =IFERROR(__xludf.DUMMYFUNCTION("""COMPUTED_VALUE"""),"ZAPP QI 620") -> ZAPP QI 620 | C66: =IFERROR(__xludf.DUMMYFUNCTION("""COMPUTED_VALUE"""),"POLO 500 SC") -> POLO 500 SC
A67: =IFERROR(__xludf.DUMMYFUNCTION("""COMPUTED_VALUE"""),"SEEKER") -> SEEKER | B67: =IFERROR(__xludf.DUMMYFUNCTION("""COMPUTED_VALUE"""),"MINOS CAPS 360 CS") -> MINOS CAPS 360 CS | C67: =IFERROR(__xludf.DUMMYFUNCTION("""COMPUTED_VALUE"""),"POLYTRIN") -> POLYTRIN
C68: =IFERROR(__xludf.DUMMYFUNCTION("""COMPUTED_VALUE"""),"PROCLAIM 50") -> PROCLAIM 50
C69: =IFERROR(__xludf.DUMMYFUNCTION("""COMPUTED_VALUE"""),"SPONTA") -> SPONTA
C70: =IFERROR(__xludf.DUMMYFUNCTION("""COMPUTED_VALUE"""),"VERDAVIS") -> VERDAVIS
C71: =IFERROR(__xludf.DUMMYFUNCTION("""COMPUTED_VALUE"""),"VERTIMEC 84 SC") -> VERTIMEC 84 SC

Sheet CUSTO OPERAÇÃO
A1: Column 11 | B1: MÁQUINA | C1: IMPLEMENTO | D1: CONJUNTO | E1: LARGURA | F1: VELOCIDADE | G1: EFICIÊNCIA | H1: ha/h | I1: L/h | J1: HM/ha | K1: L/ha | L1: CUSTO HM/HA | M1: HORA MAQ./HA | O1: GRUPO | P1: MAQUINA | Q1: CONSUMO HORA | R1: LARGURA OPERAÇÃO | S1: VELOCIDADE
A2: MÁQUINAS | B2: TRATOR - CASE STEIGER 420 | C2: PLANTADEIRA HORSCH MAESTRO DUO 36.50 | D2: =IFERROR(__xludf.DUMMYFUNCTION("REGEXREPLACE(B2,""TRATOR - |COLHEITADEIRA |PULVERIZADOR |CAMINHAO-"","""")&"" + ""&REGEXREPLACE(C2,""PLANTADEIRA |PLATAFORMA |DISTRIBUIDOR |PULVERIZADOR "", """")"),"CASE STEIGER 420 + HORSCH MAESTRO DUO 36.50") -> CASE STEIGER 420 + HORSCH MAESTRO DUO 36.50 | E2: =VLOOKUP(C2,'CUSTO OPERAÇÃO'!$P$1:$S$125,3,0) -> 18 | F2: =VLOOKUP(C2,'CUSTO OPERAÇÃO'!$P$1:$S$125,4,0) -> 8 | G2: 85 | H2: =(E2*F2*(G2/100))/10 -> 12.24 | I2: =VLOOKUP(B2,'CUSTO OPERAÇÃO'!$P$1:$Q$125,2,0) -> 60 | J2: =1/H2 -> 0.081699346 | K2: =I2/H2 -> 4.9019608 | L2: =K2*7.5 -> 36.764706 | M2: =IFERROR(L2/J2,"") -> 450 | O2: AVIÃO AGRICOLA | P2: AIR TRATOR AT-502B | Q2: 120 | R2: 30 | S2: 200
A3: MÁQUINAS | B3: TRATOR - CASE MAGNUM 340 | C3: PLANTADEIRA - CASE ASM 1213 | D3: =IFERROR(__xludf.DUMMYFUNCTION("REGEXREPLACE(B3,""TRATOR - |COLHEITADEIRA |PULVERIZADOR |CAMINHAO-"","""")&"" + ""&REGEXREPLACE(C3,""PLANTADEIRA |PLATAFORMA |DISTRIBUIDOR |PULVERIZADOR "", """")"),"CASE MAGNUM 340 + - CASE ASM 1213") -> CASE MAGNUM 340 + - CASE ASM 1213 | E3: =VLOOKUP(C3,'CUSTO OPERAÇÃO'!$P$1:$S$125,3,0) -> 13 | F3: =VLOOKUP(C3,'CUSTO OPERAÇÃO'!$P$1:$S$125,4,0) -> 7 | G3: 85 | H3: =(E3*F3*(G3/100))/10 -> 7.735 | I3: =VLOOKUP(B3,'CUSTO OPERAÇÃO'!$P$1:$Q$125,2,0) -> 40 | J3: =1/H3 -> 0.12928248 | K3: =I3/H3 -> 5.1712993 | L3: =K3*7.5 -> 38.784745 | M3: =IFERROR(L3/J3,"") -> 300
A4: MÁQUINAS | B4: COLHEITADEIRA CR 8.90 NEW HOLLAND | C4: PLATAFORMA 880 CF45 | D4: =IFERROR(__xludf.DUMMYFUNCTION("REGEXREPLACE(B4,""TRATOR - |COLHEITADEIRA |PULVERIZADOR |CAMINHAO-"","""")&"" + ""&REGEXREPLACE(C4,""PLANTADEIRA |PLATAFORMA |DISTRIBUIDOR |PULVERIZADOR "", """")"),"CR 8.90 NEW HOLLAND + 880 CF45") -> CR 8.90 NEW HOLLAND + 880 CF45 | E4: =VLOOKUP(C4,'CUSTO OPERAÇÃO'!$P$1:$S$125,3,0) -> 13 | F4: =VLOOKUP(C4,'CUSTO OPERAÇÃO'!$P$1:$S$125,4,0) -> 6 | G4: 85 | H4: =(E4*F4*(G4/100))/10 -> 6.63 | I4: =VLOOKUP(B4,'CUSTO OPERAÇÃO'!$P$1:$Q$125,2,0) -> 50 | J4: =1/H4 -> 0.15082956 | K4: =I4/H4 -> 7.5414781 | L4: =K4*7.5 -> 56.561086 | M4: =IFERROR(L4/J4,"") -> 375
A5: MÁQUINAS | B5: COLHETADEIRA - NH-CR9060 | C5: PLATAFORMA 740 CF30 AGRIDREPER | D5: =IFERROR(__xludf.DUMMYFUNCTION("REGEXREPLACE(B5,""TRATOR - |COLHEITADEIRA |PULVERIZADOR |CAMINHAO-"","""")&"" + ""&REGEXREPLACE(C5,""PLANTADEIRA |PLATAFORMA |DISTRIBUIDOR |PULVERIZADOR "", """")"),"COLHETADEIRA - NH-CR9060 + 740 CF30 AGRIDREPER") -> COLHETADEIRA - NH-CR9060 + 740 CF30 AGRIDREPER | E5: =VLOOKUP(C5,'CUSTO OPERAÇÃO'!$P$1:$S$125,3,0) -> 9 | F5: =VLOOKUP(C5,'CUSTO OPERAÇÃO'!$P$1:$S$125,4,0) -> 6 | G5: 85 | H5: =(E5*F5*(G5/100))/10 -> 4.59 | I5: =VLOOKUP(B5,'CUSTO OPERAÇÃO'!$P$1:$Q$125,2,0) -> 40 | J5: =1/H5 -> 0.21786492 | K5: =I5/H5 -> 8.714597 | L5: =K5*7.5 -> 65.359477 | M5: =IFERROR(L5/J5,"") -> 300 | O5: CAMINHÕES | P5: CAMINHAO-VOLVO VM260 | Q5: 20 | R5: 1 | S5: 40
A6: MÁQUINAS | B6: COLHETADEIRA CR7.80 | C6: PLATAFORMA MACDON 35F | D6: =IFERROR(__xludf.DUMMYFUNCTION("REGEXREPLACE(B6,""TRATOR - |COLHEITADEIRA |PULVERIZADOR |CAMINHAO-"","""")&"" + ""&REGEXREPLACE(C6,""PLANTADEIRA |PLATAFORMA |DISTRIBUIDOR |PULVERIZADOR "", """")"),"COLHETADEIRA CR7.80 + MACDON 35F") -> COLHETADEIRA CR7.80 + MACDON 35F | E6: =VLOOKUP(C6,'CUSTO OPERAÇÃO'!$P$1:$S$125,3,0) -> 9 | F6: =VLOOKUP(C6,'CUSTO OPERAÇÃO'!$P$1:$S$125,4,0) -> 6 | G6: 85 | H6: =(E6*F6*(G6/100))/10 -> 4.59 | I6: =VLOOKUP(B6,'CUSTO OPERAÇÃO'!$P$1:$Q$125,2,0) -> 40 | J6: =1/H6 -> 0.21786492 | K6: =I6/H6 -> 8.714597 | L6: =K6*7.5 -> 65.359477 | M6: =IFERROR(L6/J6,"") -> 300 | O6: CAMINHÕES | P6: CAMINHAO-VOLVO NH380 | Q6: 20
A7: MÁQUINAS | B7: TRATOR-JD 7500 | C7: DISTRIBUIDOR BRUTUS 12000 | D7: =IFERROR(__xludf.DUMMYFUNCTION("REGEXREPLACE(B7,""TRATOR - |COLHEITADEIRA |PULVERIZADOR |CAMINHAO-"","""")&"" + ""&REGEXREPLACE(C7,""PLANTADEIRA |PLATAFORMA |DISTRIBUIDOR |PULVERIZADOR "", """")"),"TRATOR-JD 7500 + BRUTUS 12000") -> TRATOR-JD 7500 + BRUTUS 12000 | E7: =VLOOKUP(C7,'CUSTO OPERAÇÃO'!$P$1:$S$125,3,0) -> 6 | F7: =VLOOKUP(C7,'CUSTO OPERAÇÃO'!$P$1:$S$125,4,0) -> 6 | G7: 85 | H7: =(E7*F7*(G7/100))/10 -> 3.06 | I7: =VLOOKUP(B7,'CUSTO OPERAÇÃO'!$P$1:$Q$125,2,0) -> 15 | J7: =1/H7 -> 0.32679739 | K7: =I7/H7 -> 4.9019608 | L7: =K7*7.5 -> 36.764706 | M7: =IFERROR(L7/J7,"") -> 112.5 | O7: CAMINHÕES | P7: CAMINHAO-WV 7.100 | Q7: 20
A8: MÁQUINAS | B8: TRATOR-JD 7500 | C8: DISTRIBUIDOR ADUBADORA HERCULES 10000 | D8: =IFERROR(__xludf.DUMMYFUNCTION("REGEXREPLACE(B8,""TRATOR - |COLHEITADEIRA |PULVERIZADOR |CAMINHAO-"","""")&"" + ""&REGEXREPLACE(C8,""PLANTADEIRA |PLATAFORMA |DISTRIBUIDOR |PULVERIZADOR "", """")"),"TRATOR-JD 7500 + ADUBADORA HERCULES 10000") -> TRATOR-JD 7500 + ADUBADORA HERCULES 10000 | E8: =VLOOKUP(C8,'CUSTO OPERAÇÃO'!$P$1:$S$125,3,0) -> 30 | F8: =VLOOKUP(C8,'CUSTO OPERAÇÃO'!$P$1:$S$125,4,0) -> 8 | G8: 85 | H8: =(E8*F8*(G8/100))/10 -> 20.4 | I8: =VLOOKUP(B8,'CUSTO OPERAÇÃO'!$P$1:$Q$125,2,0) -> 15 | J8: =1/H8 -> 0.049019608 | K8: =I8/H8 -> 0.73529412 | L8: =K8*7.5 -> 5.5147059 | M8: =IFERROR(L8/J8,"") -> 112.5 | O8: CAMINHÕES | P8: CAMINHAO-MB 1313 | Q8: 20
A9: MÁQUINAS | B9: CAMINHAO-VOLVO NH380 | C9: CAÇAMBA 430SC | D9: =IFERROR(__xludf.DUMMYFUNCTION("REGEXREPLACE(B9,""TRATOR - |COLHEITADEIRA |PULVERIZADOR |CAMINHAO-"","""")&"" + ""&REGEXREPLACE(C9,""PLANTADEIRA |PLATAFORMA |DISTRIBUIDOR |PULVERIZADOR "", """")"),"VOLVO NH380 + CAÇAMBA 430SC") -> VOLVO NH380 + CAÇAMBA 430SC | E9: 430 | F9: =VLOOKUP(C9,'CUSTO OPERAÇÃO'!$P$1:$S$125,4,0) -> 20 | G9: 85 | H9: =(E9*F9*(G9/100))/10 -> 731 | I9: =VLOOKUP(B9,'CUSTO OPERAÇÃO'!$P$1:$Q$125,2,0) -> 20 | J9: =1/H9 -> 0.0013679891 | K9: =I9/H9 -> 0.027359781 | L9: =K9*7.5 -> 0.20519836 | M9: =IFERROR(L9/J9,"") -> 150 | O9: CAMINHÕES | P9: CAMINHÃO MB 1620 | Q9: 20
A10: MÁQUINAS | B10: TRATOR - CASE MAGNUM 340 | C10: SUBSOLADOR 11 ASTES | D10: =IFERROR(__xludf.DUMMYFUNCTION("REGEXREPLACE(B10,""TRATOR - |COLHEITADEIRA |PULVERIZADOR |CAMINHAO-"","""")&"" + ""&REGEXREPLACE(C10,""PLANTADEIRA |PLATAFORMA |DISTRIBUIDOR |PULVERIZADOR "", """")"),"CASE MAGNUM 340 + SUBSOLADOR 11 ASTES") -> CASE MAGNUM 340 + SUBSOLADOR 11 ASTES | E10: =VLOOKUP(C10,'CUSTO OPERAÇÃO'!$P$1:$S$125,3,0) -> 5.5 | F10: 4.5 | G10: 85 | H10: =(E10*F10*(G10/100))/10 -> 2.10375 | I10: =VLOOKUP(B10,'CUSTO OPERAÇÃO'!$P$1:$Q$125,2,0) -> 40 | J10: =1/H10 -> 0.47534165 | K10: =I10/H10 -> 19.013666 | L10: =K10*7.5 -> 142.6025 | M10: =IFERROR(L10/J10,"") -> 300 | O10: CARRETA AGRÍCOLA | P10: CAÇAMBA 430SC | R10: 400 | S10: 20
A11: MÁQUINAS | B11: PULVERIZADOR- JD4730 | C11: PULVERIZADOR- JD4730 | D11: =IFERROR(__xludf.DUMMYFUNCTION("REGEXREPLACE(B11,""TRATOR - |COLHEITADEIRA |PULVERIZADOR |CAMINHAO-"","""")&"" + ""&REGEXREPLACE(C11,""PLANTADEIRA |PLATAFORMA |DISTRIBUIDOR |PULVERIZADOR "", """")"),"PULVERIZADOR- JD4730 + PULVERIZADOR- JD4730") -> PULVERIZADOR- JD4730 + PULVERIZADOR- JD4730 | E11: =VLOOKUP(C11,'CUSTO OPERAÇÃO'!$P$1:$S$125,3,0) -> 30 | F11: =VLOOKUP(C11,'CUSTO OPERAÇÃO'!$P$1:$S$125,4,0) -> 20 | G11: 85 | H11: =(E11*F11*(G11/100))/10 -> 51 | I11: =VLOOKUP(B11,'CUSTO OPERAÇÃO'!$P$1:$Q$125,2,0) -> 17 | J11: =1/H11 -> 0.019607843 | K11: =I11/H11 -> 0.33333333 | L11: =K11*7.5 -> 2.5 | M11: =IFERROR(L11/J11,"") -> 127.5
A12: MÁQUINAS | B12: AIR TRATOR AT-502B | C12: AIR TRATOR AT-502B | D12: =IFERROR(__xludf.DUMMYFUNCTION("REGEXREPLACE(B12,""TRATOR - |COLHEITADEIRA |PULVERIZADOR |CAMINHAO-"","""")&"" + ""&REGEXREPLACE(C12,""PLANTADEIRA |PLATAFORMA |DISTRIBUIDOR |PULVERIZADOR "", """")"),"AIR TRATOR AT-502B + AIR TRATOR AT-502B") -> AIR TRATOR AT-502B + AIR TRATOR AT-502B | E12: =VLOOKUP(C12,'CUSTO OPERAÇÃO'!$P$1:$S$125,3,0) -> 30 | F12: =VLOOKUP(C12,'CUSTO OPERAÇÃO'!$P$1:$S$125,4,0) -> 200 | G12: 25 | H12: =(E12*F12*(G12/100))/10 -> 150 | I12: 135 | J12: =1/H12 -> 0.0066666667 | K12: =I12/H12 -> 0.9 | L12: =K12*7.5 -> 6.75 | M12: 5000 | O12: CAMINHÕES | P12: CAMINHÃO-VOLVO FH 540 | Q12: 20
A13: MÁQUINAS | B13: COLHETADEIRA - NH-CR9060 | C13: PLATAFORMA MILHO BRAVA 11 | D13: =IFERROR(__xludf.DUMMYFUNCTION("REGEXREPLACE(B13,""TRATOR - |COLHEITADEIRA |PULVERIZADOR |CAMINHAO-"","""")&"" + ""&REGEXREPLACE(C13,""PLANTADEIRA |PLATAFORMA |DISTRIBUIDOR |PULVERIZADOR "", """")"),"COLHETADEIRA - NH-CR9060 + MILHO BRAVA 11") -> COLHETADEIRA - NH-CR9060 + MILHO BRAVA 11 | E13: =VLOOKUP(C13,'CUSTO OPERAÇÃO'!$P$1:$S$125,3,0) -> 5.5 | F13: =VLOOKUP(C13,'CUSTO OPERAÇÃO'!$P$1:$S$125,4,0) -> 10 | G13: 85 | H13: =(E13*F13*(G13/100))/10 -> 4.675 | I13: =VLOOKUP(B13,'CUSTO OPERAÇÃO'!$P$1:$Q$125,2,0) -> 40 | J13: =1/H13 -> 0.21390374 | K13: =I13/H13 -> 8.5561497 | L13: =K13*7.5 -> 64.171123 | M13: =IFERROR(L13/J13,"") -> 300 | O13: CARRETA AGRÍCOLA | P13: TRANSBORDO SANTAL
A14: MÁQUINAS | B14: TRATOR - NH T7.260 | C14: DISTRIBUIDOR JAN 20000 | D14: =IFERROR(__xludf.DUMMYFUNCTION("REGEXREPLACE(B14,""TRATOR - |COLHEITADEIRA |PULVERIZADOR |CAMINHAO-"","""")&"" + ""&REGEXREPLACE(C14,""PLANTADEIRA |PLATAFORMA |DISTRIBUIDOR |PULVERIZADOR "", """")"),"NH T7.260 + JAN 20000") -> NH T7.260 + JAN 20000 | E14: =VLOOKUP(C14,'CUSTO OPERAÇÃO'!$P$1:$S$125,3,0) -> 15 | F14: =VLOOKUP(C14,'CUSTO OPERAÇÃO'!$P$1:$S$125,4,0) -> 8 | G14: 85 | H14: =(E14*F14*(G14/100))/10 -> 10.2 | I14: =VLOOKUP(B14,'CUSTO OPERAÇÃO'!$P$1:$Q$125,2,0) -> 25 | J14: =1/H14 -> 0.098039216 | K14: =I14/H14 -> 2.4509804 | L14: =K14*7.5 -> 18.382353 | M14: =IFERROR(L14/J14,"") -> 187.5 | O14: CARRETA AGRÍCOLA | P14: REBOQUE 3000 KG- FA
A15: MÁQUINAS | B15: TRATOR - NH T8.355 | C15: PLANTADEIRA - JD2122 | D15: =IFERROR(__xludf.DUMMYFUNCTION("REGEXREPLACE(B15,""TRATOR - |COLHEITADEIRA |PULVERIZADOR |CAMINHAO-"","""")&"" + ""&REGEXREPLACE(C15,""PLANTADEIRA |PLATAFORMA |DISTRIBUIDOR |PULVERIZADOR "", """")"),"NH T8.355 + - JD2122") -> NH T8.355 + - JD2122 | E15: =VLOOKUP(C15,'CUSTO OPERAÇÃO'!$P$1:$S$125,3,0) -> 10.5 | F15: =VLOOKUP(C15,'CUSTO OPERAÇÃO'!$P$1:$S$125,4,0) -> 7 | G15: 85 | H15: =(E15*F15*(G15/100))/10 -> 6.2475 | I15: =VLOOKUP(B15,'CUSTO OPERAÇÃO'!$P$1:$Q$125,2,0) -> 30 | J15: =1/H15 -> 0.16006403 | K15: =I15/H15 -> 4.8019208 | L15: =K15*7.5 -> 36.014406 | M15: =IFERROR(L15/J15,"") -> 225 | O15: CARRETA AGRÍCOLA | P15: CARRETO ADUBO 20000
A16: MÁQUINAS | B16: COLHETADEIRA - CASE 2388 | C16: PLATAFORMA CASE 30PES | D16: =IFERROR(__xludf.DUMMYFUNCTION("REGEXREPLACE(B16,""TRATOR - |COLHEITADEIRA |PULVERIZADOR |CAMINHAO-"","""")&"" + ""&REGEXREPLACE(C16,""PLANTADEIRA |PLATAFORMA |DISTRIBUIDOR |PULVERIZADOR "", """")"),"COLHETADEIRA - CASE 2388 + CASE 30PES") -> COLHETADEIRA - CASE 2388 + CASE 30PES | E16: =VLOOKUP(C16,'CUSTO OPERAÇÃO'!$P$1:$S$125,3,0) -> 9 | F16: =VLOOKUP(C16,'CUSTO OPERAÇÃO'!$P$1:$S$125,4,0) -> 5 | G16: 85 | H16: =(E16*F16*(G16/100))/10 -> 3.825 | I16: =VLOOKUP(B16,'CUSTO OPERAÇÃO'!$P$1:$Q$125,2,0) -> 30 | J16: =1/H16 -> 0.26143791 | K16: =I16/H16 -> 7.8431373 | L16: =K16*7.5 -> 58.823529 | M16: =IFERROR(L16/J16,"") -> 225 | O16: CARRETA AGRÍCOLA | P16: CARRETO ADUBO ESPORA
A17: MÁQUINAS | B17: JACTO UNIPORT 2000 | C17: JACTO UNIPORT 2000 | D17: =IFERROR(__xludf.DUMMYFUNCTION("REGEXREPLACE(B17,""TRATOR - |COLHEITADEIRA |PULVERIZADOR |CAMINHAO-"","""")&"" + ""&REGEXREPLACE(C17,""PLANTADEIRA |PLATAFORMA |DISTRIBUIDOR |PULVERIZADOR "", """")"),"JACTO UNIPORT 2000 + JACTO UNIPORT 2000") -> JACTO UNIPORT 2000 + JACTO UNIPORT 2000 | E17: =VLOOKUP(C17,'CUSTO OPERAÇÃO'!$P$1:$S$125,3,0) -> 24 | F17: =VLOOKUP(C17,'CUSTO OPERAÇÃO'!$P$1:$S$125,4,0) -> 16 | G17: 85 | H17: =(E17*F17*(G17/100))/10 -> 32.64 | I17: =VLOOKUP(B17,'CUSTO OPERAÇÃO'!$P$1:$Q$125,2,0) -> 7 | J17: =1/H17 -> 0.030637255 | K17: =I17/H17 -> 0.21446078 | L17: =K17*7.5 -> 1.6084559 | M17: =IFERROR(L17/J17,"") -> 52.5 | O17: CARRETA AGRÍCOLA | P17: CARRETA PLATAFORMACR7.8
A18: MÁQUINAS | B18: TRATOR - NH T7.260 | C18: PLANTADEIRA CASE 2213 | D18: =IFERROR(__xludf.DUMMYFUNCTION("REGEXREPLACE(B18,""TRATOR - |COLHEITADEIRA |PULVERIZADOR |CAMINHAO-"","""")&"" + ""&REGEXREPLACE(C18,""PLANTADEIRA |PLATAFORMA |DISTRIBUIDOR |PULVERIZADOR "", """")"),"NH T7.260 + CASE 2213") -> NH T7.260 + CASE 2213 | E18: =VLOOKUP(C18,'CUSTO OPERAÇÃO'!$P$1:$S$125,3,0) -> 6.5 | F18: =VLOOKUP(C18,'CUSTO OPERAÇÃO'!$P$1:$S$125,4,0) -> 7 | G18: 85 | H18: =(E18*F18*(G18/100))/10 -> 3.8675 | I18: =VLOOKUP(B18,'CUSTO OPERAÇÃO'!$P$1:$Q$125,2,0) -> 25 | J18: =1/H18 -> 0.25856496 | K18: =I18/H18 -> 6.4641241 | L18: =K18*7.5 -> 48.480931 | M18: =IFERROR(L18/J18,"") -> 187.5 | O18: COLHEDORAS | P18: COLHETADEIRA - NH-CR9060 | Q18: 40
D19: =IFERROR(__xludf.DUMMYFUNCTION("REGEXREPLACE(B19,""TRATOR - |COLHEITADEIRA |PULVERIZADOR |CAMINHAO-"","""")&"" + ""&REGEXREPLACE(C19,""PLANTADEIRA |PLATAFORMA |DISTRIBUIDOR |PULVERIZADOR "", """")")," + ") -> + | E19: =VLOOKUP(C19,'CUSTO OPERAÇÃO'!$P$1:$S$125,3,0) -> #N/A | F19: =VLOOKUP(C19,'CUSTO OPERAÇÃO'!$P$1:$S$125,4,0) -> #N/A | G19: 85 | H19: =(E19*F19*(G19/100))/10 -> #N/A | I19: =VLOOKUP(B19,'CUSTO OPERAÇÃO'!$P$1:$Q$125,2,0) -> #N/A | J19: =1/H19 -> #N/A | K19: =I19/H19 -> #N/A | L19: =K19*7.5 -> #N/A | M19: =IFERROR(L19/J19,"") | O19: COLHEDORAS | P19: COLHETADEIRA - CASE 2388 | Q19: 30
D20: =IFERROR(__xludf.DUMMYFUNCTION("REGEXREPLACE(B20,""TRATOR - |COLHEITADEIRA |PULVERIZADOR |CAMINHAO-"","""")&"" + ""&REGEXREPLACE(C20,""PLANTADEIRA |PLATAFORMA |DISTRIBUIDOR |PULVERIZADOR "", """")")," + ") -> + | E20: =VLOOKUP(C20,'CUSTO OPERAÇÃO'!$P$1:$S$125,3,0) -> #N/A | F20: =VLOOKUP(C20,'CUSTO OPERAÇÃO'!$P$1:$S$125,4,0) -> #N/A | G20: 85 | H20: =(E20*F20*(G20/100))/10 -> #N/A | I20: =VLOOKUP(B20,'CUSTO OPERAÇÃO'!$P$1:$Q$125,2,0) -> #N/A | J20: =1/H20 -> #N/A | K20: =I20/H20 -> #N/A | L20: =K20*7.5 -> #N/A | M20: =IFERROR(L20/J20,"") | O20: COLHEDORAS | P20: COLHEITADEIRA CR 8.90 NEW HOLLAND | Q20: 50
D21: =IFERROR(__xludf.DUMMYFUNCTION("REGEXREPLACE(B21,""TRATOR - |COLHEITADEIRA |PULVERIZADOR |CAMINHAO-"","""")&"" + ""&REGEXREPLACE(C21,""PLANTADEIRA |PLATAFORMA |DISTRIBUIDOR |PULVERIZADOR "", """")")," + ") -> + | E21: =VLOOKUP(C21,'CUSTO OPERAÇÃO'!$P$1:$S$125,3,0) -> #N/A | F21: =VLOOKUP(C21,'CUSTO OPERAÇÃO'!$P$1:$S$125,4,0) -> #N/A | G21: 85 | H21: =(E21*F21*(G21/100))/10 -> #N/A | I21: =VLOOKUP(B21,'CUSTO OPERAÇÃO'!$P$1:$Q$125,2,0) -> #N/A | J21: =1/H21 -> #N/A | K21: =I21/H21 -> #N/A | L21: =K21*7.5 -> #N/A | M21: =IFERROR(L21/J21,"") | O21: COLHEDORAS | P21: COLHETADEIRA CR7.80 | Q21: 40
D22: =IFERROR(__xludf.DUMMYFUNCTION("REGEXREPLACE(B22,""TRATOR - |COLHEITADEIRA |PULVERIZADOR |CAMINHAO-"","""")&"" + ""&REGEXREPLACE(C22,""PLANTADEIRA |PLATAFORMA |DISTRIBUIDOR |PULVERIZADOR "", """")")," + ") -> + | E22: =VLOOKUP(C22,'CUSTO OPERAÇÃO'!$P$1:$S$125,3,0) -> #N/A | F22: =VLOOKUP(C22,'CUSTO OPERAÇÃO'!$P$1:$S$125,4,0) -> #N/A | G22: 85 | H22: =(E22*F22*(G22/100))/10 -> #N/A | I22: =VLOOKUP(B22,'CUSTO OPERAÇÃO'!$P$1:$Q$125,2,0) -> #N/A | J22: =1/H22 -> #N/A | K22: =I22/H22 -> #N/A | L22: =K22*7.5 -> #N/A | M22: =IFERROR(L22/J22,"") | O22: DISTRIBUIDOR FERTILIZANTES | P22: DISTRIBUIDOR BRUTUS 12000 | R22: 6 | S22: 6
D23: =IFERROR(__xludf.DUMMYFUNCTION("REGEXREPLACE(B23,""TRATOR - |COLHEITADEIRA |PULVERIZADOR |CAMINHAO-"","""")&"" + ""&REGEXREPLACE(C23,""PLANTADEIRA |PLATAFORMA |DISTRIBUIDOR |PULVERIZADOR "", """")")," + ") -> + | E23: =VLOOKUP(C23,'CUSTO OPERAÇÃO'!$P$1:$S$125,3,0) -> #N/A | F23: =VLOOKUP(C23,'CUSTO OPERAÇÃO'!$P$1:$S$125,4,0) -> #N/A | G23: 85 | H23: =(E23*F23*(G23/100))/10 -> #N/A | I23: =VLOOKUP(B23,'CUSTO OPERAÇÃO'!$P$1:$Q$125,2,0) -> #N/A | J23: =1/H23 -> #N/A | K23: =I23/H23 -> #N/A | L23: =K23*7.5 -> #N/A | M23: =IFERROR(L23/J23,"") | O23: DISTRIBUIDOR FERTILIZANTES | P23: DISTRIBUIDOR ADUBADORA HERCULES 10000 | R23: 30 | S23: 8
D24: =IFERROR(__xludf.DUMMYFUNCTION("REGEXREPLACE(B24,""TRATOR - |COLHEITADEIRA |PULVERIZADOR |CAMINHAO-"","""")&"" + ""&REGEXREPLACE(C24,""PLANTADEIRA |PLATAFORMA |DISTRIBUIDOR |PULVERIZADOR "", """")")," + ") -> + | E24: =VLOOKUP(C24,'CUSTO OPERAÇÃO'!$P$1:$S$125,3,0) -> #N/A | F24: =VLOOKUP(C24,'CUSTO OPERAÇÃO'!$P$1:$S$125,4,0) -> #N/A | G24: 85 | H24: =(E24*F24*(G24/100))/10 -> #N/A | I24: =VLOOKUP(B24,'CUSTO OPERAÇÃO'!$P$1:$Q$125,2,0) -> #N/A | J24: =1/H24 -> #N/A | K24: =I24/H24 -> #N/A | L24: =K24*7.5 -> #N/A | M24: =IFERROR(L24/J24,"") | O24: DISTRIBUIDOR FERTILIZANTES | P24: DISTRIBUIDOR JAN 20000 | R24: 15 | S24: 8
D25: =IFERROR(__xludf.DUMMYFUNCTION("REGEXREPLACE(B25,""TRATOR - |COLHEITADEIRA |PULVERIZADOR |CAMINHAO-"","""")&"" + ""&REGEXREPLACE(C25,""PLANTADEIRA |PLATAFORMA |DISTRIBUIDOR |PULVERIZADOR "", """")")," + ") -> + | E25: =VLOOKUP(C25,'CUSTO OPERAÇÃO'!$P$1:$S$125,3,0) -> #N/A | F25: =VLOOKUP(C25,'CUSTO OPERAÇÃO'!$P$1:$S$125,4,0) -> #N/A | G25: 85 | H25: =(E25*F25*(G25/100))/10 -> #N/A | I25: =VLOOKUP(B25,'CUSTO OPERAÇÃO'!$P$1:$Q$125,2,0) -> #N/A | J25: =1/H25 -> #N/A | K25: =I25/H25 -> #N/A | L25: =K25*7.5 -> #N/A | M25: =IFERROR(L25/J25,"") | O25: DISTRIBUIDOR FERTILIZANTES | P25: KAMAQ 6000 | R25: 7 | S25: 8
D26: =IFERROR(__xludf.DUMMYFUNCTION("REGEXREPLACE(B26,""TRATOR - |COLHEITADEIRA |PULVERIZADOR |CAMINHAO-"","""")&"" + ""&REGEXREPLACE(C26,""PLANTADEIRA |PLATAFORMA |DISTRIBUIDOR |PULVERIZADOR "", """")")," + ") -> + | E26: =VLOOKUP(C26,'CUSTO OPERAÇÃO'!$P$1:$S$125,3,0) -> #N/A | F26: =VLOOKUP(C26,'CUSTO OPERAÇÃO'!$P$1:$S$125,4,0) -> #N/A | G26: 85 | H26: =(E26*F26*(G26/100))/10 -> #N/A | I26: =VLOOKUP(B26,'CUSTO OPERAÇÃO'!$P$1:$Q$125,2,0) -> #N/A | J26: =1/H26 -> #N/A | K26: =I26/H26 -> #N/A | L26: =K26*7.5 -> #N/A | M26: =IFERROR(L26/J26,"") | O26: EQUIPAMENTOS | P26: BALANÇA CAR. 120/240T/H
D27: =IFERROR(__xludf.DUMMYFUNCTION("REGEXREPLACE(B27,""TRATOR - |COLHEITADEIRA |PULVERIZADOR |CAMINHAO-"","""")&"" + ""&REGEXREPLACE(C27,""PLANTADEIRA |PLATAFORMA |DISTRIBUIDOR |PULVERIZADOR "", """")")," + ") -> + | E27: =VLOOKUP(C27,'CUSTO OPERAÇÃO'!$P$1:$S$125,3,0) -> #N/A | F27: =VLOOKUP(C27,'CUSTO OPERAÇÃO'!$P$1:$S$125,4,0) -> #N/A | G27: 85 | H27: =(E27*F27*(G27/100))/10 -> #N/A | I27: =VLOOKUP(B27,'CUSTO OPERAÇÃO'!$P$1:$Q$125,2,0) -> #N/A | J27: =1/H27 -> #N/A | K27: =I27/H27 -> #N/A | L27: =K27*7.5 -> #N/A | M27: =IFERROR(L27/J27,"") | O27: EQUIPAMENTOS | P27: GUINDASTE HIDRAULICO GRM 14.000
D28: =IFERROR(__xludf.DUMMYFUNCTION("REGEXREPLACE(B28,""TRATOR - |COLHEITADEIRA |PULVERIZADOR |CAMINHAO-"","""")&"" + ""&REGEXREPLACE(C28,""PLANTADEIRA |PLATAFORMA |DISTRIBUIDOR |PULVERIZADOR "", """")")," + ") -> + | E28: =VLOOKUP(C28,'CUSTO OPERAÇÃO'!$P$1:$S$125,3,0) -> #N/A | F28: =VLOOKUP(C28,'CUSTO OPERAÇÃO'!$P$1:$S$125,4,0) -> #N/A | G28: 85 | H28: =(E28*F28*(G28/100))/10 -> #N/A | I28: =VLOOKUP(B28,'CUSTO OPERAÇÃO'!$P$1:$Q$125,2,0) -> #N/A | J28: =1/H28 -> #N/A | K28: =I28/H28 -> #N/A | L28: =K28*7.5 -> #N/A | M28: =IFERROR(L28/J28,"") | O28: EQUIPAMENTOS | P28: EQUIPAMENTOS
D29: =IFERROR(__xludf.DUMMYFUNCTION("REGEXREPLACE(B29,""TRATOR - |COLHEITADEIRA |PULVERIZADOR |CAMINHAO-"","""")&"" + ""&REGEXREPLACE(C29,""PLANTADEIRA |PLATAFORMA |DISTRIBUIDOR |PULVERIZADOR "", """")")," + ") -> + | E29: =VLOOKUP(C29,'CUSTO OPERAÇÃO'!$P$1:$S$125,3,0) -> #N/A | F29: =VLOOKUP(C29,'CUSTO OPERAÇÃO'!$P$1:$S$125,4,0) -> #N/A | G29: 85 | H29: =(E29*F29*(G29/100))/10 -> #N/A | I29: =VLOOKUP(B29,'CUSTO OPERAÇÃO'!$P$1:$Q$125,2,0) -> #N/A | J29: =1/H29 -> #N/A | K29: =I29/H29 -> #N/A | L29: =K29*7.5 -> #N/A | M29: =IFERROR(L29/J29,"") | O29: EQUIPAMENTOS | P29: HANGAR
D30: =IFERROR(__xludf.DUMMYFUNCTION("REGEXREPLACE(B30,""TRATOR - |COLHEITADEIRA |PULVERIZADOR |CAMINHAO-"","""")&"" + ""&REGEXREPLACE(C30,""PLANTADEIRA |PLATAFORMA |DISTRIBUIDOR |PULVERIZADOR "", """")")," + ") -> + | E30: =VLOOKUP(C30,'CUSTO OPERAÇÃO'!$P$1:$S$125,3,0) -> #N/A | F30: =VLOOKUP(C30,'CUSTO OPERAÇÃO'!$P$1:$S$125,4,0) -> #N/A | G30: 85 | H30: =(E30*F30*(G30/100))/10 -> #N/A | I30: =VLOOKUP(B30,'CUSTO OPERAÇÃO'!$P$1:$Q$125,2,0) -> #N/A | J30: =1/H30 -> #N/A | K30: =I30/H30 -> #N/A | L30: =K30*7.5 -> #N/A | M30: =IFERROR(L30/J30,"") | O30: EQUIPAMENTOS | P30: GERADOR GMG 500 KVA
O31: EQUIPAMENTOS | P31: LARANJA
O32: EQUIPAMENTOS | P32: IRRIGAÇÃO LARANJA
O33: EQUIPAMENTOS | P33: BALANÇA DE FLUXO
O34: EQUIPAMENTOS | P34: LÂMINA TRASEIRA STARA 5000
O35: EQUIPAMENTOS | P35: MIAC DOBLE IV
O36: EQUIPAMENTOS | P36: EMBUTIDORA SILO BOLSA - ESPORA
O37: EQUIPAMENTOS | P37: EXTRATORA SILO BOLSA
O38: EQUIPAMENTOS | P38: GRUPO GERADOR CAT 130KWA
O39: EQUIPAMENTOS | P39: GRUPO GERADOR CUMINS 130KWA
O40: EQUIPAMENTOS | P40: PRÉ-LIMPEZA 40 TON
O41: EQUIPAMENTOS | P41: PRÉ-LIMPEZA 120TON/H
O42: EQUIPAMENTOS | P42: SECADOR PALINI 15 TON 01
... O50: IMPLEMENTOS | P50: GRADE GASPCRC HD 9017
O51: IMPLEMENTOS | P51: SUBSOLADOR 11 ASTES | R51: 5.5 | S51: 6
O52: IMPLEMENTOS | P52: TRITON JAN 4600
O53: IMPLEMENTOS | P53: ROÇADEIRA ECOLOGICA
O54: IMPLEMENTOS | P54: CARRETA GRANELEIRA
O55: IMPLEMENTOS | P55: GRADE INTERMEDIÁRIA
O56: IMPLEMENTOS | P56: GRADE NIVELADORA
O57: IMPLEMENTOS | P57: GRADE PESADA32
O58: IMPLEMENTOS | P58: GIRASSOL RAIZ
O59: IMPLEMENTOS | P59: SEMIRREBOQUE FH 540 -1
O60: IMPLEMENTOS | P60: SEMIRREBOQUE FH 540 -2
O61: IMPLEMENTOS | P61: DOLLY FH540
O62: IMPLEMENTOS | P62: ALEIRADOR CONJUNTO DUPLO
O63: IMPLEMENTOS | P63: CEIFADEIRA CONJUNTO DUPLO
... O77: PIVO AGRICOLA | P77: P06 40
O78: PLATAFORMAS | P78: PLATAFORMA 740 CF30 AGRIDREPER | R78: 9 | S78: 6
O79: PLATAFORMAS | P79: PLATAFORMA MILHO BRAVA 11 | R79: 5.5 | S79: 10
O80: PLATAFORMAS | P80: PLATAFORMA CASE 30PES | R80: 9 | S80: 5
O81: PLATAFORMAS | P81: PLATAFORMA COLHE TUDO | R81: 9 | S81: 4
O82: PLATAFORMAS | P82: PLATAFORMA 880 CF45 | R82: 13 | S82: 6
O83: PLATAFORMAS | P83: PLATAFORMA MACDON 35F | R83: 9 | S83: 6
O84: PULVERIZADORES | P84: PULVERIZADOR- JD4730 | Q84: 17 | R84: 30 | S84: 20
O85: PULVERIZADORES | P85: JACTO UNIPORT 2000 | Q85: 7 | R85: 24 | S85: 16
O86: PULVERIZADORES | P86: AVIAO AGRICOLA PAWNEE 260
O87: PULVERIZADORES | P87: TRATADOR SEMENTE-TREVISAN 1000
O88: PULVERIZADORES | P88: PULVERIZADOR-JACTO ARBUS 4000
O89: SEMEADORAS | P89: PLANTADEIRA HORSCH MAESTRO DUO 36.50 | R89: 18 | S89: 8
O90: SEMEADORAS | P90: PLANTADEIRA - CASE ASM 1213 | R90: 13 | S90: 7
O91: SEMEADORAS | P91: PLANTADEIRA - JD2122 | R91: 10.5 | S91: 7
O92: SEMEADORAS | P92: SEMEADORA DE ARRASTO PAMPEANA | R92: 4 | S92: 10
O93: SEMEADORAS | P93: PLANTADEIRA CASE 2213 | R93: 6.5 | S93: 7
O94: TRATORES | P94: TRATOR - CASE STEIGER 420 | Q94: 60
O95: TRATORES | P95: TRATOR - CASE MAGNUM 340 | Q95: 40
O96: TRATORES | P96: EMPILHADEIRA CPCD-25 | Q96: 8
O97: TRATORES | P97: TRATOR - NH T7.260 | Q97: 25
O98: TRATORES | P98: TRATOR - VALTRA BH 180 | Q98: 20
O99: TRATORES | P99: EMPILHADEIRA LG35DT - AGUA VIVA | Q99: 8
O100: TRATORES | P100: TRATOR JARDIM -JD-LA175 | Q100: 4
O101: TRATORES | P101: TRATOR - JD 5600 | Q101: 7
O102: TRATORES | P102: TRATOR - JD-6125J | Q102: 6
O103: TRATORES | P103: TRATOR - NH 7630 | Q103: 6
O104: TRATORES | P104: TRATOR - NH T8.355 | Q104: 30
O105: TRATORES | P105: TRATOR-JD 7505 | Q105: 15
... O114: TRATORES | P114: GAFANHOTO | Q114: 5
O115: VEÍCULOS | P115: TOYOTA HILUX - JOAQUIM
O116: VEÍCULOS | P116: TOYOTA HILUX - JOVANE
O117: VEÍCULOS | P117: S10 - LTZ - FAZENDA
O118: VEÍCULOS | P118: S10 LTZ - JOÃO
O119: VEÍCULOS | P119: RANGER VITOR
O120: VEÍCULOS | P120: TOYOTA COROLLA CROSS XRE 2.0 16V
O121: VEÍCULOS | P121: D20
O122: VEÍCULOS | P122: D-20
O123: VEÍCULOS | P123: TOYOTA HILUX - VITOR
O124: VEÍCULOS | P124: TOYOTA HILUX - ELESIO
O125: VEÍCULOS | P125: S10 LTZ - JOÃO - 2

Sheet DRE ORÇADA
B1: SOJA - 02 COQ | J1: SOJA - 02 COQ | L1: SOJA - 02 COQ | N1: SOJA - 02 COQ | P1: SOJA - 02 COQ
A2: ORÇAMENTO SAFRA 2026/2027 | B2: ='PORTIFÓLIO'!$J$3 -> FE-BRACHIARIA-26/27 | D2: ='PORTIFÓLIO'!$K$3 -> FE-SOJA IRRIGADO-26/27 | F2: ='PORTIFÓLIO'!$L$3 -> FE-SOJA SEQUEIRO-26/27 | H2: ='PORTIFÓLIO'!$M$3 -> FA-MILHO SEMENTE-27/27 | J2: ='PORTIFÓLIO'!$N$3 -> FA-SORGO SEQUEIRO-27/27 | L2: ='PORTIFÓLIO'!$O$3 -> FA-MILHO SEQUEIRO-26/27 | N2: ='PORTIFÓLIO'!$P$3 -> FA-SOJA SEQUEIRO-26/27 | P2: ='PORTIFÓLIO'!$Q$3 -> FA-SOJA-IRRIGADO-26/27 | R2: TOTAL
C3: R$/ Ha | E3: R$/ Ha | G3: R$/ Ha | I3: R$/ Ha | K3: R$/ Ha | M3: R$/ Ha | O3: R$/ Ha | Q3: R$/ Ha | S3: R$/ Ha
A4: ÁREA | B4: =SUMIF('ÁREA PLANTIO'!$C$2:$C$30,"*"&B2&"*",'ÁREA PLANTIO'!$E$2:$E$30)+SUMIF('ÁREA PLANTIO'!$H$2:$H$30,"*"&B2&"*",'ÁREA PLANTIO'!$E$2:$E$30) -> 490 | D4: =SUMIF('ÁREA PLANTIO'!$C$2:$C$30,"*"&D2&"*",'ÁREA PLANTIO'!$E$2:$E$30)+SUMIF('ÁREA PLANTIO'!$H$2:$H$30,"*"&D2&"*",'ÁREA PLANTIO'!$E$2:$E$30) -> 300 | F4: =SUMIF('ÁREA PLANTIO'!$C$2:$C$30,"*"&F2&"*",'ÁREA PLANTIO'!$E$2:$E$30)+SUMIF('ÁREA PLANTIO'!$H$2:$H$30,"*"&F2&"*",'ÁREA PLANTIO'!$E$2:$E$30) -> 220 | H4: =SUMIF('ÁREA PLANTIO'!$C$2:$C$30,"*"&H2&"*",'ÁREA PLANTIO'!$E$2:$E$30)+SUMIF('ÁREA PLANTIO'!$H$2:$H$30,"*"&H2&"*",'ÁREA PLANTIO'!$E$2:$E$30) -> 200 | J4: =SUMIF('ÁREA PLANTIO'!$C$2:$C$30,"*"&J2&"*",'ÁREA PLANTIO'!$E$2:$E$30)+SUMIF('ÁREA PLANTIO'!$H$2:$H$30,"*"&J2&"*",'ÁREA PLANTIO'!$E$2:$E$30) -> 376 | L4: =SUMIF('ÁREA PLANTIO'!$C$2:$C$30,"*"&L2&"*",'ÁREA PLANTIO'!$E$2:$E$30)+SUMIF('ÁREA PLANTIO'!$H$2:$H$30,"*"&L2&"*",'ÁREA PLANTIO'!$E$2:$E$30) -> 220 | N4: =SUMIF('ÁREA PLANTIO'!$C$2:$C$30,"*"&N2&"*",'ÁREA PLANTIO'!$E$2:$E$30)+SUMIF('ÁREA PLANTIO'!$H$2:$H$30,"*"&N2&"*",'ÁREA PLANTIO'!$E$2:$E$30) -> 1218 | P4: =SUMIF('ÁREA PLANTIO'!$C$2:$C$30,"*"&P2&"*",'ÁREA PLANTIO'!$E$2:$E$30)+SUMIF('ÁREA PLANTIO'!$H$2:$H$30,"*"&P2&"*",'ÁREA PLANTIO'!$E$2:$E$30) -> 320 | R4: =SUM(P4,N4,L4,J4,B4,D4,F4,H4) -> 3344
A5: PRODUÇÃO TOTAL | B5: =SUMIF('ÁREA PLANTIO'!$C$2:$C$30,"*"&B2&"*",'ÁREA PLANTIO'!$F$2:$F$30)+SUMIF('ÁREA PLANTIO'!$H$2:$H$30,"*"&B2&"*",'ÁREA PLANTIO'!$J$2:$J$30) -> 28550 | D5: =SUMIF('ÁREA PLANTIO'!$C$2:$C$30,"*"&D2&"*",'ÁREA PLANTIO'!$F$2:$F$30)+SUMIF('ÁREA PLANTIO'!$H$2:$H$30,"*"&D2&"*",'ÁREA PLANTIO'!$J$2:$J$30) -> 18900 | F5: =SUMIF('ÁREA PLANTIO'!$C$2:$C$30,"*"&F2&"*",'ÁREA PLANTIO'!$F$2:$F$30)+SUMIF('ÁREA PLANTIO'!$H$2:$H$30,"*"&F2&"*",'ÁREA PLANTIO'!$J$2:$J$30) -> 11000 | H5: =SUMIF('ÁREA PLANTIO'!$C$2:$C$30,"*"&H2&"*",'ÁREA PLANTIO'!$F$2:$F$30)+SUMIF('ÁREA PLANTIO'!$H$2:$H$30,"*"&H2&"*",'ÁREA PLANTIO'!$J$2:$J$30) -> 40000 | J5: =SUMIF('ÁREA PLANTIO'!$C$2:$C$30,"*"&J2&"*",'ÁREA PLANTIO'!$F$2:$F$30)+SUMIF('ÁREA PLANTIO'!$H$2:$H$30,"*"&J2&"*",'ÁREA PLANTIO'!$J$2:$J$30) -> 22560 | L5: =SUMIF('ÁREA PLANTIO'!$C$2:$C$30,"*"&L2&"*",'ÁREA PLANTIO'!$F$2:$F$30)+SUMIF('ÁREA PLANTIO'!$H$2:$H$30,"*"&L2&"*",'ÁREA PLANTIO'!$J$2:$J$30) -> 39600 | N5: =SUMIF('ÁREA PLANTIO'!$C$2:$C$30,"*"&N2&"*",'ÁREA PLANTIO'!$F$2:$F$30)+SUMIF('ÁREA PLANTIO'!$H$2:$H$30,"*"&N2&"*",'ÁREA PLANTIO'!$J$2:$J$30) -> 85260 | P5: =SUMIF('ÁREA PLANTIO'!$C$2:$C$30,"*"&P2&"*",'ÁREA PLANTIO'!$F$2:$F$30)+SUMIF('ÁREA PLANTIO'!$H$2:$H$30,"*"&P2&"*",'ÁREA PLANTIO'!$J$2:$J$30) -> 22400
A6: PRODUÇÃO P/HA | B6: =B5/B4 -> 58.265306 | D6: =IFERROR(D5/D4,"") -> 63 | F6: =IFERROR(F5/F4,"") -> 50 | H6: =IFERROR(H5/H4,"") -> 200 | J6: =IFERROR(J5/J4,"") -> 60 | L6: =IFERROR(L5/L4,"") -> 180 | N6: =IFERROR(N5/N4,"") -> 70 | P6: =IFERROR(P5/P4,"") -> 70
A7: PREÇO MÉDIO | B7: 200 | D7: 110 | F7: 110 | H7: 60 | J7: 48 | L7: 60 | N7: 110 | P7: 110 | S7: =R7/$R$4 -> 0
A8: RECEITA ARRENDAMENTO | S8: =R8/$R$4 -> 0
A9: RECEITA BRUTA | B9: =B5*B7 -> 5710000 | C9: =IFERROR(B9/B4,"") -> 11653.061 | D9: =D5*D7 -> 2079000 | E9: =IFERROR(D9/D4,"") -> 6930 | F9: =F5*F7 -> 1210000 | G9: =IFERROR(F9/F4,"") -> 5500 | H9: =H5*H7 -> 2400000 | I9: =IFERROR(H9/H4,"") -> 12000 | J9: =J5*J7 -> 1082880 | K9: =IFERROR(J9/J4,"") -> 2880 | L9: =L5*L7 -> 2376000 | M9: =IFERROR(L9/L4,"") -> 10800 | N9: =N5*N7 -> 9378600 | O9: =IFERROR(N9/N4,"") -> 7700 | P9: =P5*P7 -> 2464000 | Q9: =IFERROR(P9/P4,"") -> 7700 | R9: =SUM(P9,N9,L9,J9,H9,D9,B9) -> 25490480 | S9: =IFERROR(R9/R4,"") -> 7622.7512
A10: SAÍDAS TOTAIS | B10: =SUM(B11,B465,B546,B555,B557) -> 356781.39 | C10: =B10/B4 -> 728.12528 | D10: =SUM(D11,D465,D546,D555,D557) -> 436954.42 | E10: =IFERROR(D10/D4,"") -> 1456.5147 | F10: =SUM(F11,F465,F546,F555,F557) -> 312894.8 | G10: =IFERROR(F10/F4,"") -> 1422.2491 | H10: =SUM(H11,H465,H546,H555,H557) -> 42925.506 | I10: =IFERROR(H10/H4,"") -> 214.62753 | J10: =SUM(J11,J465,J546,J555,J557) -> 123127.98 | K10: =IFERROR(J10/J4,"") -> 327.46803 | L10: =SUM(L11,L465,L546,L555,L557) -> 292129.39 | M10: =IFERROR(L10/L4,"") -> 1327.8609 | N10: =SUM(N11,N465,N546,N555,N557) -> 1814506.5 | O10: =IFERROR(N10/N4,"") -> 1489.7426 | P10: =SUM(P11,P465,P546,P555,P557) -> 496103.82 | Q10: =IFERROR(P10/P4,"") -> 1550.3244 | R10: =SUM(P10,N10,L10,J10,H10,D10,B10) -> 3562529 | S10: =R10/$R$4 -> 1065.3496
A11: CUSTOS DIRETOS | B11: =SUM(B12,B421,B458,B459,B460,B461,B462) -> 356781.39 | C11: =B11/$B$4 -> 728.12528 | D11: =SUM(D12,D421,D458,D459,D460,D461,D462) -> 436954.42 | E11: =D11/$D$4 -> 1456.5147 | F11: =SUM(F12,F421,F458,F459,F460,F461,F462) -> 312894.8 | G11: =F11/$F$4 -> 1422.2491 | H11: =SUM(H12,H421,H458,H459,H460,H461,H462) -> 42925.506 | I11: =IFERROR(H11/$H$4,"") -> 214.62753 | J11: =SUM(J12,J421,J458,J459,J460,J461,J462) -> 123127.98 | K11: =J11/$J$4 -> 327.46803 | L11: =SUM(L12,L421,L458,L459,L460,L461,L462) -> 292129.39 | M11: 4221 | N11: =SUM(N12,N421,N458,N459,N460,N461,N462) -> 1814506.5 | O11: 4221 | P11: =SUM(P12,P421,P458,P459,P460,P461,P462) -> 496103.82 | Q11: 4221 | R11: =SUM(P11,N11,L11,J11,H11,D11,B11) -> 3562529 | S11: =R11/$R$4 -> 1065.3496
A12: CUSTOS INSUMOS | B12: =B13+B32+B104+B175+B256+B293+B322+B340 -> 323903.69 | C12: =IFERROR(B12/$B$4,"") -> 661.02794 | D12: =D13+D32+D104+D175+D256+D293+D322+D340 -> 334976.77 | E12: =IFERROR(D12/$D$4,"") -> 1116.5892 | F12: =F13+F32+F104+F175+F256+F293+F322+F340 -> 238111.19 | G12: =IFERROR(F12/$F$4,"") -> 1082.3236 | H12: =H13+H32+H104+H175+H256+H293+H322+H340 -> 42925.506 | I12: =IFERROR(H12/$H$4,"") -> 214.62753 | J12: =J13+J32+J104+J175+J256+J293+J322+J340 -> 123127.98 | K12: =IFERROR(J12/$J$4,"") -> 327.46803 | L12: =L13+L32+L104+L175+L256+L293+L322+L340 -> 193459.39 | M12: =IFERROR(L12/$L$4,"") -> 879.36086 | N12: =N13+N32+N104+N175+N256+N293+N322+N340 -> 1400477.2 | O12: =IFERROR(N12/$N$4,"") -> 1149.8171 | P12: =P13+P32+P104+P175+P256+P293+P322+P340 -> 387327.66 | Q12: =IFERROR(P12/$P$4,"") -> 1210.3989 | R12: =SUM(P12,N12,L12,J12,H12,D12,B12) -> 2806198.2 | S12: =IFERROR(R12/$R$4,"") -> 839.17411
A13: FERTILIZANTES | B13: =SUM(B14:B31) -> 0 | C13: =B13/$B$4 -> 0 | D13: =SUM(D14:D31) -> 0 | E13: =D13/$D$4 -> 0 | F13: =SUM(F14:F31) -> 0 | G13: =F13/$F$4 -> 0 | H13: =SUM(H14:H31) -> 0 | I13: =H13/$H$4 -> 0 | J13: =SUM(J14:J31) -> 0 | K13: =J13/$J$4 -> 0 | L13: =SUM(L14:L31) -> 0 | M13: =L13/$L$4 -> 0 | N13: =SUM(N14:N31) -> 0 | O13: =N13/$N$4 -> 0 | P13: =SUM(P14:P31) -> 0 | Q13: =P13/$P$4 -> 0 | R13: =SUM(P13,N13,L13,J13,H13,D13,B13) -> 0 | S13: =R13/$R$4 -> 0
A14: =IFERROR(__xludf.DUMMYFUNCTION("UNIQUE(FILTER('PORTIFÓLIO'!C:C, 'PORTIFÓLIO'!B:B=""fertilizantes""))"),"I-ACTIVE") -> I-ACTIVE | B14: {=IFERROR( SUM( IF( 'PORTIFÓLIO'!$C$4:$C$564=$A14, N(INDEX('PORTIFÓLIO'!$J$4:$Q$564,,MATCH(B$2,'PORTIFÓLIO'!$J$3:$Q$3,0))) * N('PORTIFÓLIO'!$S$4:$S$564), 0 ) ), 0)} -> 0 | C14: =B14/$B$4 -> 0 | D14: {=IFERROR( SUM( IF( 'PORTIFÓLIO'!$C$4:$C$564=$A14, N(INDEX('PORTIFÓLIO'!$J$4:$Q$564,,MATCH(D$2,'PORTIFÓLIO'!$J$3:$Q$3,0))) * N('PORTIFÓLIO'!$S$4:$S$564), 0 ) ), 0)} -> 0 | E14: =D14/$D$4 -> 0 | F14: {=IFERROR( SUM( IF( 'PORTIFÓLIO'!$C$4:$C$564=$A14, N(INDEX('PORTIFÓLIO'!$J$4:$Q$564,,MATCH(F$2,'PORTIFÓLIO'!$J$3:$Q$3,0))) * N('PORTIFÓLIO'!$S$4:$S$564), 0 ) ), 0)} -> 0 | G14: =F14/$F$4 -> 0 | H14: {=IFERROR( SUM( IF( 'PORTIFÓLIO'!$C$4:$C$564=$A14, N(INDEX('PORTIFÓLIO'!$J$4:$Q$564,,MATCH(H$2,'PORTIFÓLIO'!$J$3:$Q$3,0))) * N('PORTIFÓLIO'!$S$4:$S$564), 0 ) ), 0)} -> 0 | I14: =H14/$H$4 -> 0 | J14: {=IFERROR( SUM( IF( 'PORTIFÓLIO'!$C$4:$C$564=$A14, N(INDEX('PORTIFÓLIO'!$J$4:$Q$564,,MATCH(J$2,'PORTIFÓLIO'!$J$3:$Q$3,0))) * N('PORTIFÓLIO'!$S$4:$S$564), 0 ) ), 0)} -> 0 | K14: =J14/$J$4 -> 0 | L14: {=IFERROR( SUM( IF( 'PORTIFÓLIO'!$C$4:$C$564=$A14, N(INDEX('PORTIFÓLIO'!$J$4:$Q$564,,MATCH(L$2,'PORTIFÓLIO'!$J$3:$Q$3,0))) * N('PORTIFÓLIO'!$S$4:$S$564), 0 ) ), 0)} -> 0 | M14: =L14/$L$4 -> 0 | N14: {=IFERROR( SUM( IF( 'PORTIFÓLIO'!$C$4:$C$564=$A14, N(INDEX('PORTIFÓLIO'!$J$4:$Q$564,,MATCH(N$2,'PORTIFÓLIO'!$J$3:$Q$3,0))) * N('PORTIFÓLIO'!$S$4:$S$564), 0 ) ), 0)} -> 0 | O14: =N14/$N$4 -> 0 | P14: {=IFERROR( SUM( IF( 'PORTIFÓLIO'!$C$4:$C$564=$A14, N(INDEX('PORTIFÓLIO'!$J$4:$Q$564,,MATCH(P$2,'PORTIFÓLIO'!$J$3:$Q$3,0))) * N('PORTIFÓLIO'!$S$4:$S$564), 0 ) ), 0)} -> 0 | Q14: =P14/$P$4 -> 0 | R14: =SUM(P14,N14,L14,J14,H14,D14,B14) -> 0 | S14: =R14/$R$4 -> 0
A15: =IFERROR(__xludf.DUMMYFUNCTION("""COMPUTED_VALUE"""),"MAP") -> MAP | B15: {=IFERROR( SUM( IF( 'PORTIFÓLIO'!$C$4:$C$564=$A15, N(INDEX('PORTIFÓLIO'!$J$4:$Q$564,,MATCH(B$2,'PORTIFÓLIO'!$J$3:$Q$3,0))) * N('PORTIFÓLIO'!$S$4:$S$564), 0 ) ), 0)} -> 0 | C15: =B15/$B$4 -> 0 | D15: {=IFERROR( SUM( IF( 'PORTIFÓLIO'!$C$4:$C$564=$A15, N(INDEX('PORTIFÓLIO'!$J$4:$Q$564,,MATCH(D$2,'PORTIFÓLIO'!$J$3:$Q$3,0))) * N('PORTIFÓLIO'!$S$4:$S$564), 0 ) ), 0)} -> 0 | E15: =D15/$D$4 -> 0 | F15: {=IFERROR( SUM( IF( 'PORTIFÓLIO'!$C$4:$C$564=$A15, N(INDEX('PORTIFÓLIO'!$J$4:$Q$564,,MATCH(F$2,'PORTIFÓLIO'!$J$3:$Q$3,0))) * N('PORTIFÓLIO'!$S$4:$S$564), 0 ) ), 0)} -> 0 | G15: =F15/$F$4 -> 0 | H15: {=IFERROR( SUM( IF( 'PORTIFÓLIO'!$C$4:$C$564=$A15, N(INDEX('PORTIFÓLIO'!$J$4:$Q$564,,MATCH(H$2,'PORTIFÓLIO'!$J$3:$Q$3,0))) * N('PORTIFÓLIO'!$S$4:$S$564), 0 ) ), 0)} -> 0 | I15: =H15/$H$4 -> 0 | J15: {=IFERROR( SUM( IF( 'PORTIFÓLIO'!$C$4:$C$564=$A15, N(INDEX('PORTIFÓLIO'!$J$4:$Q$564,,MATCH(J$2,'PORTIFÓLIO'!$J$3:$Q$3,0))) * N('PORTIFÓLIO'!$S$4:$S$564), 0 ) ), 0)} -> 0 | K15: =J15/$J$4 -> 0 | L15: {=IFERROR( SUM( IF( 'PORTIFÓLIO'!$C$4:$C$564=$A15, N(INDEX('PORTIFÓLIO'!$J$4:$Q$564,,MATCH(L$2,'PORTIFÓLIO'!$J$3:$Q$3,0))) * N('PORTIFÓLIO'!$S$4:$S$564), 0 ) ), 0)} -> 0 | M15: =L15/$L$4 -> 0 | N15: {=IFERROR( SUM( IF( 'PORTIFÓLIO'!$C$4:$C$564=$A15, N(INDEX('PORTIFÓLIO'!$J$4:$Q$564,,MATCH(N$2,'PORTIFÓLIO'!$J$3:$Q$3,0))) * N('PORTIFÓLIO'!$S$4:$S$564), 0 ) ), 0)} -> 0 | O15: =N15/$N$4 -> 0 | P15: {=IFERROR( SUM( IF( 'PORTIFÓLIO'!$C$4:$C$564=$A15, N(INDEX('PORTIFÓLIO'!$J$4:$Q$564,,MATCH(P$2,'PORTIFÓLIO'!$J$3:$Q$3,0))) * N('PORTIFÓLIO'!$S$4:$S$564), 0 ) ), 0)} -> 0 | Q15: =P15/$P$4 -> 0 | R15: =SUM(P15,N15,L15,J15,H15,D15,B15) -> 0 | S15: =R15/$R$4 -> 0
A16: =IFERROR(__xludf.DUMMYFUNCTION("""COMPUTED_VALUE"""),"KCL 60%") -> KCL 60% | B16: {=IFERROR( SUM( IF( 'PORTIFÓLIO'!$C$4:$C$564=$A16, N(INDEX('PORTIFÓLIO'!$J$4:$Q$564,,MATCH(B$2,'PORTIFÓLIO'!$J$3:$Q$3,0))) * N('PORTIFÓLIO'!$S$4:$S$564), 0 ) ), 0)} -> 0 | C16: =B16/$B$4 -> 0 | D16: {=IFERROR( SUM( IF( 'PORTIFÓLIO'!$C$4:$C$564=$A16, N(INDEX('PORTIFÓLIO'!$J$4:$Q$564,,MATCH(D$2,'PORTIFÓLIO'!$J$3:$Q$3,0))) * N('PORTIFÓLIO'!$S$4:$S$564), 0 ) ), 0)} -> 0 | E16: =D16/$D$4 -> 0 | F16: {=IFERROR( SUM( IF( 'PORTIFÓLIO'!$C$4:$C$564=$A16, N(INDEX('PORTIFÓLIO'!$J$4:$Q$564,,MATCH(F$2,'PORTIFÓLIO'!$J$3:$Q$3,0))) * N('PORTIFÓLIO'!$S$4:$S$564), 0 ) ), 0)} -> 0 | G16: =F16/$F$4 -> 0 | H16: {=IFERROR( SUM( IF( 'PORTIFÓLIO'!$C$4:$C$564=$A16, N(INDEX('PORTIFÓLIO'!$J$4:$Q$564,,MATCH(H$2,'PORTIFÓLIO'!$J$3:$Q$3,0))) * N('PORTIFÓLIO'!$S$4:$S$564), 0 ) ), 0)} -> 0 | I16: =H16/$H$4 -> 0 | J16: {=IFERROR( SUM( IF( 'PORTIFÓLIO'!$C$4:$C$564=$A16, N(INDEX('PORTIFÓLIO'!$J$4:$Q$564,,MATCH(J$2,'PORTIFÓLIO'!$J$3:$Q$3,0))) * N('PORTIFÓLIO'!$S$4:$S$564), 0 ) ), 0)} -> 0 | K16: =J16/$J$4 -> 0 | L16: {=IFERROR( SUM( IF( 'PORTIFÓLIO'!$C$4:$C$564=$A16, N(INDEX('PORTIFÓLIO'!$J$4:$Q$564,,MATCH(L$2,'PORTIFÓLIO'!$J$3:$Q$3,0))) * N('PORTIFÓLIO'!$S$4:$S$564), 0 ) ), 0)} -> 0 | M16: =L16/$L$4 -> 0 | N16: {=IFERROR( SUM( IF( 'PORTIFÓLIO'!$C$4:$C$564=$A16, N(INDEX('PORTIFÓLIO'!$J$4:$Q$564,,MATCH(N$2,'PORTIFÓLIO'!$J$3:$Q$3,0))) * N('PORTIFÓLIO'!$S$4:$S$564), 0 ) ), 0)} -> 0 | O16: =N16/$N$4 -> 0 | P16: {=IFERROR( SUM( IF( 'PORTIFÓLIO'!$C$4:$C$564=$A16, N(INDEX('PORTIFÓLIO'!$J$4:$Q$564,,MATCH(P$2,'PORTIFÓLIO'!$J$3:$Q$3,0))) * N('PORTIFÓLIO'!$S$4:$S$564), 0 ) ), 0)} -> 0 | Q16: =P16/$P$4 -> 0 | R16: =SUM(P16,N16,L16,J16,H16,D16,B16) -> 0 | S16: =R16/$R$4 -> 0
A17: =IFERROR(__xludf.DUMMYFUNCTION("""COMPUTED_VALUE"""),"05-37-00") -> 05-37-00 | B17: {=IFERROR( SUM( IF( 'PORTIFÓLIO'!$C$4:$C$564=$A17, N(INDEX('PORTIFÓLIO'!$J$4:$Q$564,,MATCH(B$2,'PORTIFÓLIO'!$J$3:$Q$3,0))) * N('PORTIFÓLIO'!$S$4:$S$564), 0 ) ), 0)} -> 0 | C17: =B17/$B$4 -> 0 | D17: {=IFERROR( SUM( IF( 'PORTIFÓLIO'!$C$4:$C$564=$A17, N(INDEX('PORTIFÓLIO'!$J$4:$Q$564,,MATCH(D$2,'PORTIFÓLIO'!$J$3:$Q$3,0))) * N('PORTIFÓLIO'!$S$4:$S$564), 0 ) ), 0)} -> 0 | E17: =D17/$D$4 -> 0 | F17: {=IFERROR( SUM( IF( 'PORTIFÓLIO'!$C$4:$C$564=$A17, N(INDEX('PORTIFÓLIO'!$J$4:$Q$564,,MATCH(F$2,'PORTIFÓLIO'!$J$3:$Q$3,0))) * N('PORTIFÓLIO'!$S$4:$S$564), 0 ) ), 0)} -> 0 | G17: =F17/$F$4 -> 0 | H17: {=IFERROR( SUM( IF( 'PORTIFÓLIO'!$C$4:$C$564=$A17, N(INDEX('PORTIFÓLIO'!$J$4:$Q$564,,MATCH(H$2,'PORTIFÓLIO'!$J$3:$Q$3,0))) * N('PORTIFÓLIO'!$S$4:$S$564), 0 ) ), 0)} -> 0 | I17: =H17/$H$4 -> 0 | J17: {=IFERROR( SUM( IF( 'PORTIFÓLIO'!$C$4:$C$564=$A17, N(INDEX('PORTIFÓLIO'!$J$4:$Q$564,,MATCH(J$2,'PORTIFÓLIO'!$J$3:$Q$3,0))) * N('PORTIFÓLIO'!$S$4:$S$564), 0 ) ), 0)} -> 0 | K17: =J17/$J$4 -> 0 | L17: {=IFERROR( SUM( IF( 'PORTIFÓLIO'!$C$4:$C$564=$A17, N(INDEX('PORTIFÓLIO'!$J$4:$Q$564,,MATCH(L$2,'PORTIFÓLIO'!$J$3:$Q$3,0))) * N('PORTIFÓLIO'!$S$4:$S$564), 0 ) ), 0)} -> 0 | M17: =L17/$L$4 -> 0 | N17: {=IFERROR( SUM( IF( 'PORTIFÓLIO'!$C$4:$C$564=$A17, N(INDEX('PORTIFÓLIO'!$J$4:$Q$564,,MATCH(N$2,'PORTIFÓLIO'!$J$3:$Q$3,0))) * N('PORTIFÓLIO'!$S$4:$S$564), 0 ) ), 0)} -> 0 | O17: =N17/$N$4 -> 0 | P17: {=IFERROR( SUM( IF( 'PORTIFÓLIO'!$C$4:$C$564=$A17, N(INDEX('PORTIFÓLIO'!$J$4:$Q$564,,MATCH(P$2,'PORTIFÓLIO'!$J$3:$Q$3,0))) * N('PORTIFÓLIO'!$S$4:$S$564), 0 ) ), 0)} -> 0 | Q17: =P17/$P$4 -> 0 | R17: =SUM(P17,N17,L17,J17,H17,D17,B17) -> 0 | S17: =R17/$R$4 -> 0
A18: =IFERROR(__xludf.DUMMYFUNCTION("""COMPUTED_VALUE"""),"10-46-00 + S") -> 10-46-00 + S | B18: {=IFERROR( SUM( IF( 'PORTIFÓLIO'!$C$4:$C$564=$A18, N(INDEX('PORTIFÓLIO'!$J$4:$Q$564,,MATCH(B$2,'PORTIFÓLIO'!$J$3:$Q$3,0))) * N('PORTIFÓLIO'!$S$4:$S$564), 0 ) ), 0)} -> 0 | C18: =B18/$B$4 -> 0 | D18: {=IFERROR( SUM( IF( 'PORTIFÓLIO'!$C$4:$C$564=$A18, N(INDEX('PORTIFÓLIO'!$J$4:$Q$564,,MATCH(D$2,'PORTIFÓLIO'!$J$3:$Q$3,0))) * N('PORTIFÓLIO'!$S$4:$S$564), 0 ) ), 0)} -> 0 | E18: =D18/$D$4 -> 0 | F18: {=IFERROR( SUM( IF( 'PORTIFÓLIO'!$C$4:$C$564=$A18, N(INDEX('PORTIFÓLIO'!$J$4:$Q$564,,MATCH(F$2,'PORTIFÓLIO'!$J$3:$Q$3,0))) * N('PORTIFÓLIO'!$S$4:$S$564), 0 ) ), 0)} -> 0 | G18: =F18/$F$4 -> 0 | H18: {=IFERROR( SUM( IF( 'PORTIFÓLIO'!$C$4:$C$564=$A18, N(INDEX('PORTIFÓLIO'!$J$4:$Q$564,,MATCH(H$2,'PORTIFÓLIO'!$J$3:$Q$3,0))) * N('PORTIFÓLIO'!$S$4:$S$564), 0 ) ), 0)} -> 0 | I18: =H18/$H$4 -> 0 | J18: {=IFERROR( SUM( IF( 'PORTIFÓLIO'!$C$4:$C$564=$A18, N(INDEX('PORTIFÓLIO'!$J$4:$Q$564,,MATCH(J$2,'PORTIFÓLIO'!$J$3:$Q$3,0))) * N('PORTIFÓLIO'!$S$4:$S$564), 0 ) ), 0)} -> 0 | K18: =J18/$J$4 -> 0 | L18: {=IFERROR( SUM( IF( 'PORTIFÓLIO'!$C$4:$C$564=$A18, N(INDEX('PORTIFÓLIO'!$J$4:$Q$564,,MATCH(L$2,'PORTIFÓLIO'!$J$3:$Q$3,0))) * N('PORTIFÓLIO'!$S$4:$S$564), 0 ) ), 0)} -> 0 | M18: =L18/$L$4 -> 0 | N18: {=IFERROR( SUM( IF( 'PORTIFÓLIO'!$C$4:$C$564=$A18, N(INDEX('PORTIFÓLIO'!$J$4:$Q$564,,MATCH(N$2,'PORTIFÓLIO'!$J$3:$Q$3,0))) * N('PORTIFÓLIO'!$S$4:$S$564), 0 ) ), 0)} -> 0 | O18: =N18/$N$4 -> 0 | P18: {=IFERROR( SUM( IF( 'PORTIFÓLIO'!$C$4:$C$564=$A18, N(INDEX('PORTIFÓLIO'!$J$4:$Q$564,,MATCH(P$2,'PORTIFÓLIO'!$J$3:$Q$3,0))) * N('PORTIFÓLIO'!$S$4:$S$564), 0 ) ), 0)} -> 0 | Q18: =P18/$P$4 -> 0 | R18: =SUM(P18,N18,L18,J18,H18,D18,B18) -> 0 | S18: =R18/$R$4 -> 0
A19: =IFERROR(__xludf.DUMMYFUNCTION("""COMPUTED_VALUE"""),"08-42-00") -> 08-42-00 | B19: {=IFERROR( SUM( IF( 'PORTIFÓLIO'!$C$4:$C$564=$A19, N(INDEX('PORTIFÓLIO'!$J$4:$Q$564,,MATCH(B$2,'PORTIFÓLIO'!$J$3:$Q$3,0))) * N('PORTIFÓLIO'!$S$4:$S$564), 0 ) ), 0)} -> 0 | C19: =B19/$B$4 -> 0 | D19: {=IFERROR( SUM( IF( 'PORTIFÓLIO'!$C$4:$C$564=$A19, N(INDEX('PORTIFÓLIO'!$J$4:$Q$564,,MATCH(D$2,'PORTIFÓLIO'!$J$3:$Q$3,0))) * N('PORTIFÓLIO'!$S$4:$S$564), 0 ) ), 0)} -> 0 | E19: =D19/$D$4 -> 0 | F19: {=IFERROR( SUM( IF( 'PORTIFÓLIO'!$C$4:$C$564=$A19, N(INDEX('PORTIFÓLIO'!$J$4:$Q$564,,MATCH(F$2,'PORTIFÓLIO'!$J$3:$Q$3,0))) * N('PORTIFÓLIO'!$S$4:$S$564), 0 ) ), 0)} -> 0 | G19: =F19/$F$4 -> 0 | H19: {=IFERROR( SUM( IF( 'PORTIFÓLIO'!$C$4:$C$564=$A19, N(INDEX('PORTIFÓLIO'!$J$4:$Q$564,,MATCH(H$2,'PORTIFÓLIO'!$J$3:$Q$3,0))) * N('PORTIFÓLIO'!$S$4:$S$564), 0 ) ), 0)} -> 0 | I19: =H19/$H$4 -> 0 | J19: {=IFERROR( SUM( IF( 'PORTIFÓLIO'!$C$4:$C$564=$A19, N(INDEX('PORTIFÓLIO'!$J$4:$Q$564,,MATCH(J$2,'PORTIFÓLIO'!$J$3:$Q$3,0))) * N('PORTIFÓLIO'!$S$4:$S$564), 0 ) ), 0)} -> 0 | K19: =J19/$J$4 -> 0 | L19: {=IFERROR( SUM( IF( 'PORTIFÓLIO'!$C$4:$C$564=$A19, N(INDEX('PORTIFÓLIO'!$J$4:$Q$564,,MATCH(L$2,'PORTIFÓLIO'!$J$3:$Q$3,0))) * N('PORTIFÓLIO'!$S$4:$S$564), 0 ) ), 0)} -> 0 | M19: =L19/$L$4 -> 0 | N19: {=IFERROR( SUM( IF( 'PORTIFÓLIO'!$C$4:$C$564=$A19, N(INDEX('PORTIFÓLIO'!$J$4:$Q$564,,MATCH(N$2,'PORTIFÓLIO'!$J$3:$Q$3,0))) * N('PORTIFÓLIO'!$S$4:$S$564), 0 ) ), 0)} -> 0 | O19: =N19/$N$4 -> 0 | P19: {=IFERROR( SUM( IF( 'PORTIFÓLIO'!$C$4:$C$564=$A19, N(INDEX('PORTIFÓLIO'!$J$4:$Q$564,,MATCH(P$2,'PORTIFÓLIO'!$J$3:$Q$3,0))) * N('PORTIFÓLIO'!$S$4:$S$564), 0 ) ), 0)} -> 0 | Q19: =P19/$P$4 -> 0 | R19: =SUM(P19,N19,L19,J19,H19,D19,B19) -> 0 | S19: =R19/$R$4 -> 0
A20: =IFERROR(__xludf.DUMMYFUNCTION("""COMPUTED_VALUE"""),"SSP 21") -> SSP 21 | B20: {=IFERROR( SUM( IF( 'PORTIFÓLIO'!$C$4:$C$564=$A20, N(INDEX('PORTIFÓLIO'!$J$4:$Q$564,,MATCH(B$2,'PORTIFÓLIO'!$J$3:$Q$3,0))) * N('PORTIFÓLIO'!$S$4:$S$564), 0 ) ), 0)} -> 0 | C20: =B20/$B$4 -> 0 | D20: {=IFERROR( SUM( IF( 'PORTIFÓLIO'!$C$4:$C$564=$A20, N(INDEX('PORTIFÓLIO'!$J$4:$Q$564,,MATCH(D$2,'PORTIFÓLIO'!$J$3:$Q$3,0))) * N('PORTIFÓLIO'!$S$4:$S$564), 0 ) ), 0)} -> 0 | E20: =D20/$D$4 -> 0 | F20: {=IFERROR( SUM( IF( 'PORTIFÓLIO'!$C$4:$C$564=$A20, N(INDEX('PORTIFÓLIO'!$J$4:$Q$564,,MATCH(F$2,'PORTIFÓLIO'!$J$3:$Q$3,0))) * N('PORTIFÓLIO'!$S$4:$S$564), 0 ) ), 0)} -> 0 | G20: =F20/$F$4 -> 0 | H20: {=IFERROR( SUM( IF( 'PORTIFÓLIO'!$C$4:$C$564=$A20, N(INDEX('PORTIFÓLIO'!$J$4:$Q$564,,MATCH(H$2,'PORTIFÓLIO'!$J$3:$Q$3,0))) * N('PORTIFÓLIO'!$S$4:$S$564), 0 ) ), 0)} -> 0 | I20: =H20/$H$4 -> 0 | J20: {=IFERROR( SUM( IF( 'PORTIFÓLIO'!$C$4:$C$564=$A20, N(INDEX('PORTIFÓLIO'!$J$4:$Q$564,,MATCH(J$2,'PORTIFÓLIO'!$J$3:$Q$3,0))) * N('PORTIFÓLIO'!$S$4:$S$564), 0 ) ), 0)} -> 0 | K20: =J20/$J$4 -> 0 | L20: {=IFERROR( SUM( IF( 'PORTIFÓLIO'!$C$4:$C$564=$A20, N(INDEX('PORTIFÓLIO'!$J$4:$Q$564,,MATCH(L$2,'PORTIFÓLIO'!$J$3:$Q$3,0))) * N('PORTIFÓLIO'!$S$4:$S$564), 0 ) ), 0)} -> 0 | M20: =L20/$L$4 -> 0 | N20: {=IFERROR( SUM( IF( 'PORTIFÓLIO'!$C$4:$C$564=$A20, N(INDEX('PORTIFÓLIO'!$J$4:$Q$564,,MATCH(N$2,'PORTIFÓLIO'!$J$3:$Q$3,0))) * N('PORTIFÓLIO'!$S$4:$S$564), 0 ) ), 0)} -> 0 | O20: =N20/$N$4 -> 0 | P20: {=IFERROR( SUM( IF( 'PORTIFÓLIO'!$C$4:$C$564=$A20, N(INDEX('PORTIFÓLIO'!$J$4:$Q$564,,MATCH(P$2,'PORTIFÓLIO'!$J$3:$Q$3,0))) * N('PORTIFÓLIO'!$S$4:$S$564), 0 ) ), 0)} -> 0 | Q20: =P20/$P$4 -> 0 | R20: =SUM(P20,N20,L20,J20,H20,D20,B20) -> 0 | S20: =R20/$R$4 -> 0
A21: =IFERROR(__xludf.DUMMYFUNCTION("""COMPUTED_VALUE"""),"03-15-07 +14%CO") -> 03-15-07 +14%CO | B21: {=IFERROR( SUM( IF( 'PORTIFÓLIO'!$C$4:$C$564=$A21, N(INDEX('PORTIFÓLIO'!$J$4:$Q$564,,MATCH(B$2,'PORTIFÓLIO'!$J$3:$Q$3,0))) * N('PORTIFÓLIO'!$S$4:$S$564), 0 ) ), 0)} -> 0 | C21: =B21/$B$4 -> 0 | D21: {=IFERROR( SUM( IF( 'PORTIFÓLIO'!$C$4:$C$564=$A21, N(INDEX('PORTIFÓLIO'!$J$4:$Q$564,,MATCH(D$2,'PORTIFÓLIO'!$J$3:$Q$3,0))) * N('PORTIFÓLIO'!$S$4:$S$564), 0 ) ), 0)} -> 0 | E21: =D21/$D$4 -> 0 | F21: {=IFERROR( SUM( IF( 'PORTIFÓLIO'!$C$4:$C$564=$A21, N(INDEX('PORTIFÓLIO'!$J$4:$Q$564,,MATCH(F$2,'PORTIFÓLIO'!$J$3:$Q$3,0))) * N('PORTIFÓLIO'!$S$4:$S$564), 0 ) ), 0)} -> 0 | G21: =F21/$F$4 -> 0 | H21: {=IFERROR( SUM( IF( 'PORTIFÓLIO'!$C$4:$C$564=$A21, N(INDEX('PORTIFÓLIO'!$J$4:$Q$564,,MATCH(H$2,'PORTIFÓLIO'!$J$3:$Q$3,0))) * N('PORTIFÓLIO'!$S$4:$S$564), 0 ) ), 0)} -> 0 | I21: =H21/$H$4 -> 0 | J21: {=IFERROR( SUM( IF( 'PORTIFÓLIO'!$C$4:$C$564=$A21, N(INDEX('PORTIFÓLIO'!$J$4:$Q$564,,MATCH(J$2,'PORTIFÓLIO'!$J$3:$Q$3,0))) * N('PORTIFÓLIO'!$S$4:$S$564), 0 ) ), 0)} -> 0 | K21: =J21/$J$4 -> 0 | L21: {=IFERROR( SUM( IF( 'PORTIFÓLIO'!$C$4:$C$564=$A21, N(INDEX('PORTIFÓLIO'!$J$4:$Q$564,,MATCH(L$2,'PORTIFÓLIO'!$J$3:$Q$3,0))) * N('PORTIFÓLIO'!$S$4:$S$564), 0 ) ), 0)} -> 0 | M21: =L21/$L$4 -> 0 | N21: {=IFERROR( SUM( IF( 'PORTIFÓLIO'!$C$4:$C$564=$A21, N(INDEX('PORTIFÓLIO'!$J$4:$Q$564,,MATCH(N$2,'PORTIFÓLIO'!$J$3:$Q$3,0))) * N('PORTIFÓLIO'!$S$4:$S$564), 0 ) ), 0)} -> 0 | O21: =N21/$N$4 -> 0 | P21: {=IFERROR( SUM( IF( 'PORTIFÓLIO'!$C$4:$C$564=$A21, N(INDEX('PORTIFÓLIO'!$J$4:$Q$564,,MATCH(P$2,'PORTIFÓLIO'!$J$3:$Q$3,0))) * N('PORTIFÓLIO'!$S$4:$S$564), 0 ) ), 0)} -> 0 | Q21: =P21/$P$4 -> 0 | R21: =SUM(P21,N21,L21,J21,H21,D21,B21) -> 0 | S21: =R21/$R$4 -> 0
A22: =IFERROR(__xludf.DUMMYFUNCTION("""COMPUTED_VALUE"""),"URÉIA") -> URÉIA | B22: {=IFERROR( SUM( IF( 'PORTIFÓLIO'!$C$4:$C$564=$A22, N(INDEX('PORTIFÓLIO'!$J$4:$Q$564,,MATCH(B$2,'PORTIFÓLIO'!$J$3:$Q$3,0))) * N('PORTIFÓLIO'!$S$4:$S$564), 0 ) ), 0)} -> 0 | C22: =B22/$B$4 -> 0 | D22: {=IFERROR( SUM( IF( 'PORTIFÓLIO'!$C$4:$C$564=$A22, N(INDEX('PORTIFÓLIO'!$J$4:$Q$564,,MATCH(D$2,'PORTIFÓLIO'!$J$3:$Q$3,0))) * N('PORTIFÓLIO'!$S$4:$S$564), 0 ) ), 0)} -> 0 | E22: =D22/$D$4 -> 0 | F22: {=IFERROR( SUM( IF( 'PORTIFÓLIO'!$C$4:$C$564=$A22, N(INDEX('PORTIFÓLIO'!$J$4:$Q$564,,MATCH(F$2,'PORTIFÓLIO'!$J$3:$Q$3,0))) * N('PORTIFÓLIO'!$S$4:$S$564), 0 ) ), 0)} -> 0 | G22: =F22/$F$4 -> 0 | H22: {=IFERROR( SUM( IF( 'PORTIFÓLIO'!$C$4:$C$564=$A22, N(INDEX('PORTIFÓLIO'!$J$4:$Q$564,,MATCH(H$2,'PORTIFÓLIO'!$J$3:$Q$3,0))) * N('PORTIFÓLIO'!$S$4:$S$564), 0 ) ), 0)} -> 0 | I22: =H22/$H$4 -> 0 | J22: {=IFERROR( SUM( IF( 'PORTIFÓLIO'!$C$4:$C$564=$A22, N(INDEX('PORTIFÓLIO'!$J$4:$Q$564,,MATCH(J$2,'PORTIFÓLIO'!$J$3:$Q$3,0))) * N('PORTIFÓLIO'!$S$4:$S$564), 0 ) ), 0)} -> 0 | K22: =J22/$J$4 -> 0 | L22: {=IFERROR( SUM( IF( 'PORTIFÓLIO'!$C$4:$C$564=$A22, N(INDEX('PORTIFÓLIO'!$J$4:$Q$564,,MATCH(L$2,'PORTIFÓLIO'!$J$3:$Q$3,0))) * N('PORTIFÓLIO'!$S$4:$S$564), 0 ) ), 0)} -> 0 | M22: =L22/$L$4 -> 0 | N22: {=IFERROR( SUM( IF( 'PORTIFÓLIO'!$C$4:$C$564=$A22, N(INDEX('PORTIFÓLIO'!$J$4:$Q$564,,MATCH(N$2,'PORTIFÓLIO'!$J$3:$Q$3,0))) * N('PORTIFÓLIO'!$S$4:$S$564), 0 ) ), 0)} -> 0 | O22: =N22/$N$4 -> 0 | P22: {=IFERROR( SUM( IF( 'PORTIFÓLIO'!$C$4:$C$564=$A22, N(INDEX('PORTIFÓLIO'!$J$4:$Q$564,,MATCH(P$2,'PORTIFÓLIO'!$J$3:$Q$3,0))) * N('PORTIFÓLIO'!$S$4:$S$564), 0 ) ), 0)} -> 0 | Q22: =P22/$P$4 -> 0 | R22: =SUM(P22,N22,L22,J22,H22,D22,B22) -> 0 | S22: =R22/$R$4 -> 0
A23: =IFERROR(__xludf.DUMMYFUNCTION("""COMPUTED_VALUE"""),"SULFATO DE AMÔNIO") -> SULFATO DE AMÔNIO | B23: {=IFERROR( SUM( IF( 'PORTIFÓLIO'!$C$4:$C$564=$A23, N(INDEX('PORTIFÓLIO'!$J$4:$Q$564,,MATCH(B$2,'PORTIFÓLIO'!$J$3:$Q$3,0))) * N('PORTIFÓLIO'!$S$4:$S$564), 0 ) ), 0)} -> 0 | C23: =B23/$B$4 -> 0 | D23: {=IFERROR( SUM( IF( 'PORTIFÓLIO'!$C$4:$C$564=$A23, N(INDEX('PORTIFÓLIO'!$J$4:$Q$564,,MATCH(D$2,'PORTIFÓLIO'!$J$3:$Q$3,0))) * N('PORTIFÓLIO'!$S$4:$S$564), 0 ) ), 0)} -> 0 | E23: =D23/$D$4 -> 0 | F23: {=IFERROR( SUM( IF( 'PORTIFÓLIO'!$C$4:$C$564=$A23, N(INDEX('PORTIFÓLIO'!$J$4:$Q$564,,MATCH(F$2,'PORTIFÓLIO'!$J$3:$Q$3,0))) * N('PORTIFÓLIO'!$S$4:$S$564), 0 ) ), 0)} -> 0 | G23: =F23/$F$4 -> 0 | H23: {=IFERROR( SUM( IF( 'PORTIFÓLIO'!$C$4:$C$564=$A23, N(INDEX('PORTIFÓLIO'!$J$4:$Q$564,,MATCH(H$2,'PORTIFÓLIO'!$J$3:$Q$3,0))) * N('PORTIFÓLIO'!$S$4:$S$564), 0 ) ), 0)} -> 0 | I23: =H23/$H$4 -> 0 | J23: {=IFERROR( SUM( IF( 'PORTIFÓLIO'!$C$4:$C$564=$A23, N(INDEX('PORTIFÓLIO'!$J$4:$Q$564,,MATCH(J$2,'PORTIFÓLIO'!$J$3:$Q$3,0))) * N('PORTIFÓLIO'!$S$4:$S$564), 0 ) ), 0)} -> 0 | K23: =J23/$J$4 -> 0 | L23: {=IFERROR( SUM( IF( 'PORTIFÓLIO'!$C$4:$C$564=$A23, N(INDEX('PORTIFÓLIO'!$J$4:$Q$564,,MATCH(L$2,'PORTIFÓLIO'!$J$3:$Q$3,0))) * N('PORTIFÓLIO'!$S$4:$S$564), 0 ) ), 0)} -> 0 | M23: =L23/$L$4 -> 0 | N23: {=IFERROR( SUM( IF( 'PORTIFÓLIO'!$C$4:$C$564=$A23, N(INDEX('PORTIFÓLIO'!$J$4:$Q$564,,MATCH(N$2,'PORTIFÓLIO'!$J$3:$Q$3,0))) * N('PORTIFÓLIO'!$S$4:$S$564), 0 ) ), 0)} -> 0 | O23: =N23/$N$4 -> 0 | P23: {=IFERROR( SUM( IF( 'PORTIFÓLIO'!$C$4:$C$564=$A23, N(INDEX('PORTIFÓLIO'!$J$4:$Q$564,,MATCH(P$2,'PORTIFÓLIO'!$J$3:$Q$3,0))) * N('PORTIFÓLIO'!$S$4:$S$564), 0 ) ), 0)} -> 0 | Q23: =P23/$P$4 -> 0 | R23: =SUM(P23,N23,L23,J23,H23,D23,B23) -> 0 | S23: =R23/$R$4 -> 0
A24: =IFERROR(__xludf.DUMMYFUNCTION("""COMPUTED_VALUE"""),"BOROGRAN") -> BOROGRAN | B24: {=IFERROR( SUM( IF( 'PORTIFÓLIO'!$C$4:$C$564=$A24, N(INDEX('PORTIFÓLIO'!$J$4:$Q$564,,MATCH(B$2,'PORTIFÓLIO'!$J$3:$Q$3,0))) * N('PORTIFÓLIO'!$S$4:$S$564), 0 ) ), 0)} -> 0 | C24: =B24/$B$4 -> 0 | D24: {=IFERROR( SUM( IF( 'PORTIFÓLIO'!$C$4:$C$564=$A24, N(INDEX('PORTIFÓLIO'!$J$4:$Q$564,,MATCH(D$2,'PORTIFÓLIO'!$J$3:$Q$3,0))) * N('PORTIFÓLIO'!$S$4:$S$564), 0 ) ), 0)} -> 0 | E24: =D24/$D$4 -> 0 | F24: {=IFERROR( SUM( IF( 'PORTIFÓLIO'!$C$4:$C$564=$A24, N(INDEX('PORTIFÓLIO'!$J$4:$Q$564,,MATCH(F$2,'PORTIFÓLIO'!$J$3:$Q$3,0))) * N('PORTIFÓLIO'!$S$4:$S$564), 0 ) ), 0)} -> 0 | G24: =F24/$F$4 -> 0 | H24: {=IFERROR( SUM( IF( 'PORTIFÓLIO'!$C$4:$C$564=$A24, N(INDEX('PORTIFÓLIO'!$J$4:$Q$564,,MATCH(H$2,'PORTIFÓLIO'!$J$3:$Q$3,0))) * N('PORTIFÓLIO'!$S$4:$S$564), 0 ) ), 0)} -> 0 | I24: =H24/$H$4 -> 0 | J24: {=IFERROR( SUM( IF( 'PORTIFÓLIO'!$C$4:$C$564=$A24, N(INDEX('PORTIFÓLIO'!$J$4:$Q$564,,MATCH(J$2,'PORTIFÓLIO'!$J$3:$Q$3,0))) * N('PORTIFÓLIO'!$S$4:$S$564), 0 ) ), 0)} -> 0 | K24: =J24/$J$4 -> 0 | L24: {=IFERROR( SUM( IF( 'PORTIFÓLIO'!$C$4:$C$564=$A24, N(INDEX('PORTIFÓLIO'!$J$4:$Q$564,,MATCH(L$2,'PORTIFÓLIO'!$J$3:$Q$3,0))) * N('PORTIFÓLIO'!$S$4:$S$564), 0 ) ), 0)} -> 0 | M24: =L24/$L$4 -> 0 | N24: {=IFERROR( SUM( IF( 'PORTIFÓLIO'!$C$4:$C$564=$A24, N(INDEX('PORTIFÓLIO'!$J$4:$Q$564,,MATCH(N$2,'PORTIFÓLIO'!$J$3:$Q$3,0))) * N('PORTIFÓLIO'!$S$4:$S$564), 0 ) ), 0)} -> 0 | O24: =N24/$N$4 -> 0 | P24: {=IFERROR( SUM( IF( 'PORTIFÓLIO'!$C$4:$C$564=$A24, N(INDEX('PORTIFÓLIO'!$J$4:$Q$564,,MATCH(P$2,'PORTIFÓLIO'!$J$3:$Q$3,0))) * N('PORTIFÓLIO'!$S$4:$S$564), 0 ) ), 0)} -> 0 | Q24: =P24/$P$4 -> 0 | R24: =SUM(P24,N24,L24,J24,H24,D24,B24) -> 0 | S24: =R24/$R$4 -> 0
A25: =IFERROR(__xludf.DUMMYFUNCTION("""COMPUTED_VALUE"""),"SUPER DUO") -> SUPER DUO | B25: {=IFERROR( SUM( IF( 'PORTIFÓLIO'!$C$4:$C$564=$A25, N(INDEX('PORTIFÓLIO'!$J$4:$Q$564,,MATCH(B$2,'PORTIFÓLIO'!$J$3:$Q$3,0))) * N('PORTIFÓLIO'!$S$4:$S$564), 0 ) ), 0)} -> 0 | C25: =B25/$B$4 -> 0 | D25: {=IFERROR( SUM( IF( 'PORTIFÓLIO'!$C$4:$C$564=$A25, N(INDEX('PORTIFÓLIO'!$J$4:$Q$564,,MATCH(D$2,'PORTIFÓLIO'!$J$3:$Q$3,0))) * N('PORTIFÓLIO'!$S$4:$S$564), 0 ) ), 0)} -> 0 | E25: =D25/$D$4 -> 0 | F25: {=IFERROR( SUM( IF( 'PORTIFÓLIO'!$C$4:$C$564=$A25, N(INDEX('PORTIFÓLIO'!$J$4:$Q$564,,MATCH(F$2,'PORTIFÓLIO'!$J$3:$Q$3,0))) * N('PORTIFÓLIO'!$S$4:$S$564), 0 ) ), 0)} -> 0 | G25: =F25/$F$4 -> 0 | H25: {=IFERROR( SUM( IF( 'PORTIFÓLIO'!$C$4:$C$564=$A25, N(INDEX('PORTIFÓLIO'!$J$4:$Q$564,,MATCH(H$2,'PORTIFÓLIO'!$J$3:$Q$3,0))) * N('PORTIFÓLIO'!$S$4:$S$564), 0 ) ), 0)} -> 0 | I25: =H25/$H$4 -> 0 | J25: {=IFERROR( SUM( IF( 'PORTIFÓLIO'!$C$4:$C$564=$A25, N(INDEX('PORTIFÓLIO'!$J$4:$Q$564,,MATCH(J$2,'PORTIFÓLIO'!$J$3:$Q$3,0))) * N('PORTIFÓLIO'!$S$4:$S$564), 0 ) ), 0)} -> 0 | K25: =J25/$J$4 -> 0 | L25: {=IFERROR( SUM( IF( 'PORTIFÓLIO'!$C$4:$C$564=$A25, N(INDEX('PORTIFÓLIO'!$J$4:$Q$564,,MATCH(L$2,'PORTIFÓLIO'!$J$3:$Q$3,0))) * N('PORTIFÓLIO'!$S$4:$S$564), 0 ) ), 0)} -> 0 | M25: =L25/$L$4 -> 0 | N25: {=IFERROR( SUM( IF( 'PORTIFÓLIO'!$C$4:$C$564=$A25, N(INDEX('PORTIFÓLIO'!$J$4:$Q$564,,MATCH(N$2,'PORTIFÓLIO'!$J$3:$Q$3,0))) * N('PORTIFÓLIO'!$S$4:$S$564), 0 ) ), 0)} -> 0 | O25: =N25/$N$4 -> 0 | P25: {=IFERROR( SUM( IF( 'PORTIFÓLIO'!$C$4:$C$564=$A25, N(INDEX('PORTIFÓLIO'!$J$4:$Q$564,,MATCH(P$2,'PORTIFÓLIO'!$J$3:$Q$3,0))) * N('PORTIFÓLIO'!$S$4:$S$564), 0 ) ), 0)} -> 0 | Q25: =P25/$P$4 -> 0 | R25: =SUM(P25,N25,L25,J25,H25,D25,B25) -> 0 | S25: =R25/$R$4 -> 0
A26: =IFERROR(__xludf.DUMMYFUNCTION("""COMPUTED_VALUE"""),"08-40-00 - 100M") -> 08-40-00 - 100M | B26: {=IFERROR( SUM( IF( 'PORTIFÓLIO'!$C$4:$C$564=$A26, N(INDEX('PORTIFÓLIO'!$J$4:$Q$564,,MATCH(B$2,'PORTIFÓLIO'!$J$3:$Q$3,0))) * N('PORTIFÓLIO'!$S$4:$S$564), 0 ) ), 0)} -> 0 | C26: =B26/$B$4 -> 0 | D26: {=IFERROR( SUM( IF( 'PORTIFÓLIO'!$C$4:$C$564=$A26, N(INDEX('PORTIFÓLIO'!$J$4:$Q$564,,MATCH(D$2,'PORTIFÓLIO'!$J$3:$Q$3,0))) * N('PORTIFÓLIO'!$S$4:$S$564), 0 ) ), 0)} -> 0 | E26: =D26/$D$4 -> 0 | F26: {=IFERROR( SUM( IF( 'PORTIFÓLIO'!$C$4:$C$564=$A26, N(INDEX('PORTIFÓLIO'!$J$4:$Q$564,,MATCH(F$2,'PORTIFÓLIO'!$J$3:$Q$3,0))) * N('PORTIFÓLIO'!$S$4:$S$564), 0 ) ), 0)} -> 0 | G26: =F26/$F$4 -> 0 | H26: {=IFERROR( SUM( IF( 'PORTIFÓLIO'!$C$4:$C$564=$A26, N(INDEX('PORTIFÓLIO'!$J$4:$Q$564,,MATCH(H$2,'PORTIFÓLIO'!$J$3:$Q$3,0))) * N('PORTIFÓLIO'!$S$4:$S$564), 0 ) ), 0)} -> 0 | I26: =H26/$H$4 -> 0 | J26: {=IFERROR( SUM( IF( 'PORTIFÓLIO'!$C$4:$C$564=$A26, N(INDEX('PORTIFÓLIO'!$J$4:$Q$564,,MATCH(J$2,'PORTIFÓLIO'!$J$3:$Q$3,0))) * N('PORTIFÓLIO'!$S$4:$S$564), 0 ) ), 0)} -> 0 | K26: =J26/$J$4 -> 0 | L26: {=IFERROR( SUM( IF( 'PORTIFÓLIO'!$C$4:$C$564=$A26, N(INDEX('PORTIFÓLIO'!$J$4:$Q$564,,MATCH(L$2,'PORTIFÓLIO'!$J$3:$Q$3,0))) * N('PORTIFÓLIO'!$S$4:$S$564), 0 ) ), 0)} -> 0 | M26: =L26/$L$4 -> 0 | N26: {=IFERROR( SUM( IF( 'PORTIFÓLIO'!$C$4:$C$564=$A26, N(INDEX('PORTIFÓLIO'!$J$4:$Q$564,,MATCH(N$2,'PORTIFÓLIO'!$J$3:$Q$3,0))) * N('PORTIFÓLIO'!$S$4:$S$564), 0 ) ), 0)} -> 0 | O26: =N26/$N$4 -> 0 | P26: {=IFERROR( SUM( IF( 'PORTIFÓLIO'!$C$4:$C$564=$A26, N(INDEX('PORTIFÓLIO'!$J$4:$Q$564,,MATCH(P$2,'PORTIFÓLIO'!$J$3:$Q$3,0))) * N('PORTIFÓLIO'!$S$4:$S$564), 0 ) ), 0)} -> 0 | Q26: =P26/$P$4 -> 0 | R26: =SUM(P26,N26,L26,J26,H26,D26,B26) -> 0 | S26: =R26/$R$4 -> 0
A27: =IFERROR(__xludf.DUMMYFUNCTION("""COMPUTED_VALUE"""),"AURUS 500") -> AURUS 500 | B27: {=IFERROR( SUM( IF( 'PORTIFÓLIO'!$C$4:$C$564=$A27, N(INDEX('PORTIFÓLIO'!$J$4:$Q$564,,MATCH(B$2,'PORTIFÓLIO'!$J$3:$Q$3,0))) * N('PORTIFÓLIO'!$S$4:$S$564), 0 ) ), 0)} -> 0 | C27: =B27/$B$4 -> 0 | D27: {=IFERROR( SUM( IF( 'PORTIFÓLIO'!$C$4:$C$564=$A27, N(INDEX('PORTIFÓLIO'!$J$4:$Q$564,,MATCH(D$2,'PORTIFÓLIO'!$J$3:$Q$3,0))) * N('PORTIFÓLIO'!$S$4:$S$564), 0 ) ), 0)} -> 0 | E27: =D27/$D$4 -> 0 | F27: {=IFERROR( SUM( IF( 'PORTIFÓLIO'!$C$4:$C$564=$A27, N(INDEX('PORTIFÓLIO'!$J$4:$Q$564,,MATCH(F$2,'PORTIFÓLIO'!$J$3:$Q$3,0))) * N('PORTIFÓLIO'!$S$4:$S$564), 0 ) ), 0)} -> 0 | G27: =F27/$F$4 -> 0 | H27: {=IFERROR( SUM( IF( 'PORTIFÓLIO'!$C$4:$C$564=$A27, N(INDEX('PORTIFÓLIO'!$J$4:$Q$564,,MATCH(H$2,'PORTIFÓLIO'!$J$3:$Q$3,0))) * N('PORTIFÓLIO'!$S$4:$S$564), 0 ) ), 0)} -> 0 | I27: =H27/$H$4 -> 0 | J27: {=IFERROR( SUM( IF( 'PORTIFÓLIO'!$C$4:$C$564=$A27, N(INDEX('PORTIFÓLIO'!$J$4:$Q$564,,MATCH(J$2,'PORTIFÓLIO'!$J$3:$Q$3,0))) * N('PORTIFÓLIO'!$S$4:$S$564), 0 ) ), 0)} -> 0 | K27: =J27/$J$4 -> 0 | L27: {=IFERROR( SUM( IF( 'PORTIFÓLIO'!$C$4:$C$564=$A27, N(INDEX('PORTIFÓLIO'!$J$4:$Q$564,,MATCH(L$2,'PORTIFÓLIO'!$J$3:$Q$3,0))) * N('PORTIFÓLIO'!$S$4:$S$564), 0 ) ), 0)} -> 0 | M27: =L27/$L$4 -> 0 | N27: {=IFERROR( SUM( IF( 'PORTIFÓLIO'!$C$4:$C$564=$A27, N(INDEX('PORTIFÓLIO'!$J$4:$Q$564,,MATCH(N$2,'PORTIFÓLIO'!$J$3:$Q$3,0))) * N('PORTIFÓLIO'!$S$4:$S$564), 0 ) ), 0)} -> 0 | O27: =N27/$N$4 -> 0 | P27: {=IFERROR( SUM( IF( 'PORTIFÓLIO'!$C$4:$C$564=$A27, N(INDEX('PORTIFÓLIO'!$J$4:$Q$564,,MATCH(P$2,'PORTIFÓLIO'!$J$3:$Q$3,0))) * N('PORTIFÓLIO'!$S$4:$S$564), 0 ) ), 0)} -> 0 | Q27: =P27/$P$4 -> 0 | R27: =SUM(P27,N27,L27,J27,H27,D27,B27) -> 0 | S27: =R27/$R$4 -> 0
A28: =IFERROR(__xludf.DUMMYFUNCTION("""COMPUTED_VALUE"""),"00-01-00+Cu2 Mn8 Zn7 ") -> 00-01-00+Cu2 Mn8 Zn7 | B28: {=IFERROR( SUM( IF( 'PORTIFÓLIO'!$C$4:$C$564=$A28, N(INDEX('PORTIFÓLIO'!$J$4:$Q$564,,MATCH(B$2,'PORTIFÓLIO'!$J$3:$Q$3,0))) * N('PORTIFÓLIO'!$S$4:$S$564), 0 ) ), 0)} -> 0 | C28: =B28/$B$4 -> 0 | D28: {=IFERROR( SUM( IF( 'PORTIFÓLIO'!$C$4:$C$564=$A28, N(INDEX('PORTIFÓLIO'!$J$4:$Q$564,,MATCH(D$2,'PORTIFÓLIO'!$J$3:$Q$3,0))) * N('PORTIFÓLIO'!$S$4:$S$564), 0 ) ), 0)} -> 0 | E28: =D28/$D$4 -> 0 | F28: {=IFERROR( SUM( IF( 'PORTIFÓLIO'!$C$4:$C$564=$A28, N(INDEX('PORTIFÓLIO'!$J$4:$Q$564,,MATCH(F$2,'PORTIFÓLIO'!$J$3:$Q$3,0))) * N('PORTIFÓLIO'!$S$4:$S$564), 0 ) ), 0)} -> 0 | G28: =F28/$F$4 -> 0 | H28: {=IFERROR( SUM( IF( 'PORTIFÓLIO'!$C$4:$C$564=$A28, N(INDEX('PORTIFÓLIO'!$J$4:$Q$564,,MATCH(H$2,'PORTIFÓLIO'!$J$3:$Q$3,0))) * N('PORTIFÓLIO'!$S$4:$S$564), 0 ) ), 0)} -> 0 | I28: =H28/$H$4 -> 0 | J28: {=IFERROR( SUM( IF( 'PORTIFÓLIO'!$C$4:$C$564=$A28, N(INDEX('PORTIFÓLIO'!$J$4:$Q$564,,MATCH(J$2,'PORTIFÓLIO'!$J$3:$Q$3,0))) * N('PORTIFÓLIO'!$S$4:$S$564), 0 ) ), 0)} -> 0 | K28: =J28/$J$4 -> 0 | L28: {=IFERROR( SUM( IF( 'PORTIFÓLIO'!$C$4:$C$564=$A28, N(INDEX('PORTIFÓLIO'!$J$4:$Q$564,,MATCH(L$2,'PORTIFÓLIO'!$J$3:$Q$3,0))) * N('PORTIFÓLIO'!$S$4:$S$564), 0 ) ), 0)} -> 0 | M28: =L28/$L$4 -> 0 | N28: {=IFERROR( SUM( IF( 'PORTIFÓLIO'!$C$4:$C$564=$A28, N(INDEX('PORTIFÓLIO'!$J$4:$Q$564,,MATCH(N$2,'PORTIFÓLIO'!$J$3:$Q$3,0))) * N('PORTIFÓLIO'!$S$4:$S$564), 0 ) ), 0)} -> 0 | O28: =N28/$N$4 -> 0 | P28: {=IFERROR( SUM( IF( 'PORTIFÓLIO'!$C$4:$C$564=$A28, N(INDEX('PORTIFÓLIO'!$J$4:$Q$564,,MATCH(P$2,'PORTIFÓLIO'!$J$3:$Q$3,0))) * N('PORTIFÓLIO'!$S$4:$S$564), 0 ) ), 0)} -> 0 | Q28: =P28/$P$4 -> 0 | R28: =SUM(P28,N28,L28,J28,H28,D28,B28) -> 0 | S28: =R28/$R$4 -> 0
B29: {=IFERROR( SUM( IF( 'PORTIFÓLIO'!$C$4:$C$564=$A29, N(INDEX('PORTIFÓLIO'!$J$4:$Q$564,,MATCH(B$2,'PORTIFÓLIO'!$J$3:$Q$3,0))) * N('PORTIFÓLIO'!$S$4:$S$564), 0 ) ), 0)} -> 0 | C29: =B29/$B$4 -> 0 | D29: {=IFERROR( SUM( IF( 'PORTIFÓLIO'!$C$4:$C$564=$A29, N(INDEX('PORTIFÓLIO'!$J$4:$Q$564,,MATCH(D$2,'PORTIFÓLIO'!$J$3:$Q$3,0))) * N('PORTIFÓLIO'!$S$4:$S$564), 0 ) ), 0)} -> 0 | E29: =D29/$D$4 -> 0 | F29: {=IFERROR( SUM( IF( 'PORTIFÓLIO'!$C$4:$C$564=$A29, N(INDEX('PORTIFÓLIO'!$J$4:$Q$564,,MATCH(F$2,'PORTIFÓLIO'!$J$3:$Q$3,0))) * N('PORTIFÓLIO'!$S$4:$S$564), 0 ) ), 0)} -> 0 | G29: =F29/$F$4 -> 0 | H29: {=IFERROR( SUM( IF( 'PORTIFÓLIO'!$C$4:$C$564=$A29, N(INDEX('PORTIFÓLIO'!$J$4:$Q$564,,MATCH(H$2,'PORTIFÓLIO'!$J$3:$Q$3,0))) * N('PORTIFÓLIO'!$S$4:$S$564), 0 ) ), 0)} -> 0 | I29: =H29/$H$4 -> 0 | J29: {=IFERROR( SUM( IF( 'PORTIFÓLIO'!$C$4:$C$564=$A29, N(INDEX('PORTIFÓLIO'!$J$4:$Q$564,,MATCH(J$2,'PORTIFÓLIO'!$J$3:$Q$3,0))) * N('PORTIFÓLIO'!$S$4:$S$564), 0 ) ), 0)} -> 0 | K29: =J29/$J$4 -> 0 | L29: {=IFERROR( SUM( IF( 'PORTIFÓLIO'!$C$4:$C$564=$A29, N(INDEX('PORTIFÓLIO'!$J$4:$Q$564,,MATCH(L$2,'PORTIFÓLIO'!$J$3:$Q$3,0))) * N('PORTIFÓLIO'!$S$4:$S$564), 0 ) ), 0)} -> 0 | M29: =L29/$L$4 -> 0 | N29: {=IFERROR( SUM( IF( 'PORTIFÓLIO'!$C$4:$C$564=$A29, N(INDEX('PORTIFÓLIO'!$J$4:$Q$564,,MATCH(N$2,'PORTIFÓLIO'!$J$3:$Q$3,0))) * N('PORTIFÓLIO'!$S$4:$S$564), 0 ) ), 0)} -> 0 | O29: =N29/$N$4 -> 0 | P29: {=IFERROR( SUM( IF( 'PORTIFÓLIO'!$C$4:$C$564=$A29, N(INDEX('PORTIFÓLIO'!$J$4:$Q$564,,MATCH(P$2,'PORTIFÓLIO'!$J$3:$Q$3,0))) * N('PORTIFÓLIO'!$S$4:$S$564), 0 ) ), 0)} -> 0 | Q29: =P29/$P$4 -> 0 | R29: =SUM(P29,N29,L29,J29,H29,D29,B29) -> 0 | S29: =R29/$R$4 -> 0
B30: {=IFERROR( SUM( IF( 'PORTIFÓLIO'!$C$4:$C$564=$A30, N(INDEX('PORTIFÓLIO'!$J$4:$Q$564,,MATCH(B$2,'PORTIFÓLIO'!$J$3:$Q$3,0))) * N('PORTIFÓLIO'!$S$4:$S$564), 0 ) ), 0)} -> 0 | C30: =B30/$B$4 -> 0 | D30: {=IFERROR( SUM( IF( 'PORTIFÓLIO'!$C$4:$C$564=$A30, N(INDEX('PORTIFÓLIO'!$J$4:$Q$564,,MATCH(D$2,'PORTIFÓLIO'!$J$3:$Q$3,0))) * N('PORTIFÓLIO'!$S$4:$S$564), 0 ) ), 0)} -> 0 | E30: =D30/$D$4 -> 0 | F30: {=IFERROR( SUM( IF( 'PORTIFÓLIO'!$C$4:$C$564=$A30, N(INDEX('PORTIFÓLIO'!$J$4:$Q$564,,MATCH(F$2,'PORTIFÓLIO'!$J$3:$Q$3,0))) * N('PORTIFÓLIO'!$S$4:$S$564), 0 ) ), 0)} -> 0 | G30: =F30/$F$4 -> 0 | H30: {=IFERROR( SUM( IF( 'PORTIFÓLIO'!$C$4:$C$564=$A30, N(INDEX('PORTIFÓLIO'!$J$4:$Q$564,,MATCH(H$2,'PORTIFÓLIO'!$J$3:$Q$3,0))) * N('PORTIFÓLIO'!$S$4:$S$564), 0 ) ), 0)} -> 0 | I30: =H30/$H$4 -> 0 | J30: {=IFERROR( SUM( IF( 'PORTIFÓLIO'!$C$4:$C$564=$A30, N(INDEX('PORTIFÓLIO'!$J$4:$Q$564,,MATCH(J$2,'PORTIFÓLIO'!$J$3:$Q$3,0))) * N('PORTIFÓLIO'!$S$4:$S$564), 0 ) ), 0)} -> 0 | K30: =J30/$J$4 -> 0 | L30: {=IFERROR( SUM( IF( 'PORTIFÓLIO'!$C$4:$C$564=$A30, N(INDEX('PORTIFÓLIO'!$J$4:$Q$564,,MATCH(L$2,'PORTIFÓLIO'!$J$3:$Q$3,0))) * N('PORTIFÓLIO'!$S$4:$S$564), 0 ) ), 0)} -> 0 | M30: =L30/$L$4 -> 0 | N30: {=IFERROR( SUM( IF( 'PORTIFÓLIO'!$C$4:$C$564=$A30, N(INDEX('PORTIFÓLIO'!$J$4:$Q$564,,MATCH(N$2,'PORTIFÓLIO'!$J$3:$Q$3,0))) * N('PORTIFÓLIO'!$S$4:$S$564), 0 ) ), 0)} -> 0 | O30: =N30/$N$4 -> 0 | P30: {=IFERROR( SUM( IF( 'PORTIFÓLIO'!$C$4:$C$564=$A30, N(INDEX('PORTIFÓLIO'!$J$4:$Q$564,,MATCH(P$2,'PORTIFÓLIO'!$J$3:$Q$3,0))) * N('PORTIFÓLIO'!$S$4:$S$564), 0 ) ), 0)} -> 0 | Q30: =P30/$P$4 -> 0 | R30: =SUM(P30,N30,L30,J30,H30,D30,B30) -> 0 | S30: =R30/$R$4 -> 0
B31: {=IFERROR( SUM( IF( 'PORTIFÓLIO'!$C$4:$C$564=$A31, N(INDEX('PORTIFÓLIO'!$J$4:$Q$564,,MATCH(B$2,'PORTIFÓLIO'!$J$3:$Q$3,0))) * N('PORTIFÓLIO'!$S$4:$S$564), 0 ) ), 0)} -> 0 | C31: =B31/$B$4 -> 0 | D31: {=IFERROR( SUM( IF( 'PORTIFÓLIO'!$C$4:$C$564=$A31, N(INDEX('PORTIFÓLIO'!$J$4:$Q$564,,MATCH(D$2,'PORTIFÓLIO'!$J$3:$Q$3,0))) * N('PORTIFÓLIO'!$S$4:$S$564), 0 ) ), 0)} -> 0 | E31: =D31/$D$4 -> 0 | F31: {=IFERROR( SUM( IF( 'PORTIFÓLIO'!$C$4:$C$564=$A31, N(INDEX('PORTIFÓLIO'!$J$4:$Q$564,,MATCH(F$2,'PORTIFÓLIO'!$J$3:$Q$3,0))) * N('PORTIFÓLIO'!$S$4:$S$564), 0 ) ), 0)} -> 0 | G31: =F31/$F$4 -> 0 | H31: {=IFERROR( SUM( IF( 'PORTIFÓLIO'!$C$4:$C$564=$A31, N(INDEX('PORTIFÓLIO'!$J$4:$Q$564,,MATCH(H$2,'PORTIFÓLIO'!$J$3:$Q$3,0))) * N('PORTIFÓLIO'!$S$4:$S$564), 0 ) ), 0)} -> 0 | I31: =H31/$H$4 -> 0 | J31: {=IFERROR( SUM( IF( 'PORTIFÓLIO'!$C$4:$C$564=$A31, N(INDEX('PORTIFÓLIO'!$J$4:$Q$564,,MATCH(J$2,'PORTIFÓLIO'!$J$3:$Q$3,0))) * N('PORTIFÓLIO'!$S$4:$S$564), 0 ) ), 0)} -> 0 | K31: =J31/$J$4 -> 0 | L31: {=IFERROR( SUM( IF( 'PORTIFÓLIO'!$C$4:$C$564=$A31, N(INDEX('PORTIFÓLIO'!$J$4:$Q$564,,MATCH(L$2,'PORTIFÓLIO'!$J$3:$Q$3,0))) * N('PORTIFÓLIO'!$S$4:$S$564), 0 ) ), 0)} -> 0 | M31: =L31/$L$4 -> 0 | N31: {=IFERROR( SUM( IF( 'PORTIFÓLIO'!$C$4:$C$564=$A31, N(INDEX('PORTIFÓLIO'!$J$4:$Q$564,,MATCH(N$2,'PORTIFÓLIO'!$J$3:$Q$3,0))) * N('PORTIFÓLIO'!$S$4:$S$564), 0 ) ), 0)} -> 0 | O31: =N31/$N$4 -> 0 | P31: {=IFERROR( SUM( IF( 'PORTIFÓLIO'!$C$4:$C$564=$A31, N(INDEX('PORTIFÓLIO'!$J$4:$Q$564,,MATCH(P$2,'PORTIFÓLIO'!$J$3:$Q$3,0))) * N('PORTIFÓLIO'!$S$4:$S$564), 0 ) ), 0)} -> 0 | Q31: =P31/$P$4 -> 0 | R31: =SUM(P31,N31,L31,J31,H31,D31,B31) -> 0 | S31: =R31/$R$4 -> 0
A32: HERBICIDA | B32: =SUM(B33:B103) -> 98198.083 | C32: =B32/$B$4 -> 200.40425 | D32: =SUM(D33:D103) -> 101811.05 | E32: =D32/$D$4 -> 339.37016 | F32: =SUM(F33:F103) -> 69302.179 | G32: =F32/$F$4 -> 315.00991 | H32: =SUM(H33:H103) -> 34862.306 | I32: =H32/$H$4 -> 174.31153 | J32: =SUM(J33:J103) -> 64304.392 | K32: =J32/$J$4 -> 171.02232 | L32: =SUM(L33:L103) -> 47965.412 | M32: =L32/$L$4 -> 218.0246 | N32: =SUM(N33:N103) -> 351095.66 | O32: =N32/$N$4 -> 288.25588 | P32: =SUM(P33:P103) -> 101217.24 | Q32: =P32/$P$4 -> 316.30389 | R32: =SUM(P32,N32,L32,J32,H32,D32,B32) -> 799454.15 | S32: =R32/$R$4 -> 239.07122
A33: =IFERROR(__xludf.DUMMYFUNCTION("UNIQUE(FILTER('PORTIFÓLIO'!C:C, 'PORTIFÓLIO'!B:B=""HERBICIDA""))"),"AMINOL 806") -> AMINOL 806 | B33: {=IFERROR( SUM( IF( 'PORTIFÓLIO'!$C$4:$C$564=$A33, N(INDEX('PORTIFÓLIO'!$J$4:$Q$564,,MATCH(B$2,'PORTIFÓLIO'!$J$3:$Q$3,0))) * N('PORTIFÓLIO'!$S$4:$S$564), 0 ) ), 0)} -> 8912.708 | C33: =B33/$B$4 -> 18.1892 | D33: {=IFERROR( SUM( IF( 'PORTIFÓLIO'!$C$4:$C$564=$A33, N(INDEX('PORTIFÓLIO'!$J$4:$Q$564,,MATCH(D$2,'PORTIFÓLIO'!$J$3:$Q$3,0))) * N('PORTIFÓLIO'!$S$4:$S$564), 0 ) ), 0)} -> 0 | E33: =D33/$D$4 -> 0 | F33: {=IFERROR( SUM( IF( 'PORTIFÓLIO'!$C$4:$C$564=$A33, N(INDEX('PORTIFÓLIO'!$J$4:$Q$564,,MATCH(F$2,'PORTIFÓLIO'!$J$3:$Q$3,0))) * N('PORTIFÓLIO'!$S$4:$S$564), 0 ) ), 0)} -> 0 | G33: =F33/$F$4 -> 0 | H33: {=IFERROR( SUM( IF( 'PORTIFÓLIO'!$C$4:$C$564=$A33, N(INDEX('PORTIFÓLIO'!$J$4:$Q$564,,MATCH(H$2,'PORTIFÓLIO'!$J$3:$Q$3,0))) * N('PORTIFÓLIO'!$S$4:$S$564), 0 ) ), 0)} -> 0 | I33: =H33/$H$4 -> 0 | J33: {=IFERROR( SUM( IF( 'PORTIFÓLIO'!$C$4:$C$564=$A33, N(INDEX('PORTIFÓLIO'!$J$4:$Q$564,,MATCH(J$2,'PORTIFÓLIO'!$J$3:$Q$3,0))) * N('PORTIFÓLIO'!$S$4:$S$564), 0 ) ), 0)} -> 0 | K33: =J33/$J$4 -> 0 | L33: {=IFERROR( SUM( IF( 'PORTIFÓLIO'!$C$4:$C$564=$A33, N(INDEX('PORTIFÓLIO'!$J$4:$Q$564,,MATCH(L$2,'PORTIFÓLIO'!$J$3:$Q$3,0))) * N('PORTIFÓLIO'!$S$4:$S$564), 0 ) ), 0)} -> 0 | M33: =L33/$L$4 -> 0 | N33: {=IFERROR( SUM( IF( 'PORTIFÓLIO'!$C$4:$C$564=$A33, N(INDEX('PORTIFÓLIO'!$J$4:$Q$564,,MATCH(N$2,'PORTIFÓLIO'!$J$3:$Q$3,0))) * N('PORTIFÓLIO'!$S$4:$S$564), 0 ) ), 0)} -> 0 | O33: =N33/$N$4 -> 0 | P33: {=IFERROR( SUM( IF( 'PORTIFÓLIO'!$C$4:$C$564=$A33, N(INDEX('PORTIFÓLIO'!$J$4:$Q$564,,MATCH(P$2,'PORTIFÓLIO'!$J$3:$Q$3,0))) * N('PORTIFÓLIO'!$S$4:$S$564), 0 ) ), 0)} -> 0 | Q33: =P33/$P$4 -> 0 | R33: =SUM(P33,N33,L33,J33,H33,D33,B33) -> 8912.708 | S33: =R33/$R$4 -> 2.6652835
A34: =IFERROR(__xludf.DUMMYFUNCTION("""COMPUTED_VALUE"""),"APRESA") -> APRESA | B34: {=IFERROR( SUM( IF( 'PORTIFÓLIO'!$C$4:$C$564=$A34, N(INDEX('PORTIFÓLIO'!$J$4:$Q$564,,MATCH(B$2,'PORTIFÓLIO'!$J$3:$Q$3,0))) * N('PORTIFÓLIO'!$S$4:$S$564), 0 ) ), 0)} -> 0 | C34: =B34/$B$4 -> 0 | D34: {=IFERROR( SUM( IF( 'PORTIFÓLIO'!$C$4:$C$564=$A34, N(INDEX('PORTIFÓLIO'!$J$4:$Q$564,,MATCH(D$2,'PORTIFÓLIO'!$J$3:$Q$3,0))) * N('PORTIFÓLIO'!$S$4:$S$564), 0 ) ), 0)} -> 0 | E34: =D34/$D$4 -> 0 | F34: {=IFERROR( SUM( IF( 'PORTIFÓLIO'!$C$4:$C$564=$A34, N(INDEX('PORTIFÓLIO'!$J$4:$Q$564,,MATCH(F$2,'PORTIFÓLIO'!$J$3:$Q$3,0))) * N('PORTIFÓLIO'!$S$4:$S$564), 0 ) ), 0)} -> 0 | G34: =F34/$F$4 -> 0 | H34: {=IFERROR( SUM( IF( 'PORTIFÓLIO'!$C$4:$C$564=$A34, N(INDEX('PORTIFÓLIO'!$J$4:$Q$564,,MATCH(H$2,'PORTIFÓLIO'!$J$3:$Q$3,0))) * N('PORTIFÓLIO'!$S$4:$S$564), 0 ) ), 0)} -> 0 | I34: =H34/$H$4 -> 0 | J34: {=IFERROR( SUM( IF( 'PORTIFÓLIO'!$C$4:$C$564=$A34, N(INDEX('PORTIFÓLIO'!$J$4:$Q$564,,MATCH(J$2,'PORTIFÓLIO'!$J$3:$Q$3,0))) * N('PORTIFÓLIO'!$S$4:$S$564), 0 ) ), 0)} -> 0 | K34: =J34/$J$4 -> 0 | L34: {=IFERROR( SUM( IF( 'PORTIFÓLIO'!$C$4:$C$564=$A34, N(INDEX('PORTIFÓLIO'!$J$4:$Q$564,,MATCH(L$2,'PORTIFÓLIO'!$J$3:$Q$3,0))) * N('PORTIFÓLIO'!$S$4:$S$564), 0 ) ), 0)} -> 0 | M34: =L34/$L$4 -> 0 | N34: {=IFERROR( SUM( IF( 'PORTIFÓLIO'!$C$4:$C$564=$A34, N(INDEX('PORTIFÓLIO'!$J$4:$Q$564,,MATCH(N$2,'PORTIFÓLIO'!$J$3:$Q$3,0))) * N('PORTIFÓLIO'!$S$4:$S$564), 0 ) ), 0)} -> 0 | O34: =N34/$N$4 -> 0 | P34: {=IFERROR( SUM( IF( 'PORTIFÓLIO'!$C$4:$C$564=$A34, N(INDEX('PORTIFÓLIO'!$J$4:$Q$564,,MATCH(P$2,'PORTIFÓLIO'!$J$3:$Q$3,0))) * N('PORTIFÓLIO'!$S$4:$S$564), 0 ) ), 0)} -> 0 | Q34: =P34/$P$4 -> 0 | R34: =SUM(P34,N34,L34,J34,H34,D34,B34) -> 0 | S34: =R34/$R$4 -> 0
A35: =IFERROR(__xludf.DUMMYFUNCTION("""COMPUTED_VALUE"""),"ARADDO") -> ARADDO | B35: {=IFERROR( SUM( IF( 'PORTIFÓLIO'!$C$4:$C$564=$A35, N(INDEX('PORTIFÓLIO'!$J$4:$Q$564,,MATCH(B$2,'PORTIFÓLIO'!$J$3:$Q$3,0))) * N('PORTIFÓLIO'!$S$4:$S$564), 0 ) ), 0)} -> 0 | C35: =B35/$B$4 -> 0 | D35: {=IFERROR( SUM( IF( 'PORTIFÓLIO'!$C$4:$C$564=$A35, N(INDEX('PORTIFÓLIO'!$J$4:$Q$564,,MATCH(D$2,'PORTIFÓLIO'!$J$3:$Q$3,0))) * N('PORTIFÓLIO'!$S$4:$S$564), 0 ) ), 0)} -> 18014.682 | E35: =D35/$D$4 -> 60.04894 | F35: {=IFERROR( SUM( IF( 'PORTIFÓLIO'!$C$4:$C$564=$A35, N(INDEX('PORTIFÓLIO'!$J$4:$Q$564,,MATCH(F$2,'PORTIFÓLIO'!$J$3:$Q$3,0))) * N('PORTIFÓLIO'!$S$4:$S$564), 0 ) ), 0)} -> 13210.767 | G35: =F35/$F$4 -> 60.04894 | H35: {=IFERROR( SUM( IF( 'PORTIFÓLIO'!$C$4:$C$564=$A35, N(INDEX('PORTIFÓLIO'!$J$4:$Q$564,,MATCH(H$2,'PORTIFÓLIO'!$J$3:$Q$3,0))) * N('PORTIFÓLIO'!$S$4:$S$564), 0 ) ), 0)} -> 0 | I35: =H35/$H$4 -> 0 | J35: {=IFERROR( SUM( IF( 'PORTIFÓLIO'!$C$4:$C$564=$A35, N(INDEX('PORTIFÓLIO'!$J$4:$Q$564,,MATCH(J$2,'PORTIFÓLIO'!$J$3:$Q$3,0))) * N('PORTIFÓLIO'!$S$4:$S$564), 0 ) ), 0)} -> 0 | K35: =J35/$J$4 -> 0 | L35: {=IFERROR( SUM( IF( 'PORTIFÓLIO'!$C$4:$C$564=$A35, N(INDEX('PORTIFÓLIO'!$J$4:$Q$564,,MATCH(L$2,'PORTIFÓLIO'!$J$3:$Q$3,0))) * N('PORTIFÓLIO'!$S$4:$S$564), 0 ) ), 0)} -> 0 | M35: =L35/$L$4 -> 0 | N35: {=IFERROR( SUM( IF( 'PORTIFÓLIO'!$C$4:$C$564=$A35, N(INDEX('PORTIFÓLIO'!$J$4:$Q$564,,MATCH(N$2,'PORTIFÓLIO'!$J$3:$Q$3,0))) * N('PORTIFÓLIO'!$S$4:$S$564), 0 ) ), 0)} -> 22182.078 | O35: =N35/$N$4 -> 18.211887 | P35: {=IFERROR( SUM( IF( 'PORTIFÓLIO'!$C$4:$C$564=$A35, N(INDEX('PORTIFÓLIO'!$J$4:$Q$564,,MATCH(P$2,'PORTIFÓLIO'!$J$3:$Q$3,0))) * N('PORTIFÓLIO'!$S$4:$S$564), 0 ) ), 0)} -> 18615.171 | Q35: =P35/$P$4 -> 58.172411 | R35: =SUM(P35,N35,L35,J35,H35,D35,B35) -> 58811.932 | S35: =R35/$R$4 -> 17.5873
A36: =IFERROR(__xludf.DUMMYFUNCTION("""COMPUTED_VALUE"""),"CHEVAL") -> CHEVAL | B36: {=IFERROR( SUM( IF( 'PORTIFÓLIO'!$C$4:$C$564=$A36, N(INDEX('PORTIFÓLIO'!$J$4:$Q$564,,MATCH(B$2,'PORTIFÓLIO'!$J$3:$Q$3,0))) * N('PORTIFÓLIO'!$S$4:$S$564), 0 ) ), 0)} -> 0 | C36: =B36/$B$4 -> 0 | D36: {=IFERROR( SUM( IF( 'PORTIFÓLIO'!$C$4:$C$564=$A36, N(INDEX('PORTIFÓLIO'!$J$4:$Q$564,,MATCH(D$2,'PORTIFÓLIO'!$J$3:$Q$3,0))) * N('PORTIFÓLIO'!$S$4:$S$564), 0 ) ), 0)} -> 0 | E36: =D36/$D$4 -> 0 | F36: {=IFERROR( SUM( IF( 'PORTIFÓLIO'!$C$4:$C$564=$A36, N(INDEX('PORTIFÓLIO'!$J$4:$Q$564,,MATCH(F$2,'PORTIFÓLIO'!$J$3:$Q$3,0))) * N('PORTIFÓLIO'!$S$4:$S$564), 0 ) ), 0)} -> 0 | G36: =F36/$F$4 -> 0 | H36: {=IFERROR( SUM( IF( 'PORTIFÓLIO'!$C$4:$C$564=$A36, N(INDEX('PORTIFÓLIO'!$J$4:$Q$564,,MATCH(H$2,'PORTIFÓLIO'!$J$3:$Q$3,0))) * N('PORTIFÓLIO'!$S$4:$S$564), 0 ) ), 0)} -> 0 | I36: =H36/$H$4 -> 0 | J36: {=IFERROR( SUM( IF( 'PORTIFÓLIO'!$C$4:$C$564=$A36, N(INDEX('PORTIFÓLIO'!$J$4:$Q$564,,MATCH(J$2,'PORTIFÓLIO'!$J$3:$Q$3,0))) * N('PORTIFÓLIO'!$S$4:$S$564), 0 ) ), 0)} -> 0 | K36: =J36/$J$4 -> 0 | L36: {=IFERROR( SUM( IF( 'PORTIFÓLIO'!$C$4:$C$564=$A36, N(INDEX('PORTIFÓLIO'!$J$4:$Q$564,,MATCH(L$2,'PORTIFÓLIO'!$J$3:$Q$3,0))) * N('PORTIFÓLIO'!$S$4:$S$564), 0 ) ), 0)} -> 0 | M36: =L36/$L$4 -> 0 | N36: {=IFERROR( SUM( IF( 'PORTIFÓLIO'!$C$4:$C$564=$A36, N(INDEX('PORTIFÓLIO'!$J$4:$Q$564,,MATCH(N$2,'PORTIFÓLIO'!$J$3:$Q$3,0))) * N('PORTIFÓLIO'!$S$4:$S$564), 0 ) ), 0)} -> 0 | O36: =N36/$N$4 -> 0 | P36: {=IFERROR( SUM( IF( 'PORTIFÓLIO'!$C$4:$C$564=$A36, N(INDEX('PORTIFÓLIO'!$J$4:$Q$564,,MATCH(P$2,'PORTIFÓLIO'!$J$3:$Q$3,0))) * N('PORTIFÓLIO'!$S$4:$S$564), 0 ) ), 0)} -> 0 | Q36: =P36/$P$4 -> 0 | R36: =SUM(P36,N36,L36,J36,H36,D36,B36) -> 0 | S36: =R36/$R$4 -> 0
A37: =IFERROR(__xludf.DUMMYFUNCTION("""COMPUTED_VALUE"""),"POQUER") -> POQUER | B37: {=IFERROR( SUM( IF( 'PORTIFÓLIO'!$C$4:$C$564=$A37, N(INDEX('PORTIFÓLIO'!$J$4:$Q$564,,MATCH(B$2,'PORTIFÓLIO'!$J$3:$Q$3,0))) * N('PORTIFÓLIO'!$S$4:$S$564), 0 ) ), 0)} -> 0 | C37: =B37/$B$4 -> 0 | D37: {=IFERROR( SUM( IF( 'PORTIFÓLIO'!$C$4:$C$564=$A37, N(INDEX('PORTIFÓLIO'!$J$4:$Q$564,,MATCH(D$2,'PORTIFÓLIO'!$J$3:$Q$3,0))) * N('PORTIFÓLIO'!$S$4:$S$564), 0 ) ), 0)} -> 3169.0502 | E37: =D37/$D$4 -> 10.563501 | F37: {=IFERROR( SUM( IF( 'PORTIFÓLIO'!$C$4:$C$564=$A37, N(INDEX('PORTIFÓLIO'!$J$4:$Q$564,,MATCH(F$2,'PORTIFÓLIO'!$J$3:$Q$3,0))) * N('PORTIFÓLIO'!$S$4:$S$564), 0 ) ), 0)} -> 2904.9627 | G37: =F37/$F$4 -> 13.204376 | H37: {=IFERROR( SUM( IF( 'PORTIFÓLIO'!$C$4:$C$564=$A37, N(INDEX('PORTIFÓLIO'!$J$4:$Q$564,,MATCH(H$2,'PORTIFÓLIO'!$J$3:$Q$3,0))) * N('PORTIFÓLIO'!$S$4:$S$564), 0 ) ), 0)} -> 0 | I37: =H37/$H$4 -> 0 | J37: {=IFERROR( SUM( IF( 'PORTIFÓLIO'!$C$4:$C$564=$A37, N(INDEX('PORTIFÓLIO'!$J$4:$Q$564,,MATCH(J$2,'PORTIFÓLIO'!$J$3:$Q$3,0))) * N('PORTIFÓLIO'!$S$4:$S$564), 0 ) ), 0)} -> 0 | K37: =J37/$J$4 -> 0 | L37: {=IFERROR( SUM( IF( 'PORTIFÓLIO'!$C$4:$C$564=$A37, N(INDEX('PORTIFÓLIO'!$J$4:$Q$564,,MATCH(L$2,'PORTIFÓLIO'!$J$3:$Q$3,0))) * N('PORTIFÓLIO'!$S$4:$S$564), 0 ) ), 0)} -> 0 | M37: =L37/$L$4 -> 0 | N37: {=IFERROR( SUM( IF( 'PORTIFÓLIO'!$C$4:$C$564=$A37, N(INDEX('PORTIFÓLIO'!$J$4:$Q$564,,MATCH(N$2,'PORTIFÓLIO'!$J$3:$Q$3,0))) * N('PORTIFÓLIO'!$S$4:$S$564), 0 ) ), 0)} -> 0 | O37: =N37/$N$4 -> 0 | P37: {=IFERROR( SUM( IF( 'PORTIFÓLIO'!$C$4:$C$564=$A37, N(INDEX('PORTIFÓLIO'!$J$4:$Q$564,,MATCH(P$2,'PORTIFÓLIO'!$J$3:$Q$3,0))) * N('PORTIFÓLIO'!$S$4:$S$564), 0 ) ), 0)} -> 0 | Q37: =P37/$P$4 -> 0 | R37: =SUM(P37,N37,L37,J37,H37,D37,B37) -> 3169.0502 | S37: =R37/$R$4 -> 0.94768249
A38: =IFERROR(__xludf.DUMMYFUNCTION("""COMPUTED_VALUE"""),"PREMERLIN 600 EC") -> PREMERLIN 600 EC | B38: {=IFERROR( SUM( IF( 'PORTIFÓLIO'!$C$4:$C$564=$A38, N(INDEX('PORTIFÓLIO'!$J$4:$Q$564,,MATCH(B$2,'PORTIFÓLIO'!$J$3:$Q$3,0))) * N('PORTIFÓLIO'!$S$4:$S$564), 0 ) ), 0)} -> 0 | C38: =B38/$B$4 -> 0 | D38: {=IFERROR( SUM( IF( 'PORTIFÓLIO'!$C$4:$C$564=$A38, N(INDEX('PORTIFÓLIO'!$J$4:$Q$564,,MATCH(D$2,'PORTIFÓLIO'!$J$3:$Q$3,0))) * N('PORTIFÓLIO'!$S$4:$S$564), 0 ) ), 0)} -> 0 | E38: =D38/$D$4 -> 0 | F38: {=IFERROR( SUM( IF( 'PORTIFÓLIO'!$C$4:$C$564=$A38, N(INDEX('PORTIFÓLIO'!$J$4:$Q$564,,MATCH(F$2,'PORTIFÓLIO'!$J$3:$Q$3,0))) * N('PORTIFÓLIO'!$S$4:$S$564), 0 ) ), 0)} -> 0 | G38: =F38/$F$4 -> 0 | H38: {=IFERROR( SUM( IF( 'PORTIFÓLIO'!$C$4:$C$564=$A38, N(INDEX('PORTIFÓLIO'!$J$4:$Q$564,,MATCH(H$2,'PORTIFÓLIO'!$J$3:$Q$3,0))) * N('PORTIFÓLIO'!$S$4:$S$564), 0 ) ), 0)} -> 0 | I38: =H38/$H$4 -> 0 | J38: {=IFERROR( SUM( IF( 'PORTIFÓLIO'!$C$4:$C$564=$A38, N(INDEX('PORTIFÓLIO'!$J$4:$Q$564,,MATCH(J$2,'PORTIFÓLIO'!$J$3:$Q$3,0))) * N('PORTIFÓLIO'!$S$4:$S$564), 0 ) ), 0)} -> 0 | K38: =J38/$J$4 -> 0 | L38: {=IFERROR( SUM( IF( 'PORTIFÓLIO'!$C$4:$C$564=$A38, N(INDEX('PORTIFÓLIO'!$J$4:$Q$564,,MATCH(L$2,'PORTIFÓLIO'!$J$3:$Q$3,0))) * N('PORTIFÓLIO'!$S$4:$S$564), 0 ) ), 0)} -> 0 | M38: =L38/$L$4 -> 0 | N38: {=IFERROR( SUM( IF( 'PORTIFÓLIO'!$C$4:$C$564=$A38, N(INDEX('PORTIFÓLIO'!$J$4:$Q$564,,MATCH(N$2,'PORTIFÓLIO'!$J$3:$Q$3,0))) * N('PORTIFÓLIO'!$S$4:$S$564), 0 ) ), 0)} -> 0 | O38: =N38/$N$4 -> 0 | P38: {=IFERROR( SUM( IF( 'PORTIFÓLIO'!$C$4:$C$564=$A38, N(INDEX('PORTIFÓLIO'!$J$4:$Q$564,,MATCH(P$2,'PORTIFÓLIO'!$J$3:$Q$3,0))) * N('PORTIFÓLIO'!$S$4:$S$564), 0 ) ), 0)} -> 0 | Q38: =P38/$P$4 -> 0 | R38: =SUM(P38,N38,L38,J38,H38,D38,B38) -> 0 | S38: =R38/$R$4 -> 0
A39: =IFERROR(__xludf.DUMMYFUNCTION("""COMPUTED_VALUE"""),"AMPLO") -> AMPLO | B39: {=IFERROR( SUM( IF( 'PORTIFÓLIO'!$C$4:$C$564=$A39, N(INDEX('PORTIFÓLIO'!$J$4:$Q$564,,MATCH(B$2,'PORTIFÓLIO'!$J$3:$Q$3,0))) * N('PORTIFÓLIO'!$S$4:$S$564), 0 ) ), 0)} -> 0 | C39: =B39/$B$4 -> 0 | D39: {=IFERROR( SUM( IF( 'PORTIFÓLIO'!$C$4:$C$564=$A39, N(INDEX('PORTIFÓLIO'!$J$4:$Q$564,,MATCH(D$2,'PORTIFÓLIO'!$J$3:$Q$3,0))) * N('PORTIFÓLIO'!$S$4:$S$564), 0 ) ), 0)} -> 0 | E39: =D39/$D$4 -> 0 | F39: {=IFERROR( SUM( IF( 'PORTIFÓLIO'!$C$4:$C$564=$A39, N(INDEX('PORTIFÓLIO'!$J$4:$Q$564,,MATCH(F$2,'PORTIFÓLIO'!$J$3:$Q$3,0))) * N('PORTIFÓLIO'!$S$4:$S$564), 0 ) ), 0)} -> 0 | G39: =F39/$F$4 -> 0 | H39: {=IFERROR( SUM( IF( 'PORTIFÓLIO'!$C$4:$C$564=$A39, N(INDEX('PORTIFÓLIO'!$J$4:$Q$564,,MATCH(H$2,'PORTIFÓLIO'!$J$3:$Q$3,0))) * N('PORTIFÓLIO'!$S$4:$S$564), 0 ) ), 0)} -> 0 | I39: =H39/$H$4 -> 0 | J39: {=IFERROR( SUM( IF( 'PORTIFÓLIO'!$C$4:$C$564=$A39, N(INDEX('PORTIFÓLIO'!$J$4:$Q$564,,MATCH(J$2,'PORTIFÓLIO'!$J$3:$Q$3,0))) * N('PORTIFÓLIO'!$S$4:$S$564), 0 ) ), 0)} -> 0 | K39: =J39/$J$4 -> 0 | L39: {=IFERROR( SUM( IF( 'PORTIFÓLIO'!$C$4:$C$564=$A39, N(INDEX('PORTIFÓLIO'!$J$4:$Q$564,,MATCH(L$2,'PORTIFÓLIO'!$J$3:$Q$3,0))) * N('PORTIFÓLIO'!$S$4:$S$564), 0 ) ), 0)} -> 0 | M39: =L39/$L$4 -> 0 | N39: {=IFERROR( SUM( IF( 'PORTIFÓLIO'!$C$4:$C$564=$A39, N(INDEX('PORTIFÓLIO'!$J$4:$Q$564,,MATCH(N$2,'PORTIFÓLIO'!$J$3:$Q$3,0))) * N('PORTIFÓLIO'!$S$4:$S$564), 0 ) ), 0)} -> 0 | O39: =N39/$N$4 -> 0 | P39: {=IFERROR( SUM( IF( 'PORTIFÓLIO'!$C$4:$C$564=$A39, N(INDEX('PORTIFÓLIO'!$J$4:$Q$564,,MATCH(P$2,'PORTIFÓLIO'!$J$3:$Q$3,0))) * N('PORTIFÓLIO'!$S$4:$S$564), 0 ) ), 0)} -> 0 | Q39: =P39/$P$4 -> 0 | R39: =SUM(P39,N39,L39,J39,H39,D39,B39) -> 0 | S39: =R39/$R$4 -> 0
A40: =IFERROR(__xludf.DUMMYFUNCTION("""COMPUTED_VALUE"""),"BASAGRAN 600") -> BASAGRAN 600 | B40: {=IFERROR( SUM( IF( 'PORTIFÓLIO'!$C$4:$C$564=$A40, N(INDEX('PORTIFÓLIO'!$J$4:$Q$564,,MATCH(B$2,'PORTIFÓLIO'!$J$3:$Q$3,0))) * N('PORTIFÓLIO'!$S$4:$S$564), 0 ) ), 0)} -> 0 | C40: =B40/$B$4 -> 0 | D40: {=IFERROR( SUM( IF( 'PORTIFÓLIO'!$C$4:$C$564=$A40, N(INDEX('PORTIFÓLIO'!$J$4:$Q$564,,MATCH(D$2,'PORTIFÓLIO'!$J$3:$Q$3,0))) * N('PORTIFÓLIO'!$S$4:$S$564), 0 ) ), 0)} -> 0 | E40: =D40/$D$4 -> 0 | F40: {=IFERROR( SUM( IF( 'PORTIFÓLIO'!$C$4:$C$564=$A40, N(INDEX('PORTIFÓLIO'!$J$4:$Q$564,,MATCH(F$2,'PORTIFÓLIO'!$J$3:$Q$3,0))) * N('PORTIFÓLIO'!$S$4:$S$564), 0 ) ), 0)} -> 0 | G40: =F40/$F$4 -> 0 | H40: {=IFERROR( SUM( IF( 'PORTIFÓLIO'!$C$4:$C$564=$A40, N(INDEX('PORTIFÓLIO'!$J$4:$Q$564,,MATCH(H$2,'PORTIFÓLIO'!$J$3:$Q$3,0))) * N('PORTIFÓLIO'!$S$4:$S$564), 0 ) ), 0)} -> 0 | I40: =H40/$H$4 -> 0 | J40: {=IFERROR( SUM( IF( 'PORTIFÓLIO'!$C$4:$C$564=$A40, N(INDEX('PORTIFÓLIO'!$J$4:$Q$564,,MATCH(J$2,'PORTIFÓLIO'!$J$3:$Q$3,0))) * N('PORTIFÓLIO'!$S$4:$S$564), 0 ) ), 0)} -> 0 | K40: =J40/$J$4 -> 0 | L40: {=IFERROR( SUM( IF( 'PORTIFÓLIO'!$C$4:$C$564=$A40, N(INDEX('PORTIFÓLIO'!$J$4:$Q$564,,MATCH(L$2,'PORTIFÓLIO'!$J$3:$Q$3,0))) * N('PORTIFÓLIO'!$S$4:$S$564), 0 ) ), 0)} -> 0 | M40: =L40/$L$4 -> 0 | N40: {=IFERROR( SUM( IF( 'PORTIFÓLIO'!$C$4:$C$564=$A40, N(INDEX('PORTIFÓLIO'!$J$4:$Q$564,,MATCH(N$2,'PORTIFÓLIO'!$J$3:$Q$3,0))) * N('PORTIFÓLIO'!$S$4:$S$564), 0 ) ), 0)} -> 0 | O40: =N40/$N$4 -> 0 | P40: {=IFERROR( SUM( IF( 'PORTIFÓLIO'!$C$4:$C$564=$A40, N(INDEX('PORTIFÓLIO'!$J$4:$Q$564,,MATCH(P$2,'PORTIFÓLIO'!$J$3:$Q$3,0))) * N('PORTIFÓLIO'!$S$4:$S$564), 0 ) ), 0)} -> 0 | Q40: =P40/$P$4 -> 0 | R40: =SUM(P40,N40,L40,J40,H40,D40,B40) -> 0 | S40: =R40/$R$4 -> 0
A41: =IFERROR(__xludf.DUMMYFUNCTION("""COMPUTED_VALUE"""),"FINALE") -> FINALE | B41: {=IFERROR( SUM( IF( 'PORTIFÓLIO'!$C$4:$C$564=$A41, N(INDEX('PORTIFÓLIO'!$J$4:$Q$564,,MATCH(B$2,'PORTIFÓLIO'!$J$3:$Q$3,0))) * N('PORTIFÓLIO'!$S$4:$S$564), 0 ) ), 0)} -> 0 | C41: =B41/$B$4 -> 0 | D41: {=IFERROR( SUM( IF( 'PORTIFÓLIO'!$C$4:$C$564=$A41, N(INDEX('PORTIFÓLIO'!$J$4:$Q$564,,MATCH(D$2,'PORTIFÓLIO'!$J$3:$Q$3,0))) * N('PORTIFÓLIO'!$S$4:$S$564), 0 ) ), 0)} -> 0 | E41: =D41/$D$4 -> 0 | F41: {=IFERROR( SUM( IF( 'PORTIFÓLIO'!$C$4:$C$564=$A41, N(INDEX('PORTIFÓLIO'!$J$4:$Q$564,,MATCH(F$2,'PORTIFÓLIO'!$J$3:$Q$3,0))) * N('PORTIFÓLIO'!$S$4:$S$564), 0 ) ), 0)} -> 0 | G41: =F41/$F$4 -> 0 | H41: {=IFERROR( SUM( IF( 'PORTIFÓLIO'!$C$4:$C$564=$A41, N(INDEX('PORTIFÓLIO'!$J$4:$Q$564,,MATCH(H$2,'PORTIFÓLIO'!$J$3:$Q$3,0))) * N('PORTIFÓLIO'!$S$4:$S$564), 0 ) ), 0)} -> 0 | I41: =H41/$H$4 -> 0 | J41: {=IFERROR( SUM( IF( 'PORTIFÓLIO'!$C$4:$C$564=$A41, N(INDEX('PORTIFÓLIO'!$J$4:$Q$564,,MATCH(J$2,'PORTIFÓLIO'!$J$3:$Q$3,0))) * N('PORTIFÓLIO'!$S$4:$S$564), 0 ) ), 0)} -> 0 | K41: =J41/$J$4 -> 0 | L41: {=IFERROR( SUM( IF( 'PORTIFÓLIO'!$C$4:$C$564=$A41, N(INDEX('PORTIFÓLIO'!$J$4:$Q$564,,MATCH(L$2,'PORTIFÓLIO'!$J$3:$Q$3,0))) * N('PORTIFÓLIO'!$S$4:$S$564), 0 ) ), 0)} -> 0 | M41: =L41/$L$4 -> 0 | N41: {=IFERROR( SUM( IF( 'PORTIFÓLIO'!$C$4:$C$564=$A41, N(INDEX('PORTIFÓLIO'!$J$4:$Q$564,,MATCH(N$2,'PORTIFÓLIO'!$J$3:$Q$3,0))) * N('PORTIFÓLIO'!$S$4:$S$564), 0 ) ), 0)} -> 0 | O41: =N41/$N$4 -> 0 | P41: {=IFERROR( SUM( IF( 'PORTIFÓLIO'!$C$4:$C$564=$A41, N(INDEX('PORTIFÓLIO'!$J$4:$Q$564,,MATCH(P$2,'PORTIFÓLIO'!$J$3:$Q$3,0))) * N('PORTIFÓLIO'!$S$4:$S$564), 0 ) ), 0)} -> 0 | Q41: =P41/$P$4 -> 0 | R41: =SUM(P41,N41,L41,J41,H41,D41,B41) -> 0 | S41: =R41/$R$4 -> 0
A42: =IFERROR(__xludf.DUMMYFUNCTION("""COMPUTED_VALUE"""),"HEAT") -> HEAT | B42: {=IFERROR( SUM( IF( 'PORTIFÓLIO'!$C$4:$C$564=$A42, N(INDEX('PORTIFÓLIO'!$J$4:$Q$564,,MATCH(B$2,'PORTIFÓLIO'!$J$3:$Q$3,0))) * N('PORTIFÓLIO'!$S$4:$S$564), 0 ) ), 0)} -> 0 | C42: =B42/$B$4 -> 0 | D42: {=IFERROR( SUM( IF( 'PORTIFÓLIO'!$C$4:$C$564=$A42, N(INDEX('PORTIFÓLIO'!$J$4:$Q$564,,MATCH(D$2,'PORTIFÓLIO'!$J$3:$Q$3,0))) * N('PORTIFÓLIO'!$S$4:$S$564), 0 ) ), 0)} -> 0 | E42: =D42/$D$4 -> 0 | F42: {=IFERROR( SUM( IF( 'PORTIFÓLIO'!$C$4:$C$564=$A42, N(INDEX('PORTIFÓLIO'!$J$4:$Q$564,,MATCH(F$2,'PORTIFÓLIO'!$J$3:$Q$3,0))) * N('PORTIFÓLIO'!$S$4:$S$564), 0 ) ), 0)} -> 0 | G42: =F42/$F$4 -> 0 | H42: {=IFERROR( SUM( IF( 'PORTIFÓLIO'!$C$4:$C$564=$A42, N(INDEX('PORTIFÓLIO'!$J$4:$Q$564,,MATCH(H$2,'PORTIFÓLIO'!$J$3:$Q$3,0))) * N('PORTIFÓLIO'!$S$4:$S$564), 0 ) ), 0)} -> 0 | I42: =H42/$H$4 -> 0 | J42: {=IFERROR( SUM( IF( 'PORTIFÓLIO'!$C$4:$C$564=$A42, N(INDEX('PORTIFÓLIO'!$J$4:$Q$564,,MATCH(J$2,'PORTIFÓLIO'!$J$3:$Q$3,0))) * N('PORTIFÓLIO'!$S$4:$S$564), 0 ) ), 0)} -> 0 | K42: =J42/$J$4 -> 0 | L42: {=IFERROR( SUM( IF( 'PORTIFÓLIO'!$C$4:$C$564=$A42, N(INDEX('PORTIFÓLIO'!$J$4:$Q$564,,MATCH(L$2,'PORTIFÓLIO'!$J$3:$Q$3,0))) * N('PORTIFÓLIO'!$S$4:$S$564), 0 ) ), 0)} -> 0 | M42: =L42/$L$4 -> 0 | N42: {=IFERROR( SUM( IF( 'PORTIFÓLIO'!$C$4:$C$564=$A42, N(INDEX('PORTIFÓLIO'!$J$4:$Q$564,,MATCH(N$2,'PORTIFÓLIO'!$J$3:$Q$3,0))) * N('PORTIFÓLIO'!$S$4:$S$564), 0 ) ), 0)} -> 0 | O42: =N42/$N$4 -> 0 | P42: {=IFERROR( SUM( IF( 'PORTIFÓLIO'!$C$4:$C$564=$A42, N(INDEX('PORTIFÓLIO'!$J$4:$Q$564,,MATCH(P$2,'PORTIFÓLIO'!$J$3:$Q$3,0))) * N('PORTIFÓLIO'!$S$4:$S$564), 0 ) ), 0)} -> 0 | Q42: =P42/$P$4 -> 0 | R42: =SUM(P42,N42,L42,J42,H42,D42,B42) -> 0 | S42: =R42/$R$4 -> 0
A43: =IFERROR(__xludf.DUMMYFUNCTION("""COMPUTED_VALUE"""),"LIBERTY") -> LIBERTY | B43: {=IFERROR( SUM( IF( 'PORTIFÓLIO'!$C$4:$C$564=$A43, N(INDEX('PORTIFÓLIO'!$J$4:$Q$564,,MATCH(B$2,'PORTIFÓLIO'!$J$3:$Q$3,0))) * N('PORTIFÓLIO'!$S$4:$S$564), 0 ) ), 0)} -> 0 | C43: =B43/$B$4 -> 0 | D43: {=IFERROR( SUM( IF( 'PORTIFÓLIO'!$C$4:$C$564=$A43, N(INDEX('PORTIFÓLIO'!$J$4:$Q$564,,MATCH(D$2,'PORTIFÓLIO'!$J$3:$Q$3,0))) * N('PORTIFÓLIO'!$S$4:$S$564), 0 ) ), 0)} -> 0 | E43: =D43/$D$4 -> 0 | F43: {=IFERROR( SUM( IF( 'PORTIFÓLIO'!$C$4:$C$564=$A43, N(INDEX('PORTIFÓLIO'!$J$4:$Q$564,,MATCH(F$2,'PORTIFÓLIO'!$J$3:$Q$3,0))) * N('PORTIFÓLIO'!$S$4:$S$564), 0 ) ), 0)} -> 0 | G43: =F43/$F$4 -> 0 | H43: {=IFERROR( SUM( IF( 'PORTIFÓLIO'!$C$4:$C$564=$A43, N(INDEX('PORTIFÓLIO'!$J$4:$Q$564,,MATCH(H$2,'PORTIFÓLIO'!$J$3:$Q$3,0))) * N('PORTIFÓLIO'!$S$4:$S$564), 0 ) ), 0)} -> 0 | I43: =H43/$H$4 -> 0 | J43: {=IFERROR( SUM( IF( 'PORTIFÓLIO'!$C$4:$C$564=$A43, N(INDEX('PORTIFÓLIO'!$J$4:$Q$564,,MATCH(J$2,'PORTIFÓLIO'!$J$3:$Q$3,0))) * N('PORTIFÓLIO'!$S$4:$S$564), 0 ) ), 0)} -> 0 | K43: =J43/$J$4 -> 0 | L43: {=IFERROR( SUM( IF( 'PORTIFÓLIO'!$C$4:$C$564=$A43, N(INDEX('PORTIFÓLIO'!$J$4:$Q$564,,MATCH(L$2,'PORTIFÓLIO'!$J$3:$Q$3,0))) * N('PORTIFÓLIO'!$S$4:$S$564), 0 ) ), 0)} -> 0 | M43: =L43/$L$4 -> 0 | N43: {=IFERROR( SUM( IF( 'PORTIFÓLIO'!$C$4:$C$564=$A43, N(INDEX('PORTIFÓLIO'!$J$4:$Q$564,,MATCH(N$2,'PORTIFÓLIO'!$J$3:$Q$3,0))) * N('PORTIFÓLIO'!$S$4:$S$564), 0 ) ), 0)} -> 0 | O43: =N43/$N$4 -> 0 | P43: {=IFERROR( SUM( IF( 'PORTIFÓLIO'!$C$4:$C$564=$A43, N(INDEX('PORTIFÓLIO'!$J$4:$Q$564,,MATCH(P$2,'PORTIFÓLIO'!$J$3:$Q$3,0))) * N('PORTIFÓLIO'!$S$4:$S$564), 0 ) ), 0)} -> 0 | Q43: =P43/$P$4 -> 0 | R43: =SUM(P43,N43,L43,J43,H43,D43,B43) -> 0 | S43: =R43/$R$4 -> 0
A44: =IFERROR(__xludf.DUMMYFUNCTION("""COMPUTED_VALUE"""),"PROWL H2O") -> PROWL H2O | B44: {=IFERROR( SUM( IF( 'PORTIFÓLIO'!$C$4:$C$564=$A44, N(INDEX('PORTIFÓLIO'!$J$4:$Q$564,,MATCH(B$2,'PORTIFÓLIO'!$J$3:$Q$3,0))) * N('PORTIFÓLIO'!$S$4:$S$564), 0 ) ), 0)} -> 0 | C44: =B44/$B$4 -> 0 | D44: {=IFERROR( SUM( IF( 'PORTIFÓLIO'!$C$4:$C$564=$A44, N(INDEX('PORTIFÓLIO'!$J$4:$Q$564,,MATCH(D$2,'PORTIFÓLIO'!$J$3:$Q$3,0))) * N('PORTIFÓLIO'!$S$4:$S$564), 0 ) ), 0)} -> 0 | E44: =D44/$D$4 -> 0 | F44: {=IFERROR( SUM( IF( 'PORTIFÓLIO'!$C$4:$C$564=$A44, N(INDEX('PORTIFÓLIO'!$J$4:$Q$564,,MATCH(F$2,'PORTIFÓLIO'!$J$3:$Q$3,0))) * N('PORTIFÓLIO'!$S$4:$S$564), 0 ) ), 0)} -> 0 | G44: =F44/$F$4 -> 0 | H44: {=IFERROR( SUM( IF( 'PORTIFÓLIO'!$C$4:$C$564=$A44, N(INDEX('PORTIFÓLIO'!$J$4:$Q$564,,MATCH(H$2,'PORTIFÓLIO'!$J$3:$Q$3,0))) * N('PORTIFÓLIO'!$S$4:$S$564), 0 ) ), 0)} -> 0 | I44: =H44/$H$4 -> 0 | J44: {=IFERROR( SUM( IF( 'PORTIFÓLIO'!$C$4:$C$564=$A44, N(INDEX('PORTIFÓLIO'!$J$4:$Q$564,,MATCH(J$2,'PORTIFÓLIO'!$J$3:$Q$3,0))) * N('PORTIFÓLIO'!$S$4:$S$564), 0 ) ), 0)} -> 0 | K44: =J44/$J$4 -> 0 | L44: {=IFERROR( SUM( IF( 'PORTIFÓLIO'!$C$4:$C$564=$A44, N(INDEX('PORTIFÓLIO'!$J$4:$Q$564,,MATCH(L$2,'PORTIFÓLIO'!$J$3:$Q$3,0))) * N('PORTIFÓLIO'!$S$4:$S$564), 0 ) ), 0)} -> 0 | M44: =L44/$L$4 -> 0 | N44: {=IFERROR( SUM( IF( 'PORTIFÓLIO'!$C$4:$C$564=$A44, N(INDEX('PORTIFÓLIO'!$J$4:$Q$564,,MATCH(N$2,'PORTIFÓLIO'!$J$3:$Q$3,0))) * N('PORTIFÓLIO'!$S$4:$S$564), 0 ) ), 0)} -> 0 | O44: =N44/$N$4 -> 0 | P44: {=IFERROR( SUM( IF( 'PORTIFÓLIO'!$C$4:$C$564=$A44, N(INDEX('PORTIFÓLIO'!$J$4:$Q$564,,MATCH(P$2,'PORTIFÓLIO'!$J$3:$Q$3,0))) * N('PORTIFÓLIO'!$S$4:$S$564), 0 ) ), 0)} -> 0 | Q44: =P44/$P$4 -> 0 | R44: =SUM(P44,N44,L44,J44,H44,D44,B44) -> 0 | S44: =R44/$R$4 -> 0
A45: =IFERROR(__xludf.DUMMYFUNCTION("""COMPUTED_VALUE"""),"ADENGO") -> ADENGO | B45: {=IFERROR( SUM( IF( 'PORTIFÓLIO'!$C$4:$C$564=$A45, N(INDEX('PORTIFÓLIO'!$J$4:$Q$564,,MATCH(B$2,'PORTIFÓLIO'!$J$3:$Q$3,0))) * N('PORTIFÓLIO'!$S$4:$S$564), 0 ) ), 0)} -> 0 | C45: =B45/$B$4 -> 0 | D45: {=IFERROR( SUM( IF( 'PORTIFÓLIO'!$C$4:$C$564=$A45, N(INDEX('PORTIFÓLIO'!$J$4:$Q$564,,MATCH(D$2,'PORTIFÓLIO'!$J$3:$Q$3,0))) * N('PORTIFÓLIO'!$S$4:$S$564), 0 ) ), 0)} -> 0 | E45: =D45/$D$4 -> 0 | F45: {=IFERROR( SUM( IF( 'PORTIFÓLIO'!$C$4:$C$564=$A45, N(INDEX('PORTIFÓLIO'!$J$4:$Q$564,,MATCH(F$2,'PORTIFÓLIO'!$J$3:$Q$3,0))) * N('PORTIFÓLIO'!$S$4:$S$564), 0 ) ), 0)} -> 0 | G45: =F45/$F$4 -> 0 | H45: {=IFERROR( SUM( IF( 'PORTIFÓLIO'!$C$4:$C$564=$A45, N(INDEX('PORTIFÓLIO'!$J$4:$Q$564,,MATCH(H$2,'PORTIFÓLIO'!$J$3:$Q$3,0))) * N('PORTIFÓLIO'!$S$4:$S$564), 0 ) ), 0)} -> 0 | I45: =H45/$H$4 -> 0 | J45: {=IFERROR( SUM( IF( 'PORTIFÓLIO'!$C$4:$C$564=$A45, N(INDEX('PORTIFÓLIO'!$J$4:$Q$564,,MATCH(J$2,'PORTIFÓLIO'!$J$3:$Q$3,0))) * N('PORTIFÓLIO'!$S$4:$S$564), 0 ) ), 0)} -> 0 | K45: =J45/$J$4 -> 0 | L45: {=IFERROR( SUM( IF( 'PORTIFÓLIO'!$C$4:$C$564=$A45, N(INDEX('PORTIFÓLIO'!$J$4:$Q$564,,MATCH(L$2,'PORTIFÓLIO'!$J$3:$Q$3,0))) * N('PORTIFÓLIO'!$S$4:$S$564), 0 ) ), 0)} -> 0 | M45: =L45/$L$4 -> 0 | N45: {=IFERROR( SUM( IF( 'PORTIFÓLIO'!$C$4:$C$564=$A45, N(INDEX('PORTIFÓLIO'!$J$4:$Q$564,,MATCH(N$2,'PORTIFÓLIO'!$J$3:$Q$3,0))) * N('PORTIFÓLIO'!$S$4:$S$564), 0 ) ), 0)} -> 0 | O45: =N45/$N$4 -> 0 | P45: {=IFERROR( SUM( IF( 'PORTIFÓLIO'!$C$4:$C$564=$A45, N(INDEX('PORTIFÓLIO'!$J$4:$Q$564,,MATCH(P$2,'PORTIFÓLIO'!$J$3:$Q$3,0))) * N('PORTIFÓLIO'!$S$4:$S$564), 0 ) ), 0)} -> 0 | Q45: =P45/$P$4 -> 0 | R45: =SUM(P45,N45,L45,J45,H45,D45,B45) -> 0 | S45: =R45/$R$4 -> 0
A46: =IFERROR(__xludf.DUMMYFUNCTION("""COMPUTED_VALUE"""),"ROUNDUP WG") -> ROUNDUP WG | B46: {=IFERROR( SUM( IF( 'PORTIFÓLIO'!$C$4:$C$564=$A46, N(INDEX('PORTIFÓLIO'!$J$4:$Q$564,,MATCH(B$2,'PORTIFÓLIO'!$J$3:$Q$3,0))) * N('PORTIFÓLIO'!$S$4:$S$564), 0 ) ), 0)} -> 46456.2 | C46: =B46/$B$4 -> 94.808571 | D46: {=IFERROR( SUM( IF( 'PORTIFÓLIO'!$C$4:$C$564=$A46, N(INDEX('PORTIFÓLIO'!$J$4:$Q$564,,MATCH(D$2,'PORTIFÓLIO'!$J$3:$Q$3,0))) * N('PORTIFÓLIO'!$S$4:$S$564), 0 ) ), 0)} -> 29496 | E46: =D46/$D$4 -> 98.32 | F46: {=IFERROR( SUM( IF( 'PORTIFÓLIO'!$C$4:$C$564=$A46, N(INDEX('PORTIFÓLIO'!$J$4:$Q$564,,MATCH(F$2,'PORTIFÓLIO'!$J$3:$Q$3,0))) * N('PORTIFÓLIO'!$S$4:$S$564), 0 ) ), 0)} -> 21630.4 | G46: =F46/$F$4 -> 98.32 | H46: {=IFERROR( SUM( IF( 'PORTIFÓLIO'!$C$4:$C$564=$A46, N(INDEX('PORTIFÓLIO'!$J$4:$Q$564,,MATCH(H$2,'PORTIFÓLIO'!$J$3:$Q$3,0))) * N('PORTIFÓLIO'!$S$4:$S$564), 0 ) ), 0)} -> 9832 | I46: =H46/$H$4 -> 49.16 | J46: {=IFERROR( SUM( IF( 'PORTIFÓLIO'!$C$4:$C$564=$A46, N(INDEX('PORTIFÓLIO'!$J$4:$Q$564,,MATCH(J$2,'PORTIFÓLIO'!$J$3:$Q$3,0))) * N('PORTIFÓLIO'!$S$4:$S$564), 0 ) ), 0)} -> 18484.16 | K46: =J46/$J$4 -> 49.16 | L46: {=IFERROR( SUM( IF( 'PORTIFÓLIO'!$C$4:$C$564=$A46, N(INDEX('PORTIFÓLIO'!$J$4:$Q$564,,MATCH(L$2,'PORTIFÓLIO'!$J$3:$Q$3,0))) * N('PORTIFÓLIO'!$S$4:$S$564), 0 ) ), 0)} -> 8111.4 | M46: =L46/$L$4 -> 36.87 | N46: {=IFERROR( SUM( IF( 'PORTIFÓLIO'!$C$4:$C$564=$A46, N(INDEX('PORTIFÓLIO'!$J$4:$Q$564,,MATCH(N$2,'PORTIFÓLIO'!$J$3:$Q$3,0))) * N('PORTIFÓLIO'!$S$4:$S$564), 0 ) ), 0)} -> 119753.76 | O46: =N46/$N$4 -> 98.32 | P46: {=IFERROR( SUM( IF( 'PORTIFÓLIO'!$C$4:$C$564=$A46, N(INDEX('PORTIFÓLIO'!$J$4:$Q$564,,MATCH(P$2,'PORTIFÓLIO'!$J$3:$Q$3,0))) * N('PORTIFÓLIO'!$S$4:$S$564), 0 ) ), 0)} -> 31462.4 | Q46: =P46/$P$4 -> 98.32 | R46: =SUM(P46,N46,L46,J46,H46,D46,B46) -> 263595.92 | S46: =R46/$R$4 -> 78.826531
A47: =IFERROR(__xludf.DUMMYFUNCTION("""COMPUTED_VALUE"""),"SOBERAN") -> SOBERAN | B47: {=IFERROR( SUM( IF( 'PORTIFÓLIO'!$C$4:$C$564=$A47, N(INDEX('PORTIFÓLIO'!$J$4:$Q$564,,MATCH(B$2,'PORTIFÓLIO'!$J$3:$Q$3,0))) * N('PORTIFÓLIO'!$S$4:$S$564), 0 ) ), 0)} -> 0 | C47: =B47/$B$4 -> 0 | D47: {=IFERROR( SUM( IF( 'PORTIFÓLIO'!$C$4:$C$564=$A47, N(INDEX('PORTIFÓLIO'!$J$4:$Q$564,,MATCH(D$2,'PORTIFÓLIO'!$J$3:$Q$3,0))) * N('PORTIFÓLIO'!$S$4:$S$564), 0 ) ), 0)} -> 0 | E47: =D47/$D$4 -> 0 | F47: {=IFERROR( SUM( IF( 'PORTIFÓLIO'!$C$4:$C$564=$A47, N(INDEX('PORTIFÓLIO'!$J$4:$Q$564,,MATCH(F$2,'PORTIFÓLIO'!$J$3:$Q$3,0))) * N('PORTIFÓLIO'!$S$4:$S$564), 0 ) ), 0)} -> 0 | G47: =F47/$F$4 -> 0 | H47: {=IFERROR( SUM( IF( 'PORTIFÓLIO'!$C$4:$C$564=$A47, N(INDEX('PORTIFÓLIO'!$J$4:$Q$564,,MATCH(H$2,'PORTIFÓLIO'!$J$3:$Q$3,0))) * N('PORTIFÓLIO'!$S$4:$S$564), 0 ) ), 0)} -> 0 | I47: =H47/$H$4 -> 0 | J47: {=IFERROR( SUM( IF( 'PORTIFÓLIO'!$C$4:$C$564=$A47, N(INDEX('PORTIFÓLIO'!$J$4:$Q$564,,MATCH(J$2,'PORTIFÓLIO'!$J$3:$Q$3,0))) * N('PORTIFÓLIO'!$S$4:$S$564), 0 ) ), 0)} -> 0 | K47: =J47/$J$4 -> 0 | L47: {=IFERROR( SUM( IF( 'PORTIFÓLIO'!$C$4:$C$564=$A47, N(INDEX('PORTIFÓLIO'!$J$4:$Q$564,,MATCH(L$2,'PORTIFÓLIO'!$J$3:$Q$3,0))) * N('PORTIFÓLIO'!$S$4:$S$564), 0 ) ), 0)} -> 0 | M47: =L47/$L$4 -> 0 | N47: {=IFERROR( SUM( IF( 'PORTIFÓLIO'!$C$4:$C$564=$A47, N(INDEX('PORTIFÓLIO'!$J$4:$Q$564,,MATCH(N$2,'PORTIFÓLIO'!$J$3:$Q$3,0))) * N('PORTIFÓLIO'!$S$4:$S$564), 0 ) ), 0)} -> 0 | O47: =N47/$N$4 -> 0 | P47: {=IFERROR( SUM( IF( 'PORTIFÓLIO'!$C$4:$C$564=$A47, N(INDEX('PORTIFÓLIO'!$J$4:$Q$564,,MATCH(P$2,'PORTIFÓLIO'!$J$3:$Q$3,0))) * N('PORTIFÓLIO'!$S$4:$S$564), 0 ) ), 0)} -> 0 | Q47: =P47/$P$4 -> 0 | R47: =SUM(P47,N47,L47,J47,H47,D47,B47) -> 0 | S47: =R47/$R$4 -> 0
A48: =IFERROR(__xludf.DUMMYFUNCTION("""COMPUTED_VALUE"""),"2,4-D 806+PICLORAM 64") -> 2,4-D 806+PICLORAM 64 | B48: {=IFERROR( SUM( IF( 'PORTIFÓLIO'!$C$4:$C$564=$A48, N(INDEX('PORTIFÓLIO'!$J$4:$Q$564,,MATCH(B$2,'PORTIFÓLIO'!$J$3:$Q$3,0))) * N('PORTIFÓLIO'!$S$4:$S$564), 0 ) ), 0)} -> 0 | C48: =B48/$B$4 -> 0 | D48: {=IFERROR( SUM( IF( 'PORTIFÓLIO'!$C$4:$C$564=$A48, N(INDEX('PORTIFÓLIO'!$J$4:$Q$564,,MATCH(D$2,'PORTIFÓLIO'!$J$3:$Q$3,0))) * N('PORTIFÓLIO'!$S$4:$S$564), 0 ) ), 0)} -> 0 | E48: =D48/$D$4 -> 0 | F48: {=IFERROR( SUM( IF( 'PORTIFÓLIO'!$C$4:$C$564=$A48, N(INDEX('PORTIFÓLIO'!$J$4:$Q$564,,MATCH(F$2,'PORTIFÓLIO'!$J$3:$Q$3,0))) * N('PORTIFÓLIO'!$S$4:$S$564), 0 ) ), 0)} -> 0 | G48: =F48/$F$4 -> 0 | H48: {=IFERROR( SUM( IF( 'PORTIFÓLIO'!$C$4:$C$564=$A48, N(INDEX('PORTIFÓLIO'!$J$4:$Q$564,,MATCH(H$2,'PORTIFÓLIO'!$J$3:$Q$3,0))) * N('PORTIFÓLIO'!$S$4:$S$564), 0 ) ), 0)} -> 0 | I48: =H48/$H$4 -> 0 | J48: {=IFERROR( SUM( IF( 'PORTIFÓLIO'!$C$4:$C$564=$A48, N(INDEX('PORTIFÓLIO'!$J$4:$Q$564,,MATCH(J$2,'PORTIFÓLIO'!$J$3:$Q$3,0))) * N('PORTIFÓLIO'!$S$4:$S$564), 0 ) ), 0)} -> 0 | K48: =J48/$J$4 -> 0 | L48: {=IFERROR( SUM( IF( 'PORTIFÓLIO'!$C$4:$C$564=$A48, N(INDEX('PORTIFÓLIO'!$J$4:$Q$564,,MATCH(L$2,'PORTIFÓLIO'!$J$3:$Q$3,0))) * N('PORTIFÓLIO'!$S$4:$S$564), 0 ) ), 0)} -> 0 | M48: =L48/$L$4 -> 0 | N48: {=IFERROR( SUM( IF( 'PORTIFÓLIO'!$C$4:$C$564=$A48, N(INDEX('PORTIFÓLIO'!$J$4:$Q$564,,MATCH(N$2,'PORTIFÓLIO'!$J$3:$Q$3,0))) * N('PORTIFÓLIO'!$S$4:$S$564), 0 ) ), 0)} -> 0 | O48: =N48/$N$4 -> 0 | P48: {=IFERROR( SUM( IF( 'PORTIFÓLIO'!$C$4:$C$564=$A48, N(INDEX('PORTIFÓLIO'!$J$4:$Q$564,,MATCH(P$2,'PORTIFÓLIO'!$J$3:$Q$3,0))) * N('PORTIFÓLIO'!$S$4:$S$564), 0 ) ), 0)} -> 0 | Q48: =P48/$P$4 -> 0 | R48: =SUM(P48,N48,L48,J48,H48,D48,B48) -> 0 | S48: =R48/$R$4 -> 0
A49: =IFERROR(__xludf.DUMMYFUNCTION("""COMPUTED_VALUE"""),"FOMESAFEN CCAB 250 SL") -> FOMESAFEN CCAB 250 SL | B49: {=IFERROR( SUM( IF( 'PORTIFÓLIO'!$C$4:$C$564=$A49, N(INDEX('PORTIFÓLIO'!$J$4:$Q$564,,MATCH(B$2,'PORTIFÓLIO'!$J$3:$Q$3,0))) * N('PORTIFÓLIO'!$S$4:$S$564), 0 ) ), 0)} -> 0 | C49: =B49/$B$4 -> 0 | D49: {=IFERROR( SUM( IF( 'PORTIFÓLIO'!$C$4:$C$564=$A49, N(INDEX('PORTIFÓLIO'!$J$4:$Q$564,,MATCH(D$2,'PORTIFÓLIO'!$J$3:$Q$3,0))) * N('PORTIFÓLIO'!$S$4:$S$564), 0 ) ), 0)} -> 0 | E49: =D49/$D$4 -> 0 | F49: {=IFERROR( SUM( IF( 'PORTIFÓLIO'!$C$4:$C$564=$A49, N(INDEX('PORTIFÓLIO'!$J$4:$Q$564,,MATCH(F$2,'PORTIFÓLIO'!$J$3:$Q$3,0))) * N('PORTIFÓLIO'!$S$4:$S$564), 0 ) ), 0)} -> 0 | G49: =F49/$F$4 -> 0 | H49: {=IFERROR( SUM( IF( 'PORTIFÓLIO'!$C$4:$C$564=$A49, N(INDEX('PORTIFÓLIO'!$J$4:$Q$564,,MATCH(H$2,'PORTIFÓLIO'!$J$3:$Q$3,0))) * N('PORTIFÓLIO'!$S$4:$S$564), 0 ) ), 0)} -> 0 | I49: =H49/$H$4 -> 0 | J49: {=IFERROR( SUM( IF( 'PORTIFÓLIO'!$C$4:$C$564=$A49, N(INDEX('PORTIFÓLIO'!$J$4:$Q$564,,MATCH(J$2,'PORTIFÓLIO'!$J$3:$Q$3,0))) * N('PORTIFÓLIO'!$S$4:$S$564), 0 ) ), 0)} -> 0 | K49: =J49/$J$4 -> 0 | L49: {=IFERROR( SUM( IF( 'PORTIFÓLIO'!$C$4:$C$564=$A49, N(INDEX('PORTIFÓLIO'!$J$4:$Q$564,,MATCH(L$2,'PORTIFÓLIO'!$J$3:$Q$3,0))) * N('PORTIFÓLIO'!$S$4:$S$564), 0 ) ), 0)} -> 0 | M49: =L49/$L$4 -> 0 | N49: {=IFERROR( SUM( IF( 'PORTIFÓLIO'!$C$4:$C$564=$A49, N(INDEX('PORTIFÓLIO'!$J$4:$Q$564,,MATCH(N$2,'PORTIFÓLIO'!$J$3:$Q$3,0))) * N('PORTIFÓLIO'!$S$4:$S$564), 0 ) ), 0)} -> 0 | O49: =N49/$N$4 -> 0 | P49: {=IFERROR( SUM( IF( 'PORTIFÓLIO'!$C$4:$C$564=$A49, N(INDEX('PORTIFÓLIO'!$J$4:$Q$564,,MATCH(P$2,'PORTIFÓLIO'!$J$3:$Q$3,0))) * N('PORTIFÓLIO'!$S$4:$S$564), 0 ) ), 0)} -> 0 | Q49: =P49/$P$4 -> 0 | R49: =SUM(P49,N49,L49,J49,H49,D49,B49) -> 0 | S49: =R49/$R$4 -> 0
A50: =IFERROR(__xludf.DUMMYFUNCTION("""COMPUTED_VALUE"""),"GLUFOSINATO CCAB 200 SL") -> GLUFOSINATO CCAB 200 SL | B50: {=IFERROR( SUM( IF( 'PORTIFÓLIO'!$C$4:$C$564=$A50, N(INDEX('PORTIFÓLIO'!$J$4:$Q$564,,MATCH(B$2,'PORTIFÓLIO'!$J$3:$Q$3,0))) * N('PORTIFÓLIO'!$S$4:$S$564), 0 ) ), 0)} -> 0 | C50: =B50/$B$4 -> 0 | D50: {=IFERROR( SUM( IF( 'PORTIFÓLIO'!$C$4:$C$564=$A50, N(INDEX('PORTIFÓLIO'!$J$4:$Q$564,,MATCH(D$2,'PORTIFÓLIO'!$J$3:$Q$3,0))) * N('PORTIFÓLIO'!$S$4:$S$564), 0 ) ), 0)} -> 0 | E50: =D50/$D$4 -> 0 | F50: {=IFERROR( SUM( IF( 'PORTIFÓLIO'!$C$4:$C$564=$A50, N(INDEX('PORTIFÓLIO'!$J$4:$Q$564,,MATCH(F$2,'PORTIFÓLIO'!$J$3:$Q$3,0))) * N('PORTIFÓLIO'!$S$4:$S$564), 0 ) ), 0)} -> 0 | G50: =F50/$F$4 -> 0 | H50: {=IFERROR( SUM( IF( 'PORTIFÓLIO'!$C$4:$C$564=$A50, N(INDEX('PORTIFÓLIO'!$J$4:$Q$564,,MATCH(H$2,'PORTIFÓLIO'!$J$3:$Q$3,0))) * N('PORTIFÓLIO'!$S$4:$S$564), 0 ) ), 0)} -> 0 | I50: =H50/$H$4 -> 0 | J50: {=IFERROR( SUM( IF( 'PORTIFÓLIO'!$C$4:$C$564=$A50, N(INDEX('PORTIFÓLIO'!$J$4:$Q$564,,MATCH(J$2,'PORTIFÓLIO'!$J$3:$Q$3,0))) * N('PORTIFÓLIO'!$S$4:$S$564), 0 ) ), 0)} -> 0 | K50: =J50/$J$4 -> 0 | L50: {=IFERROR( SUM( IF( 'PORTIFÓLIO'!$C$4:$C$564=$A50, N(INDEX('PORTIFÓLIO'!$J$4:$Q$564,,MATCH(L$2,'PORTIFÓLIO'!$J$3:$Q$3,0))) * N('PORTIFÓLIO'!$S$4:$S$564), 0 ) ), 0)} -> 0 | M50: =L50/$L$4 -> 0 | N50: {=IFERROR( SUM( IF( 'PORTIFÓLIO'!$C$4:$C$564=$A50, N(INDEX('PORTIFÓLIO'!$J$4:$Q$564,,MATCH(N$2,'PORTIFÓLIO'!$J$3:$Q$3,0))) * N('PORTIFÓLIO'!$S$4:$S$564), 0 ) ), 0)} -> 0 | O50: =N50/$N$4 -> 0 | P50: {=IFERROR( SUM( IF( 'PORTIFÓLIO'!$C$4:$C$564=$A50, N(INDEX('PORTIFÓLIO'!$J$4:$Q$564,,MATCH(P$2,'PORTIFÓLIO'!$J$3:$Q$3,0))) * N('PORTIFÓLIO'!$S$4:$S$564), 0 ) ), 0)} -> 0 | Q50: =P50/$P$4 -> 0 | R50: =SUM(P50,N50,L50,J50,H50,D50,B50) -> 0 | S50: =R50/$R$4 -> 0
A51: =IFERROR(__xludf.DUMMYFUNCTION("""COMPUTED_VALUE"""),"MESOTRIONA CCAB 480 SC") -> MESOTRIONA CCAB 480 SC | B51: {=IFERROR( SUM( IF( 'PORTIFÓLIO'!$C$4:$C$564=$A51, N(INDEX('PORTIFÓLIO'!$J$4:$Q$564,,MATCH(B$2,'PORTIFÓLIO'!$J$3:$Q$3,0))) * N('PORTIFÓLIO'!$S$4:$S$564), 0 ) ), 0)} -> 0 | C51: =B51/$B$4 -> 0 | D51: {=IFERROR( SUM( IF( 'PORTIFÓLIO'!$C$4:$C$564=$A51, N(INDEX('PORTIFÓLIO'!$J$4:$Q$564,,MATCH(D$2,'PORTIFÓLIO'!$J$3:$Q$3,0))) * N('PORTIFÓLIO'!$S$4:$S$564), 0 ) ), 0)} -> 0 | E51: =D51/$D$4 -> 0 | F51: {=IFERROR( SUM( IF( 'PORTIFÓLIO'!$C$4:$C$564=$A51, N(INDEX('PORTIFÓLIO'!$J$4:$Q$564,,MATCH(F$2,'PORTIFÓLIO'!$J$3:$Q$3,0))) * N('PORTIFÓLIO'!$S$4:$S$564), 0 ) ), 0)} -> 0 | G51: =F51/$F$4 -> 0 | H51: {=IFERROR( SUM( IF( 'PORTIFÓLIO'!$C$4:$C$564=$A51, N(INDEX('PORTIFÓLIO'!$J$4:$Q$564,,MATCH(H$2,'PORTIFÓLIO'!$J$3:$Q$3,0))) * N('PORTIFÓLIO'!$S$4:$S$564), 0 ) ), 0)} -> 0 | I51: =H51/$H$4 -> 0 | J51: {=IFERROR( SUM( IF( 'PORTIFÓLIO'!$C$4:$C$564=$A51, N(INDEX('PORTIFÓLIO'!$J$4:$Q$564,,MATCH(J$2,'PORTIFÓLIO'!$J$3:$Q$3,0))) * N('PORTIFÓLIO'!$S$4:$S$564), 0 ) ), 0)} -> 0 | K51: =J51/$J$4 -> 0 | L51: {=IFERROR( SUM( IF( 'PORTIFÓLIO'!$C$4:$C$564=$A51, N(INDEX('PORTIFÓLIO'!$J$4:$Q$564,,MATCH(L$2,'PORTIFÓLIO'!$J$3:$Q$3,0))) * N('PORTIFÓLIO'!$S$4:$S$564), 0 ) ), 0)} -> 0 | M51: =L51/$L$4 -> 0 | N51: {=IFERROR( SUM( IF( 'PORTIFÓLIO'!$C$4:$C$564=$A51, N(INDEX('PORTIFÓLIO'!$J$4:$Q$564,,MATCH(N$2,'PORTIFÓLIO'!$J$3:$Q$3,0))) * N('PORTIFÓLIO'!$S$4:$S$564), 0 ) ), 0)} -> 0 | O51: =N51/$N$4 -> 0 | P51: {=IFERROR( SUM( IF( 'PORTIFÓLIO'!$C$4:$C$564=$A51, N(INDEX('PORTIFÓLIO'!$J$4:$Q$564,,MATCH(P$2,'PORTIFÓLIO'!$J$3:$Q$3,0))) * N('PORTIFÓLIO'!$S$4:$S$564), 0 ) ), 0)} -> 0 | Q51: =P51/$P$4 -> 0 | R51: =SUM(P51,N51,L51,J51,H51,D51,B51) -> 0 | S51: =R51/$R$4 -> 0
A52: =IFERROR(__xludf.DUMMYFUNCTION("""COMPUTED_VALUE"""),"TRICLOPIR CCAB 480 EC") -> TRICLOPIR CCAB 480 EC | B52: {=IFERROR( SUM( IF( 'PORTIFÓLIO'!$C$4:$C$564=$A52, N(INDEX('PORTIFÓLIO'!$J$4:$Q$564,,MATCH(B$2,'PORTIFÓLIO'!$J$3:$Q$3,0))) * N('PORTIFÓLIO'!$S$4:$S$564), 0 ) ), 0)} -> 0 | C52: =B52/$B$4 -> 0 | D52: {=IFERROR( SUM( IF( 'PORTIFÓLIO'!$C$4:$C$564=$A52, N(INDEX('PORTIFÓLIO'!$J$4:$Q$564,,MATCH(D$2,'PORTIFÓLIO'!$J$3:$Q$3,0))) * N('PORTIFÓLIO'!$S$4:$S$564), 0 ) ), 0)} -> 0 | E52: =D52/$D$4 -> 0 | F52: {=IFERROR( SUM( IF( 'PORTIFÓLIO'!$C$4:$C$564=$A52, N(INDEX('PORTIFÓLIO'!$J$4:$Q$564,,MATCH(F$2,'PORTIFÓLIO'!$J$3:$Q$3,0))) * N('PORTIFÓLIO'!$S$4:$S$564), 0 ) ), 0)} -> 0 | G52: =F52/$F$4 -> 0 | H52: {=IFERROR( SUM( IF( 'PORTIFÓLIO'!$C$4:$C$564=$A52, N(INDEX('PORTIFÓLIO'!$J$4:$Q$564,,MATCH(H$2,'PORTIFÓLIO'!$J$3:$Q$3,0))) * N('PORTIFÓLIO'!$S$4:$S$564), 0 ) ), 0)} -> 0 | I52: =H52/$H$4 -> 0 | J52: {=IFERROR( SUM( IF( 'PORTIFÓLIO'!$C$4:$C$564=$A52, N(INDEX('PORTIFÓLIO'!$J$4:$Q$564,,MATCH(J$2,'PORTIFÓLIO'!$J$3:$Q$3,0))) * N('PORTIFÓLIO'!$S$4:$S$564), 0 ) ), 0)} -> 0 | K52: =J52/$J$4 -> 0 | L52: {=IFERROR( SUM( IF( 'PORTIFÓLIO'!$C$4:$C$564=$A52, N(INDEX('PORTIFÓLIO'!$J$4:$Q$564,,MATCH(L$2,'PORTIFÓLIO'!$J$3:$Q$3,0))) * N('PORTIFÓLIO'!$S$4:$S$564), 0 ) ), 0)} -> 0 | M52: =L52/$L$4 -> 0 | N52: {=IFERROR( SUM( IF( 'PORTIFÓLIO'!$C$4:$C$564=$A52, N(INDEX('PORTIFÓLIO'!$J$4:$Q$564,,MATCH(N$2,'PORTIFÓLIO'!$J$3:$Q$3,0))) * N('PORTIFÓLIO'!$S$4:$S$564), 0 ) ), 0)} -> 0 | O52: =N52/$N$4 -> 0 | P52: {=IFERROR( SUM( IF( 'PORTIFÓLIO'!$C$4:$C$564=$A52, N(INDEX('PORTIFÓLIO'!$J$4:$Q$564,,MATCH(P$2,'PORTIFÓLIO'!$J$3:$Q$3,0))) * N('PORTIFÓLIO'!$S$4:$S$564), 0 ) ), 0)} -> 0 | Q52: =P52/$P$4 -> 0 | R52: =SUM(P52,N52,L52,J52,H52,D52,B52) -> 0 | S52: =R52/$R$4 -> 0
A53: =IFERROR(__xludf.DUMMYFUNCTION("""COMPUTED_VALUE"""),"ACCENT") -> ACCENT | B53: {=IFERROR( SUM( IF( 'PORTIFÓLIO'!$C$4:$C$564=$A53, N(INDEX('PORTIFÓLIO'!$J$4:$Q$564,,MATCH(B$2,'PORTIFÓLIO'!$J$3:$Q$3,0))) * N('PORTIFÓLIO'!$S$4:$S$564), 0 ) ), 0)} -> 0 | C53: =B53/$B$4 -> 0 | D53: {=IFERROR( SUM( IF( 'PORTIFÓLIO'!$C$4:$C$564=$A53, N(INDEX('PORTIFÓLIO'!$J$4:$Q$564,,MATCH(D$2,'PORTIFÓLIO'!$J$3:$Q$3,0))) * N('PORTIFÓLIO'!$S$4:$S$564), 0 ) ), 0)} -> 0 | E53: =D53/$D$4 -> 0 | F53: {=IFERROR( SUM( IF( 'PORTIFÓLIO'!$C$4:$C$564=$A53, N(INDEX('PORTIFÓLIO'!$J$4:$Q$564,,MATCH(F$2,'PORTIFÓLIO'!$J$3:$Q$3,0))) * N('PORTIFÓLIO'!$S$4:$S$564), 0 ) ), 0)} -> 0 | G53: =F53/$F$4 -> 0 | H53: {=IFERROR( SUM( IF( 'PORTIFÓLIO'!$C$4:$C$564=$A53, N(INDEX('PORTIFÓLIO'!$J$4:$Q$564,,MATCH(H$2,'PORTIFÓLIO'!$J$3:$Q$3,0))) * N('PORTIFÓLIO'!$S$4:$S$564), 0 ) ), 0)} -> 0 | I53: =H53/$H$4 -> 0 | J53: {=IFERROR( SUM( IF( 'PORTIFÓLIO'!$C$4:$C$564=$A53, N(INDEX('PORTIFÓLIO'!$J$4:$Q$564,,MATCH(J$2,'PORTIFÓLIO'!$J$3:$Q$3,0))) * N('PORTIFÓLIO'!$S$4:$S$564), 0 ) ), 0)} -> 0 | K53: =J53/$J$4 -> 0 | L53: {=IFERROR( SUM( IF( 'PORTIFÓLIO'!$C$4:$C$564=$A53, N(INDEX('PORTIFÓLIO'!$J$4:$Q$564,,MATCH(L$2,'PORTIFÓLIO'!$J$3:$Q$3,0))) * N('PORTIFÓLIO'!$S$4:$S$564), 0 ) ), 0)} -> 0 | M53: =L53/$L$4 -> 0 | N53: {=IFERROR( SUM( IF( 'PORTIFÓLIO'!$C$4:$C$564=$A53, N(INDEX('PORTIFÓLIO'!$J$4:$Q$564,,MATCH(N$2,'PORTIFÓLIO'!$J$3:$Q$3,0))) * N('PORTIFÓLIO'!$S$4:$S$564), 0 ) ), 0)} -> 0 | O53: =N53/$N$4 -> 0 | P53: {=IFERROR( SUM( IF( 'PORTIFÓLIO'!$C$4:$C$564=$A53, N(INDEX('PORTIFÓLIO'!$J$4:$Q$564,,MATCH(P$2,'PORTIFÓLIO'!$J$3:$Q$3,0))) * N('PORTIFÓLIO'!$S$4:$S$564), 0 ) ), 0)} -> 0 | Q53: =P53/$P$4 -> 0 | R53: =SUM(P53,N53,L53,J53,H53,D53,B53) -> 0 | S53: =R53/$R$4 -> 0
A54: =IFERROR(__xludf.DUMMYFUNCTION("""COMPUTED_VALUE"""),"CLASSIC") -> CLASSIC | B54: {=IFERROR( SUM( IF( 'PORTIFÓLIO'!$C$4:$C$564=$A54, N(INDEX('PORTIFÓLIO'!$J$4:$Q$564,,MATCH(B$2,'PORTIFÓLIO'!$J$3:$Q$3,0))) * N('PORTIFÓLIO'!$S$4:$S$564), 0 ) ), 0)} -> 0 | C54: =B54/$B$4 -> 0 | D54: {=IFERROR( SUM( IF( 'PORTIFÓLIO'!$C$4:$C$564=$A54, N(INDEX('PORTIFÓLIO'!$J$4:$Q$564,,MATCH(D$2,'PORTIFÓLIO'!$J$3:$Q$3,0))) * N('PORTIFÓLIO'!$S$4:$S$564), 0 ) ), 0)} -> 0 | E54: =D54/$D$4 -> 0 | F54: {=IFERROR( SUM( IF( 'PORTIFÓLIO'!$C$4:$C$564=$A54, N(INDEX('PORTIFÓLIO'!$J$4:$Q$564,,MATCH(F$2,'PORTIFÓLIO'!$J$3:$Q$3,0))) * N('PORTIFÓLIO'!$S$4:$S$564), 0 ) ), 0)} -> 0 | G54: =F54/$F$4 -> 0 | H54: {=IFERROR( SUM( IF( 'PORTIFÓLIO'!$C$4:$C$564=$A54, N(INDEX('PORTIFÓLIO'!$J$4:$Q$564,,MATCH(H$2,'PORTIFÓLIO'!$J$3:$Q$3,0))) * N('PORTIFÓLIO'!$S$4:$S$564), 0 ) ), 0)} -> 0 | I54: =H54/$H$4 -> 0 | J54: {=IFERROR( SUM( IF( 'PORTIFÓLIO'!$C$4:$C$564=$A54, N(INDEX('PORTIFÓLIO'!$J$4:$Q$564,,MATCH(J$2,'PORTIFÓLIO'!$J$3:$Q$3,0))) * N('PORTIFÓLIO'!$S$4:$S$564), 0 ) ), 0)} -> 0 | K54: =J54/$J$4 -> 0 | L54: {=IFERROR( SUM( IF( 'PORTIFÓLIO'!$C$4:$C$564=$A54, N(INDEX('PORTIFÓLIO'!$J$4:$Q$564,,MATCH(L$2,'PORTIFÓLIO'!$J$3:$Q$3,0))) * N('PORTIFÓLIO'!$S$4:$S$564), 0 ) ), 0)} -> 0 | M54: =L54/$L$4 -> 0 | N54: {=IFERROR( SUM( IF( 'PORTIFÓLIO'!$C$4:$C$564=$A54, N(INDEX('PORTIFÓLIO'!$J$4:$Q$564,,MATCH(N$2,'PORTIFÓLIO'!$J$3:$Q$3,0))) * N('PORTIFÓLIO'!$S$4:$S$564), 0 ) ), 0)} -> 0 | O54: =N54/$N$4 -> 0 | P54: {=IFERROR( SUM( IF( 'PORTIFÓLIO'!$C$4:$C$564=$A54, N(INDEX('PORTIFÓLIO'!$J$4:$Q$564,,MATCH(P$2,'PORTIFÓLIO'!$J$3:$Q$3,0))) * N('PORTIFÓLIO'!$S$4:$S$564), 0 ) ), 0)} -> 0 | Q54: =P54/$P$4 -> 0 | R54: =SUM(P54,N54,L54,J54,H54,D54,B54) -> 0 | S54: =R54/$R$4 -> 0
A55: =IFERROR(__xludf.DUMMYFUNCTION("""COMPUTED_VALUE"""),"CLINCHER") -> CLINCHER | B55: {=IFERROR( SUM( IF( 'PORTIFÓLIO'!$C$4:$C$564=$A55, N(INDEX('PORTIFÓLIO'!$J$4:$Q$564,,MATCH(B$2,'PORTIFÓLIO'!$J$3:$Q$3,0))) * N('PORTIFÓLIO'!$S$4:$S$564), 0 ) ), 0)} -> 0 | C55: =B55/$B$4 -> 0 | D55: {=IFERROR( SUM( IF( 'PORTIFÓLIO'!$C$4:$C$564=$A55, N(INDEX('PORTIFÓLIO'!$J$4:$Q$564,,MATCH(D$2,'PORTIFÓLIO'!$J$3:$Q$3,0))) * N('PORTIFÓLIO'!$S$4:$S$564), 0 ) ), 0)} -> 0 | E55: =D55/$D$4 -> 0 | F55: {=IFERROR( SUM( IF( 'PORTIFÓLIO'!$C$4:$C$564=$A55, N(INDEX('PORTIFÓLIO'!$J$4:$Q$564,,MATCH(F$2,'PORTIFÓLIO'!$J$3:$Q$3,0))) * N('PORTIFÓLIO'!$S$4:$S$564), 0 ) ), 0)} -> 0 | G55: =F55/$F$4 -> 0 | H55: {=IFERROR( SUM( IF( 'PORTIFÓLIO'!$C$4:$C$564=$A55, N(INDEX('PORTIFÓLIO'!$J$4:$Q$564,,MATCH(H$2,'PORTIFÓLIO'!$J$3:$Q$3,0))) * N('PORTIFÓLIO'!$S$4:$S$564), 0 ) ), 0)} -> 0 | I55: =H55/$H$4 -> 0 | J55: {=IFERROR( SUM( IF( 'PORTIFÓLIO'!$C$4:$C$564=$A55, N(INDEX('PORTIFÓLIO'!$J$4:$Q$564,,MATCH(J$2,'PORTIFÓLIO'!$J$3:$Q$3,0))) * N('PORTIFÓLIO'!$S$4:$S$564), 0 ) ), 0)} -> 0 | K55: =J55/$J$4 -> 0 | L55: {=IFERROR( SUM( IF( 'PORTIFÓLIO'!$C$4:$C$564=$A55, N(INDEX('PORTIFÓLIO'!$J$4:$Q$564,,MATCH(L$2,'PORTIFÓLIO'!$J$3:$Q$3,0))) * N('PORTIFÓLIO'!$S$4:$S$564), 0 ) ), 0)} -> 0 | M55: =L55/$L$4 -> 0 | N55: {=IFERROR( SUM( IF( 'PORTIFÓLIO'!$C$4:$C$564=$A55, N(INDEX('PORTIFÓLIO'!$J$4:$Q$564,,MATCH(N$2,'PORTIFÓLIO'!$J$3:$Q$3,0))) * N('PORTIFÓLIO'!$S$4:$S$564), 0 ) ), 0)} -> 0 | O55: =N55/$N$4 -> 0 | P55: {=IFERROR( SUM( IF( 'PORTIFÓLIO'!$C$4:$C$564=$A55, N(INDEX('PORTIFÓLIO'!$J$4:$Q$564,,MATCH(P$2,'PORTIFÓLIO'!$J$3:$Q$3,0))) * N('PORTIFÓLIO'!$S$4:$S$564), 0 ) ), 0)} -> 0 | Q55: =P55/$P$4 -> 0 | R55: =SUM(P55,N55,L55,J55,H55,D55,B55) -> 0 | S55: =R55/$R$4 -> 0
A56: =IFERROR(__xludf.DUMMYFUNCTION("""COMPUTED_VALUE"""),"ELEVORE") -> ELEVORE | B56: {=IFERROR( SUM( IF( 'PORTIFÓLIO'!$C$4:$C$564=$A56, N(INDEX('PORTIFÓLIO'!$J$4:$Q$564,,MATCH(B$2,'PORTIFÓLIO'!$J$3:$Q$3,0))) * N('PORTIFÓLIO'!$S$4:$S$564), 0 ) ), 0)} -> 0 | C56: =B56/$B$4 -> 0 | D56: {=IFERROR( SUM( IF( 'PORTIFÓLIO'!$C$4:$C$564=$A56, N(INDEX('PORTIFÓLIO'!$J$4:$Q$564,,MATCH(D$2,'PORTIFÓLIO'!$J$3:$Q$3,0))) * N('PORTIFÓLIO'!$S$4:$S$564), 0 ) ), 0)} -> 0 | E56: =D56/$D$4 -> 0 | F56: {=IFERROR( SUM( IF( 'PORTIFÓLIO'!$C$4:$C$564=$A56, N(INDEX('PORTIFÓLIO'!$J$4:$Q$564,,MATCH(F$2,'PORTIFÓLIO'!$J$3:$Q$3,0))) * N('PORTIFÓLIO'!$S$4:$S$564), 0 ) ), 0)} -> 0 | G56: =F56/$F$4 -> 0 | H56: {=IFERROR( SUM( IF( 'PORTIFÓLIO'!$C$4:$C$564=$A56, N(INDEX('PORTIFÓLIO'!$J$4:$Q$564,,MATCH(H$2,'PORTIFÓLIO'!$J$3:$Q$3,0))) * N('PORTIFÓLIO'!$S$4:$S$564), 0 ) ), 0)} -> 0 | I56: =H56/$H$4 -> 0 | J56: {=IFERROR( SUM( IF( 'PORTIFÓLIO'!$C$4:$C$564=$A56, N(INDEX('PORTIFÓLIO'!$J$4:$Q$564,,MATCH(J$2,'PORTIFÓLIO'!$J$3:$Q$3,0))) * N('PORTIFÓLIO'!$S$4:$S$564), 0 ) ), 0)} -> 0 | K56: =J56/$J$4 -> 0 | L56: {=IFERROR( SUM( IF( 'PORTIFÓLIO'!$C$4:$C$564=$A56, N(INDEX('PORTIFÓLIO'!$J$4:$Q$564,,MATCH(L$2,'PORTIFÓLIO'!$J$3:$Q$3,0))) * N('PORTIFÓLIO'!$S$4:$S$564), 0 ) ), 0)} -> 0 | M56: =L56/$L$4 -> 0 | N56: {=IFERROR( SUM( IF( 'PORTIFÓLIO'!$C$4:$C$564=$A56, N(INDEX('PORTIFÓLIO'!$J$4:$Q$564,,MATCH(N$2,'PORTIFÓLIO'!$J$3:$Q$3,0))) * N('PORTIFÓLIO'!$S$4:$S$564), 0 ) ), 0)} -> 0 | O56: =N56/$N$4 -> 0 | P56: {=IFERROR( SUM( IF( 'PORTIFÓLIO'!$C$4:$C$564=$A56, N(INDEX('PORTIFÓLIO'!$J$4:$Q$564,,MATCH(P$2,'PORTIFÓLIO'!$J$3:$Q$3,0))) * N('PORTIFÓLIO'!$S$4:$S$564), 0 ) ), 0)} -> 0 | Q56: =P56/$P$4 -> 0 | R56: =SUM(P56,N56,L56,J56,H56,D56,B56) -> 0 | S56: =R56/$R$4 -> 0
A57: =IFERROR(__xludf.DUMMYFUNCTION("""COMPUTED_VALUE"""),"ENLIST COLEX-D") -> ENLIST COLEX-D | B57: {=IFERROR( SUM( IF( 'PORTIFÓLIO'!$C$4:$C$564=$A57, N(INDEX('PORTIFÓLIO'!$J$4:$Q$564,,MATCH(B$2,'PORTIFÓLIO'!$J$3:$Q$3,0))) * N('PORTIFÓLIO'!$S$4:$S$564), 0 ) ), 0)} -> 0 | C57: =B57/$B$4 -> 0 | D57: {=IFERROR( SUM( IF( 'PORTIFÓLIO'!$C$4:$C$564=$A57, N(INDEX('PORTIFÓLIO'!$J$4:$Q$564,,MATCH(D$2,'PORTIFÓLIO'!$J$3:$Q$3,0))) * N('PORTIFÓLIO'!$S$4:$S$564), 0 ) ), 0)} -> 0 | E57: =D57/$D$4 -> 0 | F57: {=IFERROR( SUM( IF( 'PORTIFÓLIO'!$C$4:$C$564=$A57, N(INDEX('PORTIFÓLIO'!$J$4:$Q$564,,MATCH(F$2,'PORTIFÓLIO'!$J$3:$Q$3,0))) * N('PORTIFÓLIO'!$S$4:$S$564), 0 ) ), 0)} -> 0 | G57: =F57/$F$4 -> 0 | H57: {=IFERROR( SUM( IF( 'PORTIFÓLIO'!$C$4:$C$564=$A57, N(INDEX('PORTIFÓLIO'!$J$4:$Q$564,,MATCH(H$2,'PORTIFÓLIO'!$J$3:$Q$3,0))) * N('PORTIFÓLIO'!$S$4:$S$564), 0 ) ), 0)} -> 0 | I57: =H57/$H$4 -> 0 | J57: {=IFERROR( SUM( IF( 'PORTIFÓLIO'!$C$4:$C$564=$A57, N(INDEX('PORTIFÓLIO'!$J$4:$Q$564,,MATCH(J$2,'PORTIFÓLIO'!$J$3:$Q$3,0))) * N('PORTIFÓLIO'!$S$4:$S$564), 0 ) ), 0)} -> 0 | K57: =J57/$J$4 -> 0 | L57: {=IFERROR( SUM( IF( 'PORTIFÓLIO'!$C$4:$C$564=$A57, N(INDEX('PORTIFÓLIO'!$J$4:$Q$564,,MATCH(L$2,'PORTIFÓLIO'!$J$3:$Q$3,0))) * N('PORTIFÓLIO'!$S$4:$S$564), 0 ) ), 0)} -> 0 | M57: =L57/$L$4 -> 0 | N57: {=IFERROR( SUM( IF( 'PORTIFÓLIO'!$C$4:$C$564=$A57, N(INDEX('PORTIFÓLIO'!$J$4:$Q$564,,MATCH(N$2,'PORTIFÓLIO'!$J$3:$Q$3,0))) * N('PORTIFÓLIO'!$S$4:$S$564), 0 ) ), 0)} -> 0 | O57: =N57/$N$4 -> 0 | P57: {=IFERROR( SUM( IF( 'PORTIFÓLIO'!$C$4:$C$564=$A57, N(INDEX('PORTIFÓLIO'!$J$4:$Q$564,,MATCH(P$2,'PORTIFÓLIO'!$J$3:$Q$3,0))) * N('PORTIFÓLIO'!$S$4:$S$564), 0 ) ), 0)} -> 0 | Q57: =P57/$P$4 -> 0 | R57: =SUM(P57,N57,L57,J57,H57,D57,B57) -> 0 | S57: =R57/$R$4 -> 0
A58: =IFERROR(__xludf.DUMMYFUNCTION("""COMPUTED_VALUE"""),"GAPPER") -> GAPPER | B58: {=IFERROR( SUM( IF( 'PORTIFÓLIO'!$C$4:$C$564=$A58, N(INDEX('PORTIFÓLIO'!$J$4:$Q$564,,MATCH(B$2,'PORTIFÓLIO'!$J$3:$Q$3,0))) * N('PORTIFÓLIO'!$S$4:$S$564), 0 ) ), 0)} -> 0 | C58: =B58/$B$4 -> 0 | D58: {=IFERROR( SUM( IF( 'PORTIFÓLIO'!$C$4:$C$564=$A58, N(INDEX('PORTIFÓLIO'!$J$4:$Q$564,,MATCH(D$2,'PORTIFÓLIO'!$J$3:$Q$3,0))) * N('PORTIFÓLIO'!$S$4:$S$564), 0 ) ), 0)} -> 0 | E58: =D58/$D$4 -> 0 | F58: {=IFERROR( SUM( IF( 'PORTIFÓLIO'!$C$4:$C$564=$A58, N(INDEX('PORTIFÓLIO'!$J$4:$Q$564,,MATCH(F$2,'PORTIFÓLIO'!$J$3:$Q$3,0))) * N('PORTIFÓLIO'!$S$4:$S$564), 0 ) ), 0)} -> 0 | G58: =F58/$F$4 -> 0 | H58: {=IFERROR( SUM( IF( 'PORTIFÓLIO'!$C$4:$C$564=$A58, N(INDEX('PORTIFÓLIO'!$J$4:$Q$564,,MATCH(H$2,'PORTIFÓLIO'!$J$3:$Q$3,0))) * N('PORTIFÓLIO'!$S$4:$S$564), 0 ) ), 0)} -> 0 | I58: =H58/$H$4 -> 0 | J58: {=IFERROR( SUM( IF( 'PORTIFÓLIO'!$C$4:$C$564=$A58, N(INDEX('PORTIFÓLIO'!$J$4:$Q$564,,MATCH(J$2,'PORTIFÓLIO'!$J$3:$Q$3,0))) * N('PORTIFÓLIO'!$S$4:$S$564), 0 ) ), 0)} -> 0 | K58: =J58/$J$4 -> 0 | L58: {=IFERROR( SUM( IF( 'PORTIFÓLIO'!$C$4:$C$564=$A58, N(INDEX('PORTIFÓLIO'!$J$4:$Q$564,,MATCH(L$2,'PORTIFÓLIO'!$J$3:$Q$3,0))) * N('PORTIFÓLIO'!$S$4:$S$564), 0 ) ), 0)} -> 0 | M58: =L58/$L$4 -> 0 | N58: {=IFERROR( SUM( IF( 'PORTIFÓLIO'!$C$4:$C$564=$A58, N(INDEX('PORTIFÓLIO'!$J$4:$Q$564,,MATCH(N$2,'PORTIFÓLIO'!$J$3:$Q$3,0))) * N('PORTIFÓLIO'!$S$4:$S$564), 0 ) ), 0)} -> 0 | O58: =N58/$N$4 -> 0 | P58: {=IFERROR( SUM( IF( 'PORTIFÓLIO'!$C$4:$C$564=$A58, N(INDEX('PORTIFÓLIO'!$J$4:$Q$564,,MATCH(P$2,'PORTIFÓLIO'!$J$3:$Q$3,0))) * N('PORTIFÓLIO'!$S$4:$S$564), 0 ) ), 0)} -> 0 | Q58: =P58/$P$4 -> 0 | R58: =SUM(P58,N58,L58,J58,H58,D58,B58) -> 0 | S58: =R58/$R$4 -> 0
A59: =IFERROR(__xludf.DUMMYFUNCTION("""COMPUTED_VALUE"""),"PACTO") -> PACTO | B59: {=IFERROR( SUM( IF( 'PORTIFÓLIO'!$C$4:$C$564=$A59, N(INDEX('PORTIFÓLIO'!$J$4:$Q$564,,MATCH(B$2,'PORTIFÓLIO'!$J$3:$Q$3,0))) * N('PORTIFÓLIO'!$S$4:$S$564), 0 ) ), 0)} -> 0 | C59: =B59/$B$4 -> 0 | D59: {=IFERROR( SUM( IF( 'PORTIFÓLIO'!$C$4:$C$564=$A59, N(INDEX('PORTIFÓLIO'!$J$4:$Q$564,,MATCH(D$2,'PORTIFÓLIO'!$J$3:$Q$3,0))) * N('PORTIFÓLIO'!$S$4:$S$564), 0 ) ), 0)} -> 0 | E59: =D59/$D$4 -> 0 | F59: {=IFERROR( SUM( IF( 'PORTIFÓLIO'!$C$4:$C$564=$A59, N(INDEX('PORTIFÓLIO'!$J$4:$Q$564,,MATCH(F$2,'PORTIFÓLIO'!$J$3:$Q$3,0))) * N('PORTIFÓLIO'!$S$4:$S$564), 0 ) ), 0)} -> 0 | G59: =F59/$F$4 -> 0 | H59: {=IFERROR( SUM( IF( 'PORTIFÓLIO'!$C$4:$C$564=$A59, N(INDEX('PORTIFÓLIO'!$J$4:$Q$564,,MATCH(H$2,'PORTIFÓLIO'!$J$3:$Q$3,0))) * N('PORTIFÓLIO'!$S$4:$S$564), 0 ) ), 0)} -> 0 | I59: =H59/$H$4 -> 0 | J59: {=IFERROR( SUM( IF( 'PORTIFÓLIO'!$C$4:$C$564=$A59, N(INDEX('PORTIFÓLIO'!$J$4:$Q$564,,MATCH(J$2,'PORTIFÓLIO'!$J$3:$Q$3,0))) * N('PORTIFÓLIO'!$S$4:$S$564), 0 ) ), 0)} -> 0 | K59: =J59/$J$4 -> 0 | L59: {=IFERROR( SUM( IF( 'PORTIFÓLIO'!$C$4:$C$564=$A59, N(INDEX('PORTIFÓLIO'!$J$4:$Q$564,,MATCH(L$2,'PORTIFÓLIO'!$J$3:$Q$3,0))) * N('PORTIFÓLIO'!$S$4:$S$564), 0 ) ), 0)} -> 0 | M59: =L59/$L$4 -> 0 | N59: {=IFERROR( SUM( IF( 'PORTIFÓLIO'!$C$4:$C$564=$A59, N(INDEX('PORTIFÓLIO'!$J$4:$Q$564,,MATCH(N$2,'PORTIFÓLIO'!$J$3:$Q$3,0))) * N('PORTIFÓLIO'!$S$4:$S$564), 0 ) ), 0)} -> 0 | O59: =N59/$N$4 -> 0 | P59: {=IFERROR( SUM( IF( 'PORTIFÓLIO'!$C$4:$C$564=$A59, N(INDEX('PORTIFÓLIO'!$J$4:$Q$564,,MATCH(P$2,'PORTIFÓLIO'!$J$3:$Q$3,0))) * N('PORTIFÓLIO'!$S$4:$S$564), 0 ) ), 0)} -> 0 | Q59: =P59/$P$4 -> 0 | R59: =SUM(P59,N59,L59,J59,H59,D59,B59) -> 0 | S59: =R59/$R$4 -> 0
A60: =IFERROR(__xludf.DUMMYFUNCTION("""COMPUTED_VALUE"""),"PAXEO") -> PAXEO | B60: {=IFERROR( SUM( IF( 'PORTIFÓLIO'!$C$4:$C$564=$A60, N(INDEX('PORTIFÓLIO'!$J$4:$Q$564,,MATCH(B$2,'PORTIFÓLIO'!$J$3:$Q$3,0))) * N('PORTIFÓLIO'!$S$4:$S$564), 0 ) ), 0)} -> 0 | C60: =B60/$B$4 -> 0 | D60: {=IFERROR( SUM( IF( 'PORTIFÓLIO'!$C$4:$C$564=$A60, N(INDEX('PORTIFÓLIO'!$J$4:$Q$564,,MATCH(D$2,'PORTIFÓLIO'!$J$3:$Q$3,0))) * N('PORTIFÓLIO'!$S$4:$S$564), 0 ) ), 0)} -> 0 | E60: =D60/$D$4 -> 0 | F60: {=IFERROR( SUM( IF( 'PORTIFÓLIO'!$C$4:$C$564=$A60, N(INDEX('PORTIFÓLIO'!$J$4:$Q$564,,MATCH(F$2,'PORTIFÓLIO'!$J$3:$Q$3,0))) * N('PORTIFÓLIO'!$S$4:$S$564), 0 ) ), 0)} -> 0 | G60: =F60/$F$4 -> 0 | H60: {=IFERROR( SUM( IF( 'PORTIFÓLIO'!$C$4:$C$564=$A60, N(INDEX('PORTIFÓLIO'!$J$4:$Q$564,,MATCH(H$2,'PORTIFÓLIO'!$J$3:$Q$3,0))) * N('PORTIFÓLIO'!$S$4:$S$564), 0 ) ), 0)} -> 0 | I60: =H60/$H$4 -> 0 | J60: {=IFERROR( SUM( IF( 'PORTIFÓLIO'!$C$4:$C$564=$A60, N(INDEX('PORTIFÓLIO'!$J$4:$Q$564,,MATCH(J$2,'PORTIFÓLIO'!$J$3:$Q$3,0))) * N('PORTIFÓLIO'!$S$4:$S$564), 0 ) ), 0)} -> 0 | K60: =J60/$J$4 -> 0 | L60: {=IFERROR( SUM( IF( 'PORTIFÓLIO'!$C$4:$C$564=$A60, N(INDEX('PORTIFÓLIO'!$J$4:$Q$564,,MATCH(L$2,'PORTIFÓLIO'!$J$3:$Q$3,0))) * N('PORTIFÓLIO'!$S$4:$S$564), 0 ) ), 0)} -> 0 | M60: =L60/$L$4 -> 0 | N60: {=IFERROR( SUM( IF( 'PORTIFÓLIO'!$C$4:$C$564=$A60, N(INDEX('PORTIFÓLIO'!$J$4:$Q$564,,MATCH(N$2,'PORTIFÓLIO'!$J$3:$Q$3,0))) * N('PORTIFÓLIO'!$S$4:$S$564), 0 ) ), 0)} -> 0 | O60: =N60/$N$4 -> 0 | P60: {=IFERROR( SUM( IF( 'PORTIFÓLIO'!$C$4:$C$564=$A60, N(INDEX('PORTIFÓLIO'!$J$4:$Q$564,,MATCH(P$2,'PORTIFÓLIO'!$J$3:$Q$3,0))) * N('PORTIFÓLIO'!$S$4:$S$564), 0 ) ), 0)} -> 0 | Q60: =P60/$P$4 -> 0 | R60: =SUM(P60,N60,L60,J60,H60,D60,B60) -> 0 | S60: =R60/$R$4 -> 0
A61: =IFERROR(__xludf.DUMMYFUNCTION("""COMPUTED_VALUE"""),"SPIDER 840 WG") -> SPIDER 840 WG | B61: {=IFERROR( SUM( IF( 'PORTIFÓLIO'!$C$4:$C$564=$A61, N(INDEX('PORTIFÓLIO'!$J$4:$Q$564,,MATCH(B$2,'PORTIFÓLIO'!$J$3:$Q$3,0))) * N('PORTIFÓLIO'!$S$4:$S$564), 0 ) ), 0)} -> 0 | C61: =B61/$B$4 -> 0 | D61: {=IFERROR( SUM( IF( 'PORTIFÓLIO'!$C$4:$C$564=$A61, N(INDEX('PORTIFÓLIO'!$J$4:$Q$564,,MATCH(D$2,'PORTIFÓLIO'!$J$3:$Q$3,0))) * N('PORTIFÓLIO'!$S$4:$S$564), 0 ) ), 0)} -> 0 | E61: =D61/$D$4 -> 0 | F61: {=IFERROR( SUM( IF( 'PORTIFÓLIO'!$C$4:$C$564=$A61, N(INDEX('PORTIFÓLIO'!$J$4:$Q$564,,MATCH(F$2,'PORTIFÓLIO'!$J$3:$Q$3,0))) * N('PORTIFÓLIO'!$S$4:$S$564), 0 ) ), 0)} -> 0 | G61: =F61/$F$4 -> 0 | H61: {=IFERROR( SUM( IF( 'PORTIFÓLIO'!$C$4:$C$564=$A61, N(INDEX('PORTIFÓLIO'!$J$4:$Q$564,,MATCH(H$2,'PORTIFÓLIO'!$J$3:$Q$3,0))) * N('PORTIFÓLIO'!$S$4:$S$564), 0 ) ), 0)} -> 0 | I61: =H61/$H$4 -> 0 | J61: {=IFERROR( SUM( IF( 'PORTIFÓLIO'!$C$4:$C$564=$A61, N(INDEX('PORTIFÓLIO'!$J$4:$Q$564,,MATCH(J$2,'PORTIFÓLIO'!$J$3:$Q$3,0))) * N('PORTIFÓLIO'!$S$4:$S$564), 0 ) ), 0)} -> 0 | K61: =J61/$J$4 -> 0 | L61: {=IFERROR( SUM( IF( 'PORTIFÓLIO'!$C$4:$C$564=$A61, N(INDEX('PORTIFÓLIO'!$J$4:$Q$564,,MATCH(L$2,'PORTIFÓLIO'!$J$3:$Q$3,0))) * N('PORTIFÓLIO'!$S$4:$S$564), 0 ) ), 0)} -> 0 | M61: =L61/$L$4 -> 0 | N61: {=IFERROR( SUM( IF( 'PORTIFÓLIO'!$C$4:$C$564=$A61, N(INDEX('PORTIFÓLIO'!$J$4:$Q$564,,MATCH(N$2,'PORTIFÓLIO'!$J$3:$Q$3,0))) * N('PORTIFÓLIO'!$S$4:$S$564), 0 ) ), 0)} -> 0 | O61: =N61/$N$4 -> 0 | P61: {=IFERROR( SUM( IF( 'PORTIFÓLIO'!$C$4:$C$564=$A61, N(INDEX('PORTIFÓLIO'!$J$4:$Q$564,,MATCH(P$2,'PORTIFÓLIO'!$J$3:$Q$3,0))) * N('PORTIFÓLIO'!$S$4:$S$564), 0 ) ), 0)} -> 0 | Q61: =P61/$P$4 -> 0 | R61: =SUM(P61,N61,L61,J61,H61,D61,B61) -> 0 | S61: =R61/$R$4 -> 0
A62: =IFERROR(__xludf.DUMMYFUNCTION("""COMPUTED_VALUE"""),"VERDICT ULTRA") -> VERDICT ULTRA | B62: {=IFERROR( SUM( IF( 'PORTIFÓLIO'!$C$4:$C$564=$A62, N(INDEX('PORTIFÓLIO'!$J$4:$Q$564,,MATCH(B$2,'PORTIFÓLIO'!$J$3:$Q$3,0))) * N('PORTIFÓLIO'!$S$4:$S$564), 0 ) ), 0)} -> 0 | C62: =B62/$B$4 -> 0 | D62: {=IFERROR( SUM( IF( 'PORTIFÓLIO'!$C$4:$C$564=$A62, N(INDEX('PORTIFÓLIO'!$J$4:$Q$564,,MATCH(D$2,'PORTIFÓLIO'!$J$3:$Q$3,0))) * N('PORTIFÓLIO'!$S$4:$S$564), 0 ) ), 0)} -> 0 | E62: =D62/$D$4 -> 0 | F62: {=IFERROR( SUM( IF( 'PORTIFÓLIO'!$C$4:$C$564=$A62, N(INDEX('PORTIFÓLIO'!$J$4:$Q$564,,MATCH(F$2,'PORTIFÓLIO'!$J$3:$Q$3,0))) * N('PORTIFÓLIO'!$S$4:$S$564), 0 ) ), 0)} -> 0 | G62: =F62/$F$4 -> 0 | H62: {=IFERROR( SUM( IF( 'PORTIFÓLIO'!$C$4:$C$564=$A62, N(INDEX('PORTIFÓLIO'!$J$4:$Q$564,,MATCH(H$2,'PORTIFÓLIO'!$J$3:$Q$3,0))) * N('PORTIFÓLIO'!$S$4:$S$564), 0 ) ), 0)} -> 0 | I62: =H62/$H$4 -> 0 | J62: {=IFERROR( SUM( IF( 'PORTIFÓLIO'!$C$4:$C$564=$A62, N(INDEX('PORTIFÓLIO'!$J$4:$Q$564,,MATCH(J$2,'PORTIFÓLIO'!$J$3:$Q$3,0))) * N('PORTIFÓLIO'!$S$4:$S$564), 0 ) ), 0)} -> 0 | K62: =J62/$J$4 -> 0 | L62: {=IFERROR( SUM( IF( 'PORTIFÓLIO'!$C$4:$C$564=$A62, N(INDEX('PORTIFÓLIO'!$J$4:$Q$564,,MATCH(L$2,'PORTIFÓLIO'!$J$3:$Q$3,0))) * N('PORTIFÓLIO'!$S$4:$S$564), 0 ) ), 0)} -> 0 | M62: =L62/$L$4 -> 0 | N62: {=IFERROR( SUM( IF( 'PORTIFÓLIO'!$C$4:$C$564=$A62, N(INDEX('PORTIFÓLIO'!$J$4:$Q$564,,MATCH(N$2,'PORTIFÓLIO'!$J$3:$Q$3,0))) * N('PORTIFÓLIO'!$S$4:$S$564), 0 ) ), 0)} -> 0 | O62: =N62/$N$4 -> 0 | P62: {=IFERROR( SUM( IF( 'PORTIFÓLIO'!$C$4:$C$564=$A62, N(INDEX('PORTIFÓLIO'!$J$4:$Q$564,,MATCH(P$2,'PORTIFÓLIO'!$J$3:$Q$3,0))) * N('PORTIFÓLIO'!$S$4:$S$564), 0 ) ), 0)} -> 0 | Q62: =P62/$P$4 -> 0 | R62: =SUM(P62,N62,L62,J62,H62,D62,B62) -> 0 | S62: =R62/$R$4 -> 0
A63: =IFERROR(__xludf.DUMMYFUNCTION("""COMPUTED_VALUE"""),"BLOWOUT") -> BLOWOUT | B63: {=IFERROR( SUM( IF( 'PORTIFÓLIO'!$C$4:$C$564=$A63, N(INDEX('PORTIFÓLIO'!$J$4:$Q$564,,MATCH(B$2,'PORTIFÓLIO'!$J$3:$Q$3,0))) * N('PORTIFÓLIO'!$S$4:$S$564), 0 ) ), 0)} -> 0 | C63: =B63/$B$4 -> 0 | D63: {=IFERROR( SUM( IF( 'PORTIFÓLIO'!$C$4:$C$564=$A63, N(INDEX('PORTIFÓLIO'!$J$4:$Q$564,,MATCH(D$2,'PORTIFÓLIO'!$J$3:$Q$3,0))) * N('PORTIFÓLIO'!$S$4:$S$564), 0 ) ), 0)} -> 0 | E63: =D63/$D$4 -> 0 | F63: {=IFERROR( SUM( IF( 'PORTIFÓLIO'!$C$4:$C$564=$A63, N(INDEX('PORTIFÓLIO'!$J$4:$Q$564,,MATCH(F$2,'PORTIFÓLIO'!$J$3:$Q$3,0))) * N('PORTIFÓLIO'!$S$4:$S$564), 0 ) ), 0)} -> 0 | G63: =F63/$F$4 -> 0 | H63: {=IFERROR( SUM( IF( 'PORTIFÓLIO'!$C$4:$C$564=$A63, N(INDEX('PORTIFÓLIO'!$J$4:$Q$564,,MATCH(H$2,'PORTIFÓLIO'!$J$3:$Q$3,0))) * N('PORTIFÓLIO'!$S$4:$S$564), 0 ) ), 0)} -> 0 | I63: =H63/$H$4 -> 0 | J63: {=IFERROR( SUM( IF( 'PORTIFÓLIO'!$C$4:$C$564=$A63, N(INDEX('PORTIFÓLIO'!$J$4:$Q$564,,MATCH(J$2,'PORTIFÓLIO'!$J$3:$Q$3,0))) * N('PORTIFÓLIO'!$S$4:$S$564), 0 ) ), 0)} -> 0 | K63: =J63/$J$4 -> 0 | L63: {=IFERROR( SUM( IF( 'PORTIFÓLIO'!$C$4:$C$564=$A63, N(INDEX('PORTIFÓLIO'!$J$4:$Q$564,,MATCH(L$2,'PORTIFÓLIO'!$J$3:$Q$3,0))) * N('PORTIFÓLIO'!$S$4:$S$564), 0 ) ), 0)} -> 0 | M63: =L63/$L$4 -> 0 | N63: {=IFERROR( SUM( IF( 'PORTIFÓLIO'!$C$4:$C$564=$A63, N(INDEX('PORTIFÓLIO'!$J$4:$Q$564,,MATCH(N$2,'PORTIFÓLIO'!$J$3:$Q$3,0))) * N('PORTIFÓLIO'!$S$4:$S$564), 0 ) ), 0)} -> 0 | O63: =N63/$N$4 -> 0 | P63: {=IFERROR( SUM( IF( 'PORTIFÓLIO'!$C$4:$C$564=$A63, N(INDEX('PORTIFÓLIO'!$J$4:$Q$564,,MATCH(P$2,'PORTIFÓLIO'!$J$3:$Q$3,0))) * N('PORTIFÓLIO'!$S$4:$S$564), 0 ) ), 0)} -> 0 | Q63: =P63/$P$4 -> 0 | R63: =SUM(P63,N63,L63,J63,H63,D63,B63) -> 0 | S63: =R63/$R$4 -> 0
A64: =IFERROR(__xludf.DUMMYFUNCTION("""COMPUTED_VALUE"""),"CLETODIM 240 EC BRILLIANCE") -> CLETODIM 240 EC BRILLIANCE | B64: {=IFERROR( SUM( IF( 'PORTIFÓLIO'!$C$4:$C$564=$A64, N(INDEX('PORTIFÓLIO'!$J$4:$Q$564,,MATCH(B$2,'PORTIFÓLIO'!$J$3:$Q$3,0))) * N('PORTIFÓLIO'!$S$4:$S$564), 0 ) ), 0)} -> 0 | C64: =B64/$B$4 -> 0 | D64: {=IFERROR( SUM( IF( 'PORTIFÓLIO'!$C$4:$C$564=$A64, N(INDEX('PORTIFÓLIO'!$J$4:$Q$564,,MATCH(D$2,'PORTIFÓLIO'!$J$3:$Q$3,0))) * N('PORTIFÓLIO'!$S$4:$S$564), 0 ) ), 0)} -> 740.3496 | E64: =D64/$D$4 -> 2.467832 | F64: {=IFERROR( SUM( IF( 'PORTIFÓLIO'!$C$4:$C$564=$A64, N(INDEX('PORTIFÓLIO'!$J$4:$Q$564,,MATCH(F$2,'PORTIFÓLIO'!$J$3:$Q$3,0))) * N('PORTIFÓLIO'!$S$4:$S$564), 0 ) ), 0)} -> 0 | G64: =F64/$F$4 -> 0 | H64: {=IFERROR( SUM( IF( 'PORTIFÓLIO'!$C$4:$C$564=$A64, N(INDEX('PORTIFÓLIO'!$J$4:$Q$564,,MATCH(H$2,'PORTIFÓLIO'!$J$3:$Q$3,0))) * N('PORTIFÓLIO'!$S$4:$S$564), 0 ) ), 0)} -> 0 | I64: =H64/$H$4 -> 0 | J64: {=IFERROR( SUM( IF( 'PORTIFÓLIO'!$C$4:$C$564=$A64, N(INDEX('PORTIFÓLIO'!$J$4:$Q$564,,MATCH(J$2,'PORTIFÓLIO'!$J$3:$Q$3,0))) * N('PORTIFÓLIO'!$S$4:$S$564), 0 ) ), 0)} -> 0 | K64: =J64/$J$4 -> 0 | L64: {=IFERROR( SUM( IF( 'PORTIFÓLIO'!$C$4:$C$564=$A64, N(INDEX('PORTIFÓLIO'!$J$4:$Q$564,,MATCH(L$2,'PORTIFÓLIO'!$J$3:$Q$3,0))) * N('PORTIFÓLIO'!$S$4:$S$564), 0 ) ), 0)} -> 0 | M64: =L64/$L$4 -> 0 | N64: {=IFERROR( SUM( IF( 'PORTIFÓLIO'!$C$4:$C$564=$A64, N(INDEX('PORTIFÓLIO'!$J$4:$Q$564,,MATCH(N$2,'PORTIFÓLIO'!$J$3:$Q$3,0))) * N('PORTIFÓLIO'!$S$4:$S$564), 0 ) ), 0)} -> 18885.084 | O64: =N64/$N$4 -> 15.504995 | P64: {=IFERROR( SUM( IF( 'PORTIFÓLIO'!$C$4:$C$564=$A64, N(INDEX('PORTIFÓLIO'!$J$4:$Q$564,,MATCH(P$2,'PORTIFÓLIO'!$J$3:$Q$3,0))) * N('PORTIFÓLIO'!$S$4:$S$564), 0 ) ), 0)} -> 5182.4472 | Q64: =P64/$P$4 -> 16.195148 | R64: =SUM(P64,N64,L64,J64,H64,D64,B64) -> 24807.881 | S64: =R64/$R$4 -> 7.4186248
A65: =IFERROR(__xludf.DUMMYFUNCTION("""COMPUTED_VALUE"""),"GLUFOS-WYN 880") -> GLUFOS-WYN 880 | B65: {=IFERROR( SUM( IF( 'PORTIFÓLIO'!$C$4:$C$564=$A65, N(INDEX('PORTIFÓLIO'!$J$4:$Q$564,,MATCH(B$2,'PORTIFÓLIO'!$J$3:$Q$3,0))) * N('PORTIFÓLIO'!$S$4:$S$564), 0 ) ), 0)} -> 22558.787 | C65: =B65/$B$4 -> 46.03834 | D65: {=IFERROR( SUM( IF( 'PORTIFÓLIO'!$C$4:$C$564=$A65, N(INDEX('PORTIFÓLIO'!$J$4:$Q$564,,MATCH(D$2,'PORTIFÓLIO'!$J$3:$Q$3,0))) * N('PORTIFÓLIO'!$S$4:$S$564), 0 ) ), 0)} -> 3683.0672 | E65: =D65/$D$4 -> 12.276891 | F65: {=IFERROR( SUM( IF( 'PORTIFÓLIO'!$C$4:$C$564=$A65, N(INDEX('PORTIFÓLIO'!$J$4:$Q$564,,MATCH(F$2,'PORTIFÓLIO'!$J$3:$Q$3,0))) * N('PORTIFÓLIO'!$S$4:$S$564), 0 ) ), 0)} -> 5064.2174 | G65: =F65/$F$4 -> 23.01917 | H65: {=IFERROR( SUM( IF( 'PORTIFÓLIO'!$C$4:$C$564=$A65, N(INDEX('PORTIFÓLIO'!$J$4:$Q$564,,MATCH(H$2,'PORTIFÓLIO'!$J$3:$Q$3,0))) * N('PORTIFÓLIO'!$S$4:$S$564), 0 ) ), 0)} -> 0 | I65: =H65/$H$4 -> 0 | J65: {=IFERROR( SUM( IF( 'PORTIFÓLIO'!$C$4:$C$564=$A65, N(INDEX('PORTIFÓLIO'!$J$4:$Q$564,,MATCH(J$2,'PORTIFÓLIO'!$J$3:$Q$3,0))) * N('PORTIFÓLIO'!$S$4:$S$564), 0 ) ), 0)} -> 12899.943 | K65: =J65/$J$4 -> 34.308359 | L65: {=IFERROR( SUM( IF( 'PORTIFÓLIO'!$C$4:$C$564=$A65, N(INDEX('PORTIFÓLIO'!$J$4:$Q$564,,MATCH(L$2,'PORTIFÓLIO'!$J$3:$Q$3,0))) * N('PORTIFÓLIO'!$S$4:$S$564), 0 ) ), 0)} -> 10128.435 | M65: =L65/$L$4 -> 46.03834 | N65: {=IFERROR( SUM( IF( 'PORTIFÓLIO'!$C$4:$C$564=$A65, N(INDEX('PORTIFÓLIO'!$J$4:$Q$564,,MATCH(N$2,'PORTIFÓLIO'!$J$3:$Q$3,0))) * N('PORTIFÓLIO'!$S$4:$S$564), 0 ) ), 0)} -> 28773.963 | O65: =N65/$N$4 -> 23.623943 | P65: {=IFERROR( SUM( IF( 'PORTIFÓLIO'!$C$4:$C$564=$A65, N(INDEX('PORTIFÓLIO'!$J$4:$Q$564,,MATCH(P$2,'PORTIFÓLIO'!$J$3:$Q$3,0))) * N('PORTIFÓLIO'!$S$4:$S$564), 0 ) ), 0)} -> 4603.834 | Q65: =P65/$P$4 -> 14.386981 | R65: =SUM(P65,N65,L65,J65,H65,D65,B65) -> 82648.028 | S65: =R65/$R$4 -> 24.715319
A66: =IFERROR(__xludf.DUMMYFUNCTION("""COMPUTED_VALUE"""),"GINETE 212 SL") -> GINETE 212 SL | B66: {=IFERROR( SUM( IF( 'PORTIFÓLIO'!$C$4:$C$564=$A66, N(INDEX('PORTIFÓLIO'!$J$4:$Q$564,,MATCH(B$2,'PORTIFÓLIO'!$J$3:$Q$3,0))) * N('PORTIFÓLIO'!$S$4:$S$564), 0 ) ), 0)} -> 0 | C66: =B66/$B$4 -> 0 | D66: {=IFERROR( SUM( IF( 'PORTIFÓLIO'!$C$4:$C$564=$A66, N(INDEX('PORTIFÓLIO'!$J$4:$Q$564,,MATCH(D$2,'PORTIFÓLIO'!$J$3:$Q$3,0))) * N('PORTIFÓLIO'!$S$4:$S$564), 0 ) ), 0)} -> 0 | E66: =D66/$D$4 -> 0 | F66: {=IFERROR( SUM( IF( 'PORTIFÓLIO'!$C$4:$C$564=$A66, N(INDEX('PORTIFÓLIO'!$J$4:$Q$564,,MATCH(F$2,'PORTIFÓLIO'!$J$3:$Q$3,0))) * N('PORTIFÓLIO'!$S$4:$S$564), 0 ) ), 0)} -> 0 | G66: =F66/$F$4 -> 0 | H66: {=IFERROR( SUM( IF( 'PORTIFÓLIO'!$C$4:$C$564=$A66, N(INDEX('PORTIFÓLIO'!$J$4:$Q$564,,MATCH(H$2,'PORTIFÓLIO'!$J$3:$Q$3,0))) * N('PORTIFÓLIO'!$S$4:$S$564), 0 ) ), 0)} -> 0 | I66: =H66/$H$4 -> 0 | J66: {=IFERROR( SUM( IF( 'PORTIFÓLIO'!$C$4:$C$564=$A66, N(INDEX('PORTIFÓLIO'!$J$4:$Q$564,,MATCH(J$2,'PORTIFÓLIO'!$J$3:$Q$3,0))) * N('PORTIFÓLIO'!$S$4:$S$564), 0 ) ), 0)} -> 0 | K66: =J66/$J$4 -> 0 | L66: {=IFERROR( SUM( IF( 'PORTIFÓLIO'!$C$4:$C$564=$A66, N(INDEX('PORTIFÓLIO'!$J$4:$Q$564,,MATCH(L$2,'PORTIFÓLIO'!$J$3:$Q$3,0))) * N('PORTIFÓLIO'!$S$4:$S$564), 0 ) ), 0)} -> 0 | M66: =L66/$L$4 -> 0 | N66: {=IFERROR( SUM( IF( 'PORTIFÓLIO'!$C$4:$C$564=$A66, N(INDEX('PORTIFÓLIO'!$J$4:$Q$564,,MATCH(N$2,'PORTIFÓLIO'!$J$3:$Q$3,0))) * N('PORTIFÓLIO'!$S$4:$S$564), 0 ) ), 0)} -> 0 | O66: =N66/$N$4 -> 0 | P66: {=IFERROR( SUM( IF( 'PORTIFÓLIO'!$C$4:$C$564=$A66, N(INDEX('PORTIFÓLIO'!$J$4:$Q$564,,MATCH(P$2,'PORTIFÓLIO'!$J$3:$Q$3,0))) * N('PORTIFÓLIO'!$S$4:$S$564), 0 ) ), 0)} -> 0 | Q66: =P66/$P$4 -> 0 | R66: =SUM(P66,N66,L66,J66,H66,D66,B66) -> 0 | S66: =R66/$R$4 -> 0
A67: =IFERROR(__xludf.DUMMYFUNCTION("""COMPUTED_VALUE"""),"AURORA 400 EC") -> AURORA 400 EC | B67: {=IFERROR( SUM( IF( 'PORTIFÓLIO'!$C$4:$C$564=$A67, N(INDEX('PORTIFÓLIO'!$J$4:$Q$564,,MATCH(B$2,'PORTIFÓLIO'!$J$3:$Q$3,0))) * N('PORTIFÓLIO'!$S$4:$S$564), 0 ) ), 0)} -> 0 | C67: =B67/$B$4 -> 0 | D67: {=IFERROR( SUM( IF( 'PORTIFÓLIO'!$C$4:$C$564=$A67, N(INDEX('PORTIFÓLIO'!$J$4:$Q$564,,MATCH(D$2,'PORTIFÓLIO'!$J$3:$Q$3,0))) * N('PORTIFÓLIO'!$S$4:$S$564), 0 ) ), 0)} -> 0 | E67: =D67/$D$4 -> 0 | F67: {=IFERROR( SUM( IF( 'PORTIFÓLIO'!$C$4:$C$564=$A67, N(INDEX('PORTIFÓLIO'!$J$4:$Q$564,,MATCH(F$2,'PORTIFÓLIO'!$J$3:$Q$3,0))) * N('PORTIFÓLIO'!$S$4:$S$564), 0 ) ), 0)} -> 0 | G67: =F67/$F$4 -> 0 | H67: {=IFERROR( SUM( IF( 'PORTIFÓLIO'!$C$4:$C$564=$A67, N(INDEX('PORTIFÓLIO'!$J$4:$Q$564,,MATCH(H$2,'PORTIFÓLIO'!$J$3:$Q$3,0))) * N('PORTIFÓLIO'!$S$4:$S$564), 0 ) ), 0)} -> 0 | I67: =H67/$H$4 -> 0 | J67: {=IFERROR( SUM( IF( 'PORTIFÓLIO'!$C$4:$C$564=$A67, N(INDEX('PORTIFÓLIO'!$J$4:$Q$564,,MATCH(J$2,'PORTIFÓLIO'!$J$3:$Q$3,0))) * N('PORTIFÓLIO'!$S$4:$S$564), 0 ) ), 0)} -> 0 | K67: =J67/$J$4 -> 0 | L67: {=IFERROR( SUM( IF( 'PORTIFÓLIO'!$C$4:$C$564=$A67, N(INDEX('PORTIFÓLIO'!$J$4:$Q$564,,MATCH(L$2,'PORTIFÓLIO'!$J$3:$Q$3,0))) * N('PORTIFÓLIO'!$S$4:$S$564), 0 ) ), 0)} -> 0 | M67: =L67/$L$4 -> 0 | N67: {=IFERROR( SUM( IF( 'PORTIFÓLIO'!$C$4:$C$564=$A67, N(INDEX('PORTIFÓLIO'!$J$4:$Q$564,,MATCH(N$2,'PORTIFÓLIO'!$J$3:$Q$3,0))) * N('PORTIFÓLIO'!$S$4:$S$564), 0 ) ), 0)} -> 0 | O67: =N67/$N$4 -> 0 | P67: {=IFERROR( SUM( IF( 'PORTIFÓLIO'!$C$4:$C$564=$A67, N(INDEX('PORTIFÓLIO'!$J$4:$Q$564,,MATCH(P$2,'PORTIFÓLIO'!$J$3:$Q$3,0))) * N('PORTIFÓLIO'!$S$4:$S$564), 0 ) ), 0)} -> 0 | Q67: =P67/$P$4 -> 0 | R67: =SUM(P67,N67,L67,J67,H67,D67,B67) -> 0 | S67: =R67/$R$4 -> 0
A68: =IFERROR(__xludf.DUMMYFUNCTION("""COMPUTED_VALUE"""),"AZUGRO") -> AZUGRO | B68: {=IFERROR( SUM( IF( 'PORTIFÓLIO'!$C$4:$C$564=$A68, N(INDEX('PORTIFÓLIO'!$J$4:$Q$564,,MATCH(B$2,'PORTIFÓLIO'!$J$3:$Q$3,0))) * N('PORTIFÓLIO'!$S$4:$S$564), 0 ) ), 0)} -> 0 | C68: =B68/$B$4 -> 0 | D68: {=IFERROR( SUM( IF( 'PORTIFÓLIO'!$C$4:$C$564=$A68, N(INDEX('PORTIFÓLIO'!$J$4:$Q$564,,MATCH(D$2,'PORTIFÓLIO'!$J$3:$Q$3,0))) * N('PORTIFÓLIO'!$S$4:$S$564), 0 ) ), 0)} -> 0 | E68: =D68/$D$4 -> 0 | F68: {=IFERROR( SUM( IF( 'PORTIFÓLIO'!$C$4:$C$564=$A68, N(INDEX('PORTIFÓLIO'!$J$4:$Q$564,,MATCH(F$2,'PORTIFÓLIO'!$J$3:$Q$3,0))) * N('PORTIFÓLIO'!$S$4:$S$564), 0 ) ), 0)} -> 0 | G68: =F68/$F$4 -> 0 | H68: {=IFERROR( SUM( IF( 'PORTIFÓLIO'!$C$4:$C$564=$A68, N(INDEX('PORTIFÓLIO'!$J$4:$Q$564,,MATCH(H$2,'PORTIFÓLIO'!$J$3:$Q$3,0))) * N('PORTIFÓLIO'!$S$4:$S$564), 0 ) ), 0)} -> 0 | I68: =H68/$H$4 -> 0 | J68: {=IFERROR( SUM( IF( 'PORTIFÓLIO'!$C$4:$C$564=$A68, N(INDEX('PORTIFÓLIO'!$J$4:$Q$564,,MATCH(J$2,'PORTIFÓLIO'!$J$3:$Q$3,0))) * N('PORTIFÓLIO'!$S$4:$S$564), 0 ) ), 0)} -> 0 | K68: =J68/$J$4 -> 0 | L68: {=IFERROR( SUM( IF( 'PORTIFÓLIO'!$C$4:$C$564=$A68, N(INDEX('PORTIFÓLIO'!$J$4:$Q$564,,MATCH(L$2,'PORTIFÓLIO'!$J$3:$Q$3,0))) * N('PORTIFÓLIO'!$S$4:$S$564), 0 ) ), 0)} -> 0 | M68: =L68/$L$4 -> 0 | N68: {=IFERROR( SUM( IF( 'PORTIFÓLIO'!$C$4:$C$564=$A68, N(INDEX('PORTIFÓLIO'!$J$4:$Q$564,,MATCH(N$2,'PORTIFÓLIO'!$J$3:$Q$3,0))) * N('PORTIFÓLIO'!$S$4:$S$564), 0 ) ), 0)} -> 0 | O68: =N68/$N$4 -> 0 | P68: {=IFERROR( SUM( IF( 'PORTIFÓLIO'!$C$4:$C$564=$A68, N(INDEX('PORTIFÓLIO'!$J$4:$Q$564,,MATCH(P$2,'PORTIFÓLIO'!$J$3:$Q$3,0))) * N('PORTIFÓLIO'!$S$4:$S$564), 0 ) ), 0)} -> 0 | Q68: =P68/$P$4 -> 0 | R68: =SUM(P68,N68,L68,J68,H68,D68,B68) -> 0 | S68: =R68/$R$4 -> 0
A69: =IFERROR(__xludf.DUMMYFUNCTION("""COMPUTED_VALUE"""),"BORAL") -> BORAL | B69: {=IFERROR( SUM( IF( 'PORTIFÓLIO'!$C$4:$C$564=$A69, N(INDEX('PORTIFÓLIO'!$J$4:$Q$564,,MATCH(B$2,'PORTIFÓLIO'!$J$3:$Q$3,0))) * N('PORTIFÓLIO'!$S$4:$S$564), 0 ) ), 0)} -> 0 | C69: =B69/$B$4 -> 0 | D69: {=IFERROR( SUM( IF( 'PORTIFÓLIO'!$C$4:$C$564=$A69, N(INDEX('PORTIFÓLIO'!$J$4:$Q$564,,MATCH(D$2,'PORTIFÓLIO'!$J$3:$Q$3,0))) * N('PORTIFÓLIO'!$S$4:$S$564), 0 ) ), 0)} -> 0 | E69: =D69/$D$4 -> 0 | F69: {=IFERROR( SUM( IF( 'PORTIFÓLIO'!$C$4:$C$564=$A69, N(INDEX('PORTIFÓLIO'!$J$4:$Q$564,,MATCH(F$2,'PORTIFÓLIO'!$J$3:$Q$3,0))) * N('PORTIFÓLIO'!$S$4:$S$564), 0 ) ), 0)} -> 0 | G69: =F69/$F$4 -> 0 | H69: {=IFERROR( SUM( IF( 'PORTIFÓLIO'!$C$4:$C$564=$A69, N(INDEX('PORTIFÓLIO'!$J$4:$Q$564,,MATCH(H$2,'PORTIFÓLIO'!$J$3:$Q$3,0))) * N('PORTIFÓLIO'!$S$4:$S$564), 0 ) ), 0)} -> 0 | I69: =H69/$H$4 -> 0 | J69: {=IFERROR( SUM( IF( 'PORTIFÓLIO'!$C$4:$C$564=$A69, N(INDEX('PORTIFÓLIO'!$J$4:$Q$564,,MATCH(J$2,'PORTIFÓLIO'!$J$3:$Q$3,0))) * N('PORTIFÓLIO'!$S$4:$S$564), 0 ) ), 0)} -> 0 | K69: =J69/$J$4 -> 0 | L69: {=IFERROR( SUM( IF( 'PORTIFÓLIO'!$C$4:$C$564=$A69, N(INDEX('PORTIFÓLIO'!$J$4:$Q$564,,MATCH(L$2,'PORTIFÓLIO'!$J$3:$Q$3,0))) * N('PORTIFÓLIO'!$S$4:$S$564), 0 ) ), 0)} -> 0 | M69: =L69/$L$4 -> 0 | N69: {=IFERROR( SUM( IF( 'PORTIFÓLIO'!$C$4:$C$564=$A69, N(INDEX('PORTIFÓLIO'!$J$4:$Q$564,,MATCH(N$2,'PORTIFÓLIO'!$J$3:$Q$3,0))) * N('PORTIFÓLIO'!$S$4:$S$564), 0 ) ), 0)} -> 0 | O69: =N69/$N$4 -> 0 | P69: {=IFERROR( SUM( IF( 'PORTIFÓLIO'!$C$4:$C$564=$A69, N(INDEX('PORTIFÓLIO'!$J$4:$Q$564,,MATCH(P$2,'PORTIFÓLIO'!$J$3:$Q$3,0))) * N('PORTIFÓLIO'!$S$4:$S$564), 0 ) ), 0)} -> 0 | Q69: =P69/$P$4 -> 0 | R69: =SUM(P69,N69,L69,J69,H69,D69,B69) -> 0 | S69: =R69/$R$4 -> 0
A70: =IFERROR(__xludf.DUMMYFUNCTION("""COMPUTED_VALUE"""),"REATOR 360 CS") -> REATOR 360 CS | B70: {=IFERROR( SUM( IF( 'PORTIFÓLIO'!$C$4:$C$564=$A70, N(INDEX('PORTIFÓLIO'!$J$4:$Q$564,,MATCH(B$2,'PORTIFÓLIO'!$J$3:$Q$3,0))) * N('PORTIFÓLIO'!$S$4:$S$564), 0 ) ), 0)} -> 0 | C70: =B70/$B$4 -> 0 | D70: {=IFERROR( SUM( IF( 'PORTIFÓLIO'!$C$4:$C$564=$A70, N(INDEX('PORTIFÓLIO'!$J$4:$Q$564,,MATCH(D$2,'PORTIFÓLIO'!$J$3:$Q$3,0))) * N('PORTIFÓLIO'!$S$4:$S$564), 0 ) ), 0)} -> 0 | E70: =D70/$D$4 -> 0 | F70: {=IFERROR( SUM( IF( 'PORTIFÓLIO'!$C$4:$C$564=$A70, N(INDEX('PORTIFÓLIO'!$J$4:$Q$564,,MATCH(F$2,'PORTIFÓLIO'!$J$3:$Q$3,0))) * N('PORTIFÓLIO'!$S$4:$S$564), 0 ) ), 0)} -> 9636.3432 | G70: =F70/$F$4 -> 43.80156 | H70: {=IFERROR( SUM( IF( 'PORTIFÓLIO'!$C$4:$C$564=$A70, N(INDEX('PORTIFÓLIO'!$J$4:$Q$564,,MATCH(H$2,'PORTIFÓLIO'!$J$3:$Q$3,0))) * N('PORTIFÓLIO'!$S$4:$S$564), 0 ) ), 0)} -> 0 | I70: =H70/$H$4 -> 0 | J70: {=IFERROR( SUM( IF( 'PORTIFÓLIO'!$C$4:$C$564=$A70, N(INDEX('PORTIFÓLIO'!$J$4:$Q$564,,MATCH(J$2,'PORTIFÓLIO'!$J$3:$Q$3,0))) * N('PORTIFÓLIO'!$S$4:$S$564), 0 ) ), 0)} -> 0 | K70: =J70/$J$4 -> 0 | L70: {=IFERROR( SUM( IF( 'PORTIFÓLIO'!$C$4:$C$564=$A70, N(INDEX('PORTIFÓLIO'!$J$4:$Q$564,,MATCH(L$2,'PORTIFÓLIO'!$J$3:$Q$3,0))) * N('PORTIFÓLIO'!$S$4:$S$564), 0 ) ), 0)} -> 0 | M70: =L70/$L$4 -> 0 | N70: {=IFERROR( SUM( IF( 'PORTIFÓLIO'!$C$4:$C$564=$A70, N(INDEX('PORTIFÓLIO'!$J$4:$Q$564,,MATCH(N$2,'PORTIFÓLIO'!$J$3:$Q$3,0))) * N('PORTIFÓLIO'!$S$4:$S$564), 0 ) ), 0)} -> 41961.894 | O70: =N70/$N$4 -> 34.451473 | P70: {=IFERROR( SUM( IF( 'PORTIFÓLIO'!$C$4:$C$564=$A70, N(INDEX('PORTIFÓLIO'!$J$4:$Q$564,,MATCH(P$2,'PORTIFÓLIO'!$J$3:$Q$3,0))) * N('PORTIFÓLIO'!$S$4:$S$564), 0 ) ), 0)} -> 14016.499 | Q70: =P70/$P$4 -> 43.80156 | R70: =SUM(P70,N70,L70,J70,H70,D70,B70) -> 55978.394 | S70: =R70/$R$4 -> 16.73995
A71: =IFERROR(__xludf.DUMMYFUNCTION("""COMPUTED_VALUE"""),"STONE") -> STONE | B71: {=IFERROR( SUM( IF( 'PORTIFÓLIO'!$C$4:$C$564=$A71, N(INDEX('PORTIFÓLIO'!$J$4:$Q$564,,MATCH(B$2,'PORTIFÓLIO'!$J$3:$Q$3,0))) * N('PORTIFÓLIO'!$S$4:$S$564), 0 ) ), 0)} -> 0 | C71: =B71/$B$4 -> 0 | D71: {=IFERROR( SUM( IF( 'PORTIFÓLIO'!$C$4:$C$564=$A71, N(INDEX('PORTIFÓLIO'!$J$4:$Q$564,,MATCH(D$2,'PORTIFÓLIO'!$J$3:$Q$3,0))) * N('PORTIFÓLIO'!$S$4:$S$564), 0 ) ), 0)} -> 20433.354 | E71: =D71/$D$4 -> 68.11118 | F71: {=IFERROR( SUM( IF( 'PORTIFÓLIO'!$C$4:$C$564=$A71, N(INDEX('PORTIFÓLIO'!$J$4:$Q$564,,MATCH(F$2,'PORTIFÓLIO'!$J$3:$Q$3,0))) * N('PORTIFÓLIO'!$S$4:$S$564), 0 ) ), 0)} -> 0 | G71: =F71/$F$4 -> 0 | H71: {=IFERROR( SUM( IF( 'PORTIFÓLIO'!$C$4:$C$564=$A71, N(INDEX('PORTIFÓLIO'!$J$4:$Q$564,,MATCH(H$2,'PORTIFÓLIO'!$J$3:$Q$3,0))) * N('PORTIFÓLIO'!$S$4:$S$564), 0 ) ), 0)} -> 0 | I71: =H71/$H$4 -> 0 | J71: {=IFERROR( SUM( IF( 'PORTIFÓLIO'!$C$4:$C$564=$A71, N(INDEX('PORTIFÓLIO'!$J$4:$Q$564,,MATCH(J$2,'PORTIFÓLIO'!$J$3:$Q$3,0))) * N('PORTIFÓLIO'!$S$4:$S$564), 0 ) ), 0)} -> 0 | K71: =J71/$J$4 -> 0 | L71: {=IFERROR( SUM( IF( 'PORTIFÓLIO'!$C$4:$C$564=$A71, N(INDEX('PORTIFÓLIO'!$J$4:$Q$564,,MATCH(L$2,'PORTIFÓLIO'!$J$3:$Q$3,0))) * N('PORTIFÓLIO'!$S$4:$S$564), 0 ) ), 0)} -> 0 | M71: =L71/$L$4 -> 0 | N71: {=IFERROR( SUM( IF( 'PORTIFÓLIO'!$C$4:$C$564=$A71, N(INDEX('PORTIFÓLIO'!$J$4:$Q$564,,MATCH(N$2,'PORTIFÓLIO'!$J$3:$Q$3,0))) * N('PORTIFÓLIO'!$S$4:$S$564), 0 ) ), 0)} -> 0 | O71: =N71/$N$4 -> 0 | P71: {=IFERROR( SUM( IF( 'PORTIFÓLIO'!$C$4:$C$564=$A71, N(INDEX('PORTIFÓLIO'!$J$4:$Q$564,,MATCH(P$2,'PORTIFÓLIO'!$J$3:$Q$3,0))) * N('PORTIFÓLIO'!$S$4:$S$564), 0 ) ), 0)} -> 0 | Q71: =P71/$P$4 -> 0 | R71: =SUM(P71,N71,L71,J71,H71,D71,B71) -> 20433.354 | S71: =R71/$R$4 -> 6.1104528
A72: =IFERROR(__xludf.DUMMYFUNCTION("""COMPUTED_VALUE"""),"ARKEIRO NORTOX") -> ARKEIRO NORTOX | B72: {=IFERROR( SUM( IF( 'PORTIFÓLIO'!$C$4:$C$564=$A72, N(INDEX('PORTIFÓLIO'!$J$4:$Q$564,,MATCH(B$2,'PORTIFÓLIO'!$J$3:$Q$3,0))) * N('PORTIFÓLIO'!$S$4:$S$564), 0 ) ), 0)} -> 0 | C72: =B72/$B$4 -> 0 | D72: {=IFERROR( SUM( IF( 'PORTIFÓLIO'!$C$4:$C$564=$A72, N(INDEX('PORTIFÓLIO'!$J$4:$Q$564,,MATCH(D$2,'PORTIFÓLIO'!$J$3:$Q$3,0))) * N('PORTIFÓLIO'!$S$4:$S$564), 0 ) ), 0)} -> 0 | E72: =D72/$D$4 -> 0 | F72: {=IFERROR( SUM( IF( 'PORTIFÓLIO'!$C$4:$C$564=$A72, N(INDEX('PORTIFÓLIO'!$J$4:$Q$564,,MATCH(F$2,'PORTIFÓLIO'!$J$3:$Q$3,0))) * N('PORTIFÓLIO'!$S$4:$S$564), 0 ) ), 0)} -> 0 | G72: =F72/$F$4 -> 0 | H72: {=IFERROR( SUM( IF( 'PORTIFÓLIO'!$C$4:$C$564=$A72, N(INDEX('PORTIFÓLIO'!$J$4:$Q$564,,MATCH(H$2,'PORTIFÓLIO'!$J$3:$Q$3,0))) * N('PORTIFÓLIO'!$S$4:$S$564), 0 ) ), 0)} -> 0 | I72: =H72/$H$4 -> 0 | J72: {=IFERROR( SUM( IF( 'PORTIFÓLIO'!$C$4:$C$564=$A72, N(INDEX('PORTIFÓLIO'!$J$4:$Q$564,,MATCH(J$2,'PORTIFÓLIO'!$J$3:$Q$3,0))) * N('PORTIFÓLIO'!$S$4:$S$564), 0 ) ), 0)} -> 0 | K72: =J72/$J$4 -> 0 | L72: {=IFERROR( SUM( IF( 'PORTIFÓLIO'!$C$4:$C$564=$A72, N(INDEX('PORTIFÓLIO'!$J$4:$Q$564,,MATCH(L$2,'PORTIFÓLIO'!$J$3:$Q$3,0))) * N('PORTIFÓLIO'!$S$4:$S$564), 0 ) ), 0)} -> 0 | M72: =L72/$L$4 -> 0 | N72: {=IFERROR( SUM( IF( 'PORTIFÓLIO'!$C$4:$C$564=$A72, N(INDEX('PORTIFÓLIO'!$J$4:$Q$564,,MATCH(N$2,'PORTIFÓLIO'!$J$3:$Q$3,0))) * N('PORTIFÓLIO'!$S$4:$S$564), 0 ) ), 0)} -> 0 | O72: =N72/$N$4 -> 0 | P72: {=IFERROR( SUM( IF( 'PORTIFÓLIO'!$C$4:$C$564=$A72, N(INDEX('PORTIFÓLIO'!$J$4:$Q$564,,MATCH(P$2,'PORTIFÓLIO'!$J$3:$Q$3,0))) * N('PORTIFÓLIO'!$S$4:$S$564), 0 ) ), 0)} -> 0 | Q72: =P72/$P$4 -> 0 | R72: =SUM(P72,N72,L72,J72,H72,D72,B72) -> 0 | S72: =R72/$R$4 -> 0
A73: =IFERROR(__xludf.DUMMYFUNCTION("""COMPUTED_VALUE"""),"CLETODIM OLEUM NORTOX") -> CLETODIM OLEUM NORTOX | B73: {=IFERROR( SUM( IF( 'PORTIFÓLIO'!$C$4:$C$564=$A73, N(INDEX('PORTIFÓLIO'!$J$4:$Q$564,,MATCH(B$2,'PORTIFÓLIO'!$J$3:$Q$3,0))) * N('PORTIFÓLIO'!$S$4:$S$564), 0 ) ), 0)} -> 0 | C73: =B73/$B$4 -> 0 | D73: {=IFERROR( SUM( IF( 'PORTIFÓLIO'!$C$4:$C$564=$A73, N(INDEX('PORTIFÓLIO'!$J$4:$Q$564,,MATCH(D$2,'PORTIFÓLIO'!$J$3:$Q$3,0))) * N('PORTIFÓLIO'!$S$4:$S$564), 0 ) ), 0)} -> 0 | E73: =D73/$D$4 -> 0 | F73: {=IFERROR( SUM( IF( 'PORTIFÓLIO'!$C$4:$C$564=$A73, N(INDEX('PORTIFÓLIO'!$J$4:$Q$564,,MATCH(F$2,'PORTIFÓLIO'!$J$3:$Q$3,0))) * N('PORTIFÓLIO'!$S$4:$S$564), 0 ) ), 0)} -> 0 | G73: =F73/$F$4 -> 0 | H73: {=IFERROR( SUM( IF( 'PORTIFÓLIO'!$C$4:$C$564=$A73, N(INDEX('PORTIFÓLIO'!$J$4:$Q$564,,MATCH(H$2,'PORTIFÓLIO'!$J$3:$Q$3,0))) * N('PORTIFÓLIO'!$S$4:$S$564), 0 ) ), 0)} -> 0 | I73: =H73/$H$4 -> 0 | J73: {=IFERROR( SUM( IF( 'PORTIFÓLIO'!$C$4:$C$564=$A73, N(INDEX('PORTIFÓLIO'!$J$4:$Q$564,,MATCH(J$2,'PORTIFÓLIO'!$J$3:$Q$3,0))) * N('PORTIFÓLIO'!$S$4:$S$564), 0 ) ), 0)} -> 0 | K73: =J73/$J$4 -> 0 | L73: {=IFERROR( SUM( IF( 'PORTIFÓLIO'!$C$4:$C$564=$A73, N(INDEX('PORTIFÓLIO'!$J$4:$Q$564,,MATCH(L$2,'PORTIFÓLIO'!$J$3:$Q$3,0))) * N('PORTIFÓLIO'!$S$4:$S$564), 0 ) ), 0)} -> 0 | M73: =L73/$L$4 -> 0 | N73: {=IFERROR( SUM( IF( 'PORTIFÓLIO'!$C$4:$C$564=$A73, N(INDEX('PORTIFÓLIO'!$J$4:$Q$564,,MATCH(N$2,'PORTIFÓLIO'!$J$3:$Q$3,0))) * N('PORTIFÓLIO'!$S$4:$S$564), 0 ) ), 0)} -> 0 | O73: =N73/$N$4 -> 0 | P73: {=IFERROR( SUM( IF( 'PORTIFÓLIO'!$C$4:$C$564=$A73, N(INDEX('PORTIFÓLIO'!$J$4:$Q$564,,MATCH(P$2,'PORTIFÓLIO'!$J$3:$Q$3,0))) * N('PORTIFÓLIO'!$S$4:$S$564), 0 ) ), 0)} -> 0 | Q73: =P73/$P$4 -> 0 | R73: =SUM(P73,N73,L73,J73,H73,D73,B73) -> 0 | S73: =R73/$R$4 -> 0
A74: =IFERROR(__xludf.DUMMYFUNCTION("""COMPUTED_VALUE"""),"CLORIMUROM MAX NORTOX") -> CLORIMUROM MAX NORTOX | B74: {=IFERROR( SUM( IF( 'PORTIFÓLIO'!$C$4:$C$564=$A74, N(INDEX('PORTIFÓLIO'!$J$4:$Q$564,,MATCH(B$2,'PORTIFÓLIO'!$J$3:$Q$3,0))) * N('PORTIFÓLIO'!$S$4:$S$564), 0 ) ), 0)} -> 0 | C74: =B74/$B$4 -> 0 | D74: {=IFERROR( SUM( IF( 'PORTIFÓLIO'!$C$4:$C$564=$A74, N(INDEX('PORTIFÓLIO'!$J$4:$Q$564,,MATCH(D$2,'PORTIFÓLIO'!$J$3:$Q$3,0))) * N('PORTIFÓLIO'!$S$4:$S$564), 0 ) ), 0)} -> 0 | E74: =D74/$D$4 -> 0 | F74: {=IFERROR( SUM( IF( 'PORTIFÓLIO'!$C$4:$C$564=$A74, N(INDEX('PORTIFÓLIO'!$J$4:$Q$564,,MATCH(F$2,'PORTIFÓLIO'!$J$3:$Q$3,0))) * N('PORTIFÓLIO'!$S$4:$S$564), 0 ) ), 0)} -> 0 | G74: =F74/$F$4 -> 0 | H74: {=IFERROR( SUM( IF( 'PORTIFÓLIO'!$C$4:$C$564=$A74, N(INDEX('PORTIFÓLIO'!$J$4:$Q$564,,MATCH(H$2,'PORTIFÓLIO'!$J$3:$Q$3,0))) * N('PORTIFÓLIO'!$S$4:$S$564), 0 ) ), 0)} -> 0 | I74: =H74/$H$4 -> 0 | J74: {=IFERROR( SUM( IF( 'PORTIFÓLIO'!$C$4:$C$564=$A74, N(INDEX('PORTIFÓLIO'!$J$4:$Q$564,,MATCH(J$2,'PORTIFÓLIO'!$J$3:$Q$3,0))) * N('PORTIFÓLIO'!$S$4:$S$564), 0 ) ), 0)} -> 0 | K74: =J74/$J$4 -> 0 | L74: {=IFERROR( SUM( IF( 'PORTIFÓLIO'!$C$4:$C$564=$A74, N(INDEX('PORTIFÓLIO'!$J$4:$Q$564,,MATCH(L$2,'PORTIFÓLIO'!$J$3:$Q$3,0))) * N('PORTIFÓLIO'!$S$4:$S$564), 0 ) ), 0)} -> 0 | M74: =L74/$L$4 -> 0 | N74: {=IFERROR( SUM( IF( 'PORTIFÓLIO'!$C$4:$C$564=$A74, N(INDEX('PORTIFÓLIO'!$J$4:$Q$564,,MATCH(N$2,'PORTIFÓLIO'!$J$3:$Q$3,0))) * N('PORTIFÓLIO'!$S$4:$S$564), 0 ) ), 0)} -> 0 | O74: =N74/$N$4 -> 0 | P74: {=IFERROR( SUM( IF( 'PORTIFÓLIO'!$C$4:$C$564=$A74, N(INDEX('PORTIFÓLIO'!$J$4:$Q$564,,MATCH(P$2,'PORTIFÓLIO'!$J$3:$Q$3,0))) * N('PORTIFÓLIO'!$S$4:$S$564), 0 ) ), 0)} -> 0 | Q74: =P74/$P$4 -> 0 | R74: =SUM(P74,N74,L74,J74,H74,D74,B74) -> 0 | S74: =R74/$R$4 -> 0
A75: =IFERROR(__xludf.DUMMYFUNCTION("""COMPUTED_VALUE"""),"FLUROXIPIR NORTOX") -> FLUROXIPIR NORTOX | B75: {=IFERROR( SUM( IF( 'PORTIFÓLIO'!$C$4:$C$564=$A75, N(INDEX('PORTIFÓLIO'!$J$4:$Q$564,,MATCH(B$2,'PORTIFÓLIO'!$J$3:$Q$3,0))) * N('PORTIFÓLIO'!$S$4:$S$564), 0 ) ), 0)} -> 0 | C75: =B75/$B$4 -> 0 | D75: {=IFERROR( SUM( IF( 'PORTIFÓLIO'!$C$4:$C$564=$A75, N(INDEX('PORTIFÓLIO'!$J$4:$Q$564,,MATCH(D$2,'PORTIFÓLIO'!$J$3:$Q$3,0))) * N('PORTIFÓLIO'!$S$4:$S$564), 0 ) ), 0)} -> 0 | E75: =D75/$D$4 -> 0 | F75: {=IFERROR( SUM( IF( 'PORTIFÓLIO'!$C$4:$C$564=$A75, N(INDEX('PORTIFÓLIO'!$J$4:$Q$564,,MATCH(F$2,'PORTIFÓLIO'!$J$3:$Q$3,0))) * N('PORTIFÓLIO'!$S$4:$S$564), 0 ) ), 0)} -> 0 | G75: =F75/$F$4 -> 0 | H75: {=IFERROR( SUM( IF( 'PORTIFÓLIO'!$C$4:$C$564=$A75, N(INDEX('PORTIFÓLIO'!$J$4:$Q$564,,MATCH(H$2,'PORTIFÓLIO'!$J$3:$Q$3,0))) * N('PORTIFÓLIO'!$S$4:$S$564), 0 ) ), 0)} -> 0 | I75: =H75/$H$4 -> 0 | J75: {=IFERROR( SUM( IF( 'PORTIFÓLIO'!$C$4:$C$564=$A75, N(INDEX('PORTIFÓLIO'!$J$4:$Q$564,,MATCH(J$2,'PORTIFÓLIO'!$J$3:$Q$3,0))) * N('PORTIFÓLIO'!$S$4:$S$564), 0 ) ), 0)} -> 0 | K75: =J75/$J$4 -> 0 | L75: {=IFERROR( SUM( IF( 'PORTIFÓLIO'!$C$4:$C$564=$A75, N(INDEX('PORTIFÓLIO'!$J$4:$Q$564,,MATCH(L$2,'PORTIFÓLIO'!$J$3:$Q$3,0))) * N('PORTIFÓLIO'!$S$4:$S$564), 0 ) ), 0)} -> 0 | M75: =L75/$L$4 -> 0 | N75: {=IFERROR( SUM( IF( 'PORTIFÓLIO'!$C$4:$C$564=$A75, N(INDEX('PORTIFÓLIO'!$J$4:$Q$564,,MATCH(N$2,'PORTIFÓLIO'!$J$3:$Q$3,0))) * N('PORTIFÓLIO'!$S$4:$S$564), 0 ) ), 0)} -> 0 | O75: =N75/$N$4 -> 0 | P75: {=IFERROR( SUM( IF( 'PORTIFÓLIO'!$C$4:$C$564=$A75, N(INDEX('PORTIFÓLIO'!$J$4:$Q$564,,MATCH(P$2,'PORTIFÓLIO'!$J$3:$Q$3,0))) * N('PORTIFÓLIO'!$S$4:$S$564), 0 ) ), 0)} -> 0 | Q75: =P75/$P$4 -> 0 | R75: =SUM(P75,N75,L75,J75,H75,D75,B75) -> 0 | S75: =R75/$R$4 -> 0
A76: =IFERROR(__xludf.DUMMYFUNCTION("""COMPUTED_VALUE"""),"GLUFOSINATO NORTOX 880 SG") -> GLUFOSINATO NORTOX 880 SG | B76: {=IFERROR( SUM( IF( 'PORTIFÓLIO'!$C$4:$C$564=$A76, N(INDEX('PORTIFÓLIO'!$J$4:$Q$564,,MATCH(B$2,'PORTIFÓLIO'!$J$3:$Q$3,0))) * N('PORTIFÓLIO'!$S$4:$S$564), 0 ) ), 0)} -> 0 | C76: =B76/$B$4 -> 0 | D76: {=IFERROR( SUM( IF( 'PORTIFÓLIO'!$C$4:$C$564=$A76, N(INDEX('PORTIFÓLIO'!$J$4:$Q$564,,MATCH(D$2,'PORTIFÓLIO'!$J$3:$Q$3,0))) * N('PORTIFÓLIO'!$S$4:$S$564), 0 ) ), 0)} -> 3289.7872 | E76: =D76/$D$4 -> 10.965957 | F76: {=IFERROR( SUM( IF( 'PORTIFÓLIO'!$C$4:$C$564=$A76, N(INDEX('PORTIFÓLIO'!$J$4:$Q$564,,MATCH(F$2,'PORTIFÓLIO'!$J$3:$Q$3,0))) * N('PORTIFÓLIO'!$S$4:$S$564), 0 ) ), 0)} -> 0 | G76: =F76/$F$4 -> 0 | H76: {=IFERROR( SUM( IF( 'PORTIFÓLIO'!$C$4:$C$564=$A76, N(INDEX('PORTIFÓLIO'!$J$4:$Q$564,,MATCH(H$2,'PORTIFÓLIO'!$J$3:$Q$3,0))) * N('PORTIFÓLIO'!$S$4:$S$564), 0 ) ), 0)} -> 7519.5136 | I76: =H76/$H$4 -> 37.597568 | J76: {=IFERROR( SUM( IF( 'PORTIFÓLIO'!$C$4:$C$564=$A76, N(INDEX('PORTIFÓLIO'!$J$4:$Q$564,,MATCH(J$2,'PORTIFÓLIO'!$J$3:$Q$3,0))) * N('PORTIFÓLIO'!$S$4:$S$564), 0 ) ), 0)} -> 0 | K76: =J76/$J$4 -> 0 | L76: {=IFERROR( SUM( IF( 'PORTIFÓLIO'!$C$4:$C$564=$A76, N(INDEX('PORTIFÓLIO'!$J$4:$Q$564,,MATCH(L$2,'PORTIFÓLIO'!$J$3:$Q$3,0))) * N('PORTIFÓLIO'!$S$4:$S$564), 0 ) ), 0)} -> 0 | M76: =L76/$L$4 -> 0 | N76: {=IFERROR( SUM( IF( 'PORTIFÓLIO'!$C$4:$C$564=$A76, N(INDEX('PORTIFÓLIO'!$J$4:$Q$564,,MATCH(N$2,'PORTIFÓLIO'!$J$3:$Q$3,0))) * N('PORTIFÓLIO'!$S$4:$S$564), 0 ) ), 0)} -> 17623.86 | O76: =N76/$N$4 -> 14.469507 | P76: {=IFERROR( SUM( IF( 'PORTIFÓLIO'!$C$4:$C$564=$A76, N(INDEX('PORTIFÓLIO'!$J$4:$Q$564,,MATCH(P$2,'PORTIFÓLIO'!$J$3:$Q$3,0))) * N('PORTIFÓLIO'!$S$4:$S$564), 0 ) ), 0)} -> 2819.8176 | Q76: =P76/$P$4 -> 8.81193 | R76: =SUM(P76,N76,L76,J76,H76,D76,B76) -> 31252.978 | S76: =R76/$R$4 -> 9.3459864
A77: =IFERROR(__xludf.DUMMYFUNCTION("""COMPUTED_VALUE"""),"IMAZETAPIR NORTOX") -> IMAZETAPIR NORTOX | B77: {=IFERROR( SUM( IF( 'PORTIFÓLIO'!$C$4:$C$564=$A77, N(INDEX('PORTIFÓLIO'!$J$4:$Q$564,,MATCH(B$2,'PORTIFÓLIO'!$J$3:$Q$3,0))) * N('PORTIFÓLIO'!$S$4:$S$564), 0 ) ), 0)} -> 20270.389 | C77: =B77/$B$4 -> 41.36814 | D77: {=IFERROR( SUM( IF( 'PORTIFÓLIO'!$C$4:$C$564=$A77, N(INDEX('PORTIFÓLIO'!$J$4:$Q$564,,MATCH(D$2,'PORTIFÓLIO'!$J$3:$Q$3,0))) * N('PORTIFÓLIO'!$S$4:$S$564), 0 ) ), 0)} -> 0 | E77: =D77/$D$4 -> 0 | F77: {=IFERROR( SUM( IF( 'PORTIFÓLIO'!$C$4:$C$564=$A77, N(INDEX('PORTIFÓLIO'!$J$4:$Q$564,,MATCH(F$2,'PORTIFÓLIO'!$J$3:$Q$3,0))) * N('PORTIFÓLIO'!$S$4:$S$564), 0 ) ), 0)} -> 0 | G77: =F77/$F$4 -> 0 | H77: {=IFERROR( SUM( IF( 'PORTIFÓLIO'!$C$4:$C$564=$A77, N(INDEX('PORTIFÓLIO'!$J$4:$Q$564,,MATCH(H$2,'PORTIFÓLIO'!$J$3:$Q$3,0))) * N('PORTIFÓLIO'!$S$4:$S$564), 0 ) ), 0)} -> 0 | I77: =H77/$H$4 -> 0 | J77: {=IFERROR( SUM( IF( 'PORTIFÓLIO'!$C$4:$C$564=$A77, N(INDEX('PORTIFÓLIO'!$J$4:$Q$564,,MATCH(J$2,'PORTIFÓLIO'!$J$3:$Q$3,0))) * N('PORTIFÓLIO'!$S$4:$S$564), 0 ) ), 0)} -> 0 | K77: =J77/$J$4 -> 0 | L77: {=IFERROR( SUM( IF( 'PORTIFÓLIO'!$C$4:$C$564=$A77, N(INDEX('PORTIFÓLIO'!$J$4:$Q$564,,MATCH(L$2,'PORTIFÓLIO'!$J$3:$Q$3,0))) * N('PORTIFÓLIO'!$S$4:$S$564), 0 ) ), 0)} -> 0 | M77: =L77/$L$4 -> 0 | N77: {=IFERROR( SUM( IF( 'PORTIFÓLIO'!$C$4:$C$564=$A77, N(INDEX('PORTIFÓLIO'!$J$4:$Q$564,,MATCH(N$2,'PORTIFÓLIO'!$J$3:$Q$3,0))) * N('PORTIFÓLIO'!$S$4:$S$564), 0 ) ), 0)} -> 0 | O77: =N77/$N$4 -> 0 | P77: {=IFERROR( SUM( IF( 'PORTIFÓLIO'!$C$4:$C$564=$A77, N(INDEX('PORTIFÓLIO'!$J$4:$Q$564,,MATCH(P$2,'PORTIFÓLIO'!$J$3:$Q$3,0))) * N('PORTIFÓLIO'!$S$4:$S$564), 0 ) ), 0)} -> 0 | Q77: =P77/$P$4 -> 0 | R77: =SUM(P77,N77,L77,J77,H77,D77,B77) -> 20270.389 | S77: =R77/$R$4 -> 6.0617191
A78: =IFERROR(__xludf.DUMMYFUNCTION("""COMPUTED_VALUE"""),"MESOTRIONA NORTOX") -> MESOTRIONA NORTOX | B78: {=IFERROR( SUM( IF( 'PORTIFÓLIO'!$C$4:$C$564=$A78, N(INDEX('PORTIFÓLIO'!$J$4:$Q$564,,MATCH(B$2,'PORTIFÓLIO'!$J$3:$Q$3,0))) * N('PORTIFÓLIO'!$S$4:$S$564), 0 ) ), 0)} -> 0 | C78: =B78/$B$4 -> 0 | D78: {=IFERROR( SUM( IF( 'PORTIFÓLIO'!$C$4:$C$564=$A78, N(INDEX('PORTIFÓLIO'!$J$4:$Q$564,,MATCH(D$2,'PORTIFÓLIO'!$J$3:$Q$3,0))) * N('PORTIFÓLIO'!$S$4:$S$564), 0 ) ), 0)} -> 0 | E78: =D78/$D$4 -> 0 | F78: {=IFERROR( SUM( IF( 'PORTIFÓLIO'!$C$4:$C$564=$A78, N(INDEX('PORTIFÓLIO'!$J$4:$Q$564,,MATCH(F$2,'PORTIFÓLIO'!$J$3:$Q$3,0))) * N('PORTIFÓLIO'!$S$4:$S$564), 0 ) ), 0)} -> 0 | G78: =F78/$F$4 -> 0 | H78: {=IFERROR( SUM( IF( 'PORTIFÓLIO'!$C$4:$C$564=$A78, N(INDEX('PORTIFÓLIO'!$J$4:$Q$564,,MATCH(H$2,'PORTIFÓLIO'!$J$3:$Q$3,0))) * N('PORTIFÓLIO'!$S$4:$S$564), 0 ) ), 0)} -> 0 | I78: =H78/$H$4 -> 0 | J78: {=IFERROR( SUM( IF( 'PORTIFÓLIO'!$C$4:$C$564=$A78, N(INDEX('PORTIFÓLIO'!$J$4:$Q$564,,MATCH(J$2,'PORTIFÓLIO'!$J$3:$Q$3,0))) * N('PORTIFÓLIO'!$S$4:$S$564), 0 ) ), 0)} -> 0 | K78: =J78/$J$4 -> 0 | L78: {=IFERROR( SUM( IF( 'PORTIFÓLIO'!$C$4:$C$564=$A78, N(INDEX('PORTIFÓLIO'!$J$4:$Q$564,,MATCH(L$2,'PORTIFÓLIO'!$J$3:$Q$3,0))) * N('PORTIFÓLIO'!$S$4:$S$564), 0 ) ), 0)} -> 0 | M78: =L78/$L$4 -> 0 | N78: {=IFERROR( SUM( IF( 'PORTIFÓLIO'!$C$4:$C$564=$A78, N(INDEX('PORTIFÓLIO'!$J$4:$Q$564,,MATCH(N$2,'PORTIFÓLIO'!$J$3:$Q$3,0))) * N('PORTIFÓLIO'!$S$4:$S$564), 0 ) ), 0)} -> 0 | O78: =N78/$N$4 -> 0 | P78: {=IFERROR( SUM( IF( 'PORTIFÓLIO'!$C$4:$C$564=$A78, N(INDEX('PORTIFÓLIO'!$J$4:$Q$564,,MATCH(P$2,'PORTIFÓLIO'!$J$3:$Q$3,0))) * N('PORTIFÓLIO'!$S$4:$S$564), 0 ) ), 0)} -> 0 | Q78: =P78/$P$4 -> 0 | R78: =SUM(P78,N78,L78,J78,H78,D78,B78) -> 0 | S78: =R78/$R$4 -> 0
A79: =IFERROR(__xludf.DUMMYFUNCTION("""COMPUTED_VALUE"""),"TRIFLURALINA NORTOX GOLD") -> TRIFLURALINA NORTOX GOLD | B79: {=IFERROR( SUM( IF( 'PORTIFÓLIO'!$C$4:$C$564=$A79, N(INDEX('PORTIFÓLIO'!$J$4:$Q$564,,MATCH(B$2,'PORTIFÓLIO'!$J$3:$Q$3,0))) * N('PORTIFÓLIO'!$S$4:$S$564), 0 ) ), 0)} -> 0 | C79: =B79/$B$4 -> 0 | D79: {=IFERROR( SUM( IF( 'PORTIFÓLIO'!$C$4:$C$564=$A79, N(INDEX('PORTIFÓLIO'!$J$4:$Q$564,,MATCH(D$2,'PORTIFÓLIO'!$J$3:$Q$3,0))) * N('PORTIFÓLIO'!$S$4:$S$564), 0 ) ), 0)} -> 0 | E79: =D79/$D$4 -> 0 | F79: {=IFERROR( SUM( IF( 'PORTIFÓLIO'!$C$4:$C$564=$A79, N(INDEX('PORTIFÓLIO'!$J$4:$Q$564,,MATCH(F$2,'PORTIFÓLIO'!$J$3:$Q$3,0))) * N('PORTIFÓLIO'!$S$4:$S$564), 0 ) ), 0)} -> 0 | G79: =F79/$F$4 -> 0 | H79: {=IFERROR( SUM( IF( 'PORTIFÓLIO'!$C$4:$C$564=$A79, N(INDEX('PORTIFÓLIO'!$J$4:$Q$564,,MATCH(H$2,'PORTIFÓLIO'!$J$3:$Q$3,0))) * N('PORTIFÓLIO'!$S$4:$S$564), 0 ) ), 0)} -> 0 | I79: =H79/$H$4 -> 0 | J79: {=IFERROR( SUM( IF( 'PORTIFÓLIO'!$C$4:$C$564=$A79, N(INDEX('PORTIFÓLIO'!$J$4:$Q$564,,MATCH(J$2,'PORTIFÓLIO'!$J$3:$Q$3,0))) * N('PORTIFÓLIO'!$S$4:$S$564), 0 ) ), 0)} -> 0 | K79: =J79/$J$4 -> 0 | L79: {=IFERROR( SUM( IF( 'PORTIFÓLIO'!$C$4:$C$564=$A79, N(INDEX('PORTIFÓLIO'!$J$4:$Q$564,,MATCH(L$2,'PORTIFÓLIO'!$J$3:$Q$3,0))) * N('PORTIFÓLIO'!$S$4:$S$564), 0 ) ), 0)} -> 0 | M79: =L79/$L$4 -> 0 | N79: {=IFERROR( SUM( IF( 'PORTIFÓLIO'!$C$4:$C$564=$A79, N(INDEX('PORTIFÓLIO'!$J$4:$Q$564,,MATCH(N$2,'PORTIFÓLIO'!$J$3:$Q$3,0))) * N('PORTIFÓLIO'!$S$4:$S$564), 0 ) ), 0)} -> 0 | O79: =N79/$N$4 -> 0 | P79: {=IFERROR( SUM( IF( 'PORTIFÓLIO'!$C$4:$C$564=$A79, N(INDEX('PORTIFÓLIO'!$J$4:$Q$564,,MATCH(P$2,'PORTIFÓLIO'!$J$3:$Q$3,0))) * N('PORTIFÓLIO'!$S$4:$S$564), 0 ) ), 0)} -> 0 | Q79: =P79/$P$4 -> 0 | R79: =SUM(P79,N79,L79,J79,H79,D79,B79) -> 0 | S79: =R79/$R$4 -> 0
A80: =IFERROR(__xludf.DUMMYFUNCTION("""COMPUTED_VALUE"""),"CLICK") -> CLICK | B80: {=IFERROR( SUM( IF( 'PORTIFÓLIO'!$C$4:$C$564=$A80, N(INDEX('PORTIFÓLIO'!$J$4:$Q$564,,MATCH(B$2,'PORTIFÓLIO'!$J$3:$Q$3,0))) * N('PORTIFÓLIO'!$S$4:$S$564), 0 ) ), 0)} -> 0 | C80: =B80/$B$4 -> 0 | D80: {=IFERROR( SUM( IF( 'PORTIFÓLIO'!$C$4:$C$564=$A80, N(INDEX('PORTIFÓLIO'!$J$4:$Q$564,,MATCH(D$2,'PORTIFÓLIO'!$J$3:$Q$3,0))) * N('PORTIFÓLIO'!$S$4:$S$564), 0 ) ), 0)} -> 0 | E80: =D80/$D$4 -> 0 | F80: {=IFERROR( SUM( IF( 'PORTIFÓLIO'!$C$4:$C$564=$A80, N(INDEX('PORTIFÓLIO'!$J$4:$Q$564,,MATCH(F$2,'PORTIFÓLIO'!$J$3:$Q$3,0))) * N('PORTIFÓLIO'!$S$4:$S$564), 0 ) ), 0)} -> 0 | G80: =F80/$F$4 -> 0 | H80: {=IFERROR( SUM( IF( 'PORTIFÓLIO'!$C$4:$C$564=$A80, N(INDEX('PORTIFÓLIO'!$J$4:$Q$564,,MATCH(H$2,'PORTIFÓLIO'!$J$3:$Q$3,0))) * N('PORTIFÓLIO'!$S$4:$S$564), 0 ) ), 0)} -> 0 | I80: =H80/$H$4 -> 0 | J80: {=IFERROR( SUM( IF( 'PORTIFÓLIO'!$C$4:$C$564=$A80, N(INDEX('PORTIFÓLIO'!$J$4:$Q$564,,MATCH(J$2,'PORTIFÓLIO'!$J$3:$Q$3,0))) * N('PORTIFÓLIO'!$S$4:$S$564), 0 ) ), 0)} -> 0 | K80: =J80/$J$4 -> 0 | L80: {=IFERROR( SUM( IF( 'PORTIFÓLIO'!$C$4:$C$564=$A80, N(INDEX('PORTIFÓLIO'!$J$4:$Q$564,,MATCH(L$2,'PORTIFÓLIO'!$J$3:$Q$3,0))) * N('PORTIFÓLIO'!$S$4:$S$564), 0 ) ), 0)} -> 0 | M80: =L80/$L$4 -> 0 | N80: {=IFERROR( SUM( IF( 'PORTIFÓLIO'!$C$4:$C$564=$A80, N(INDEX('PORTIFÓLIO'!$J$4:$Q$564,,MATCH(N$2,'PORTIFÓLIO'!$J$3:$Q$3,0))) * N('PORTIFÓLIO'!$S$4:$S$564), 0 ) ), 0)} -> 0 | O80: =N80/$N$4 -> 0 | P80: {=IFERROR( SUM( IF( 'PORTIFÓLIO'!$C$4:$C$564=$A80, N(INDEX('PORTIFÓLIO'!$J$4:$Q$564,,MATCH(P$2,'PORTIFÓLIO'!$J$3:$Q$3,0))) * N('PORTIFÓLIO'!$S$4:$S$564), 0 ) ), 0)} -> 0 | Q80: =P80/$P$4 -> 0 | R80: =SUM(P80,N80,L80,J80,H80,D80,B80) -> 0 | S80: =R80/$R$4 -> 0
A81: =IFERROR(__xludf.DUMMYFUNCTION("""COMPUTED_VALUE"""),"VOLCANE") -> VOLCANE | B81: {=IFERROR( SUM( IF( 'PORTIFÓLIO'!$C$4:$C$564=$A81, N(INDEX('PORTIFÓLIO'!$J$4:$Q$564,,MATCH(B$2,'PORTIFÓLIO'!$J$3:$Q$3,0))) * N('PORTIFÓLIO'!$S$4:$S$564), 0 ) ), 0)} -> 0 | C81: =B81/$B$4 -> 0 | D81: {=IFERROR( SUM( IF( 'PORTIFÓLIO'!$C$4:$C$564=$A81, N(INDEX('PORTIFÓLIO'!$J$4:$Q$564,,MATCH(D$2,'PORTIFÓLIO'!$J$3:$Q$3,0))) * N('PORTIFÓLIO'!$S$4:$S$564), 0 ) ), 0)} -> 0 | E81: =D81/$D$4 -> 0 | F81: {=IFERROR( SUM( IF( 'PORTIFÓLIO'!$C$4:$C$564=$A81, N(INDEX('PORTIFÓLIO'!$J$4:$Q$564,,MATCH(F$2,'PORTIFÓLIO'!$J$3:$Q$3,0))) * N('PORTIFÓLIO'!$S$4:$S$564), 0 ) ), 0)} -> 0 | G81: =F81/$F$4 -> 0 | H81: {=IFERROR( SUM( IF( 'PORTIFÓLIO'!$C$4:$C$564=$A81, N(INDEX('PORTIFÓLIO'!$J$4:$Q$564,,MATCH(H$2,'PORTIFÓLIO'!$J$3:$Q$3,0))) * N('PORTIFÓLIO'!$S$4:$S$564), 0 ) ), 0)} -> 0 | I81: =H81/$H$4 -> 0 | J81: {=IFERROR( SUM( IF( 'PORTIFÓLIO'!$C$4:$C$564=$A81, N(INDEX('PORTIFÓLIO'!$J$4:$Q$564,,MATCH(J$2,'PORTIFÓLIO'!$J$3:$Q$3,0))) * N('PORTIFÓLIO'!$S$4:$S$564), 0 ) ), 0)} -> 0 | K81: =J81/$J$4 -> 0 | L81: {=IFERROR( SUM( IF( 'PORTIFÓLIO'!$C$4:$C$564=$A81, N(INDEX('PORTIFÓLIO'!$J$4:$Q$564,,MATCH(L$2,'PORTIFÓLIO'!$J$3:$Q$3,0))) * N('PORTIFÓLIO'!$S$4:$S$564), 0 ) ), 0)} -> 0 | M81: =L81/$L$4 -> 0 | N81: {=IFERROR( SUM( IF( 'PORTIFÓLIO'!$C$4:$C$564=$A81, N(INDEX('PORTIFÓLIO'!$J$4:$Q$564,,MATCH(N$2,'PORTIFÓLIO'!$J$3:$Q$3,0))) * N('PORTIFÓLIO'!$S$4:$S$564), 0 ) ), 0)} -> 0 | O81: =N81/$N$4 -> 0 | P81: {=IFERROR( SUM( IF( 'PORTIFÓLIO'!$C$4:$C$564=$A81, N(INDEX('PORTIFÓLIO'!$J$4:$Q$564,,MATCH(P$2,'PORTIFÓLIO'!$J$3:$Q$3,0))) * N('PORTIFÓLIO'!$S$4:$S$564), 0 ) ), 0)} -> 0 | Q81: =P81/$P$4 -> 0 | R81: =SUM(P81,N81,L81,J81,H81,D81,B81) -> 0 | S81: =R81/$R$4 -> 0
A82: =IFERROR(__xludf.DUMMYFUNCTION("""COMPUTED_VALUE"""),"CRUCIAL") -> CRUCIAL | B82: {=IFERROR( SUM( IF( 'PORTIFÓLIO'!$C$4:$C$564=$A82, N(INDEX('PORTIFÓLIO'!$J$4:$Q$564,,MATCH(B$2,'PORTIFÓLIO'!$J$3:$Q$3,0))) * N('PORTIFÓLIO'!$S$4:$S$564), 0 ) ), 0)} -> 0 | C82: =B82/$B$4 -> 0 | D82: {=IFERROR( SUM( IF( 'PORTIFÓLIO'!$C$4:$C$564=$A82, N(INDEX('PORTIFÓLIO'!$J$4:$Q$564,,MATCH(D$2,'PORTIFÓLIO'!$J$3:$Q$3,0))) * N('PORTIFÓLIO'!$S$4:$S$564), 0 ) ), 0)} -> 0 | E82: =D82/$D$4 -> 0 | F82: {=IFERROR( SUM( IF( 'PORTIFÓLIO'!$C$4:$C$564=$A82, N(INDEX('PORTIFÓLIO'!$J$4:$Q$564,,MATCH(F$2,'PORTIFÓLIO'!$J$3:$Q$3,0))) * N('PORTIFÓLIO'!$S$4:$S$564), 0 ) ), 0)} -> 0 | G82: =F82/$F$4 -> 0 | H82: {=IFERROR( SUM( IF( 'PORTIFÓLIO'!$C$4:$C$564=$A82, N(INDEX('PORTIFÓLIO'!$J$4:$Q$564,,MATCH(H$2,'PORTIFÓLIO'!$J$3:$Q$3,0))) * N('PORTIFÓLIO'!$S$4:$S$564), 0 ) ), 0)} -> 0 | I82: =H82/$H$4 -> 0 | J82: {=IFERROR( SUM( IF( 'PORTIFÓLIO'!$C$4:$C$564=$A82, N(INDEX('PORTIFÓLIO'!$J$4:$Q$564,,MATCH(J$2,'PORTIFÓLIO'!$J$3:$Q$3,0))) * N('PORTIFÓLIO'!$S$4:$S$564), 0 ) ), 0)} -> 0 | K82: =J82/$J$4 -> 0 | L82: {=IFERROR( SUM( IF( 'PORTIFÓLIO'!$C$4:$C$564=$A82, N(INDEX('PORTIFÓLIO'!$J$4:$Q$564,,MATCH(L$2,'PORTIFÓLIO'!$J$3:$Q$3,0))) * N('PORTIFÓLIO'!$S$4:$S$564), 0 ) ), 0)} -> 0 | M82: =L82/$L$4 -> 0 | N82: {=IFERROR( SUM( IF( 'PORTIFÓLIO'!$C$4:$C$564=$A82, N(INDEX('PORTIFÓLIO'!$J$4:$Q$564,,MATCH(N$2,'PORTIFÓLIO'!$J$3:$Q$3,0))) * N('PORTIFÓLIO'!$S$4:$S$564), 0 ) ), 0)} -> 0 | O82: =N82/$N$4 -> 0 | P82: {=IFERROR( SUM( IF( 'PORTIFÓLIO'!$C$4:$C$564=$A82, N(INDEX('PORTIFÓLIO'!$J$4:$Q$564,,MATCH(P$2,'PORTIFÓLIO'!$J$3:$Q$3,0))) * N('PORTIFÓLIO'!$S$4:$S$564), 0 ) ), 0)} -> 0 | Q82: =P82/$P$4 -> 0 | R82: =SUM(P82,N82,L82,J82,H82,D82,B82) -> 0 | S82: =R82/$R$4 -> 0
A83: =IFERROR(__xludf.DUMMYFUNCTION("""COMPUTED_VALUE"""),"SUMYZIN 500 SC") -> SUMYZIN 500 SC | B83: {=IFERROR( SUM( IF( 'PORTIFÓLIO'!$C$4:$C$564=$A83, N(INDEX('PORTIFÓLIO'!$J$4:$Q$564,,MATCH(B$2,'PORTIFÓLIO'!$J$3:$Q$3,0))) * N('PORTIFÓLIO'!$S$4:$S$564), 0 ) ), 0)} -> 0 | C83: =B83/$B$4 -> 0 | D83: {=IFERROR( SUM( IF( 'PORTIFÓLIO'!$C$4:$C$564=$A83, N(INDEX('PORTIFÓLIO'!$J$4:$Q$564,,MATCH(D$2,'PORTIFÓLIO'!$J$3:$Q$3,0))) * N('PORTIFÓLIO'!$S$4:$S$564), 0 ) ), 0)} -> 0 | E83: =D83/$D$4 -> 0 | F83: {=IFERROR( SUM( IF( 'PORTIFÓLIO'!$C$4:$C$564=$A83, N(INDEX('PORTIFÓLIO'!$J$4:$Q$564,,MATCH(F$2,'PORTIFÓLIO'!$J$3:$Q$3,0))) * N('PORTIFÓLIO'!$S$4:$S$564), 0 ) ), 0)} -> 0 | G83: =F83/$F$4 -> 0 | H83: {=IFERROR( SUM( IF( 'PORTIFÓLIO'!$C$4:$C$564=$A83, N(INDEX('PORTIFÓLIO'!$J$4:$Q$564,,MATCH(H$2,'PORTIFÓLIO'!$J$3:$Q$3,0))) * N('PORTIFÓLIO'!$S$4:$S$564), 0 ) ), 0)} -> 0 | I83: =H83/$H$4 -> 0 | J83: {=IFERROR( SUM( IF( 'PORTIFÓLIO'!$C$4:$C$564=$A83, N(INDEX('PORTIFÓLIO'!$J$4:$Q$564,,MATCH(J$2,'PORTIFÓLIO'!$J$3:$Q$3,0))) * N('PORTIFÓLIO'!$S$4:$S$564), 0 ) ), 0)} -> 0 | K83: =J83/$J$4 -> 0 | L83: {=IFERROR( SUM( IF( 'PORTIFÓLIO'!$C$4:$C$564=$A83, N(INDEX('PORTIFÓLIO'!$J$4:$Q$564,,MATCH(L$2,'PORTIFÓLIO'!$J$3:$Q$3,0))) * N('PORTIFÓLIO'!$S$4:$S$564), 0 ) ), 0)} -> 0 | M83: =L83/$L$4 -> 0 | N83: {=IFERROR( SUM( IF( 'PORTIFÓLIO'!$C$4:$C$564=$A83, N(INDEX('PORTIFÓLIO'!$J$4:$Q$564,,MATCH(N$2,'PORTIFÓLIO'!$J$3:$Q$3,0))) * N('PORTIFÓLIO'!$S$4:$S$564), 0 ) ), 0)} -> 0 | O83: =N83/$N$4 -> 0 | P83: {=IFERROR( SUM( IF( 'PORTIFÓLIO'!$C$4:$C$564=$A83, N(INDEX('PORTIFÓLIO'!$J$4:$Q$564,,MATCH(P$2,'PORTIFÓLIO'!$J$3:$Q$3,0))) * N('PORTIFÓLIO'!$S$4:$S$564), 0 ) ), 0)} -> 0 | Q83: =P83/$P$4 -> 0 | R83: =SUM(P83,N83,L83,J83,H83,D83,B83) -> 0 | S83: =R83/$R$4 -> 0
A84: =IFERROR(__xludf.DUMMYFUNCTION("""COMPUTED_VALUE"""),"U 46 BR") -> U 46 BR | B84: {=IFERROR( SUM( IF( 'PORTIFÓLIO'!$C$4:$C$564=$A84, N(INDEX('PORTIFÓLIO'!$J$4:$Q$564,,MATCH(B$2,'PORTIFÓLIO'!$J$3:$Q$3,0))) * N('PORTIFÓLIO'!$S$4:$S$564), 0 ) ), 0)} -> 0 | C84: =B84/$B$4 -> 0 | D84: {=IFERROR( SUM( IF( 'PORTIFÓLIO'!$C$4:$C$564=$A84, N(INDEX('PORTIFÓLIO'!$J$4:$Q$564,,MATCH(D$2,'PORTIFÓLIO'!$J$3:$Q$3,0))) * N('PORTIFÓLIO'!$S$4:$S$564), 0 ) ), 0)} -> 0 | E84: =D84/$D$4 -> 0 | F84: {=IFERROR( SUM( IF( 'PORTIFÓLIO'!$C$4:$C$564=$A84, N(INDEX('PORTIFÓLIO'!$J$4:$Q$564,,MATCH(F$2,'PORTIFÓLIO'!$J$3:$Q$3,0))) * N('PORTIFÓLIO'!$S$4:$S$564), 0 ) ), 0)} -> 0 | G84: =F84/$F$4 -> 0 | H84: {=IFERROR( SUM( IF( 'PORTIFÓLIO'!$C$4:$C$564=$A84, N(INDEX('PORTIFÓLIO'!$J$4:$Q$564,,MATCH(H$2,'PORTIFÓLIO'!$J$3:$Q$3,0))) * N('PORTIFÓLIO'!$S$4:$S$564), 0 ) ), 0)} -> 0 | I84: =H84/$H$4 -> 0 | J84: {=IFERROR( SUM( IF( 'PORTIFÓLIO'!$C$4:$C$564=$A84, N(INDEX('PORTIFÓLIO'!$J$4:$Q$564,,MATCH(J$2,'PORTIFÓLIO'!$J$3:$Q$3,0))) * N('PORTIFÓLIO'!$S$4:$S$564), 0 ) ), 0)} -> 0 | K84: =J84/$J$4 -> 0 | L84: {=IFERROR( SUM( IF( 'PORTIFÓLIO'!$C$4:$C$564=$A84, N(INDEX('PORTIFÓLIO'!$J$4:$Q$564,,MATCH(L$2,'PORTIFÓLIO'!$J$3:$Q$3,0))) * N('PORTIFÓLIO'!$S$4:$S$564), 0 ) ), 0)} -> 0 | M84: =L84/$L$4 -> 0 | N84: {=IFERROR( SUM( IF( 'PORTIFÓLIO'!$C$4:$C$564=$A84, N(INDEX('PORTIFÓLIO'!$J$4:$Q$564,,MATCH(N$2,'PORTIFÓLIO'!$J$3:$Q$3,0))) * N('PORTIFÓLIO'!$S$4:$S$564), 0 ) ), 0)} -> 0 | O84: =N84/$N$4 -> 0 | P84: {=IFERROR( SUM( IF( 'PORTIFÓLIO'!$C$4:$C$564=$A84, N(INDEX('PORTIFÓLIO'!$J$4:$Q$564,,MATCH(P$2,'PORTIFÓLIO'!$J$3:$Q$3,0))) * N('PORTIFÓLIO'!$S$4:$S$564), 0 ) ), 0)} -> 0 | Q84: =P84/$P$4 -> 0 | R84: =SUM(P84,N84,L84,J84,H84,D84,B84) -> 0 | S84: =R84/$R$4 -> 0
A85: =IFERROR(__xludf.DUMMYFUNCTION("""COMPUTED_VALUE"""),"ZETHAMAXX") -> ZETHAMAXX | B85: {=IFERROR( SUM( IF( 'PORTIFÓLIO'!$C$4:$C$564=$A85, N(INDEX('PORTIFÓLIO'!$J$4:$Q$564,,MATCH(B$2,'PORTIFÓLIO'!$J$3:$Q$3,0))) * N('PORTIFÓLIO'!$S$4:$S$564), 0 ) ), 0)} -> 0 | C85: =B85/$B$4 -> 0 | D85: {=IFERROR( SUM( IF( 'PORTIFÓLIO'!$C$4:$C$564=$A85, N(INDEX('PORTIFÓLIO'!$J$4:$Q$564,,MATCH(D$2,'PORTIFÓLIO'!$J$3:$Q$3,0))) * N('PORTIFÓLIO'!$S$4:$S$564), 0 ) ), 0)} -> 0 | E85: =D85/$D$4 -> 0 | F85: {=IFERROR( SUM( IF( 'PORTIFÓLIO'!$C$4:$C$564=$A85, N(INDEX('PORTIFÓLIO'!$J$4:$Q$564,,MATCH(F$2,'PORTIFÓLIO'!$J$3:$Q$3,0))) * N('PORTIFÓLIO'!$S$4:$S$564), 0 ) ), 0)} -> 0 | G85: =F85/$F$4 -> 0 | H85: {=IFERROR( SUM( IF( 'PORTIFÓLIO'!$C$4:$C$564=$A85, N(INDEX('PORTIFÓLIO'!$J$4:$Q$564,,MATCH(H$2,'PORTIFÓLIO'!$J$3:$Q$3,0))) * N('PORTIFÓLIO'!$S$4:$S$564), 0 ) ), 0)} -> 0 | I85: =H85/$H$4 -> 0 | J85: {=IFERROR( SUM( IF( 'PORTIFÓLIO'!$C$4:$C$564=$A85, N(INDEX('PORTIFÓLIO'!$J$4:$Q$564,,MATCH(J$2,'PORTIFÓLIO'!$J$3:$Q$3,0))) * N('PORTIFÓLIO'!$S$4:$S$564), 0 ) ), 0)} -> 0 | K85: =J85/$J$4 -> 0 | L85: {=IFERROR( SUM( IF( 'PORTIFÓLIO'!$C$4:$C$564=$A85, N(INDEX('PORTIFÓLIO'!$J$4:$Q$564,,MATCH(L$2,'PORTIFÓLIO'!$J$3:$Q$3,0))) * N('PORTIFÓLIO'!$S$4:$S$564), 0 ) ), 0)} -> 0 | M85: =L85/$L$4 -> 0 | N85: {=IFERROR( SUM( IF( 'PORTIFÓLIO'!$C$4:$C$564=$A85, N(INDEX('PORTIFÓLIO'!$J$4:$Q$564,,MATCH(N$2,'PORTIFÓLIO'!$J$3:$Q$3,0))) * N('PORTIFÓLIO'!$S$4:$S$564), 0 ) ), 0)} -> 8596.9042 | O85: =N85/$N$4 -> 7.0582136 | P85: {=IFERROR( SUM( IF( 'PORTIFÓLIO'!$C$4:$C$564=$A85, N(INDEX('PORTIFÓLIO'!$J$4:$Q$564,,MATCH(P$2,'PORTIFÓLIO'!$J$3:$Q$3,0))) * N('PORTIFÓLIO'!$S$4:$S$564), 0 ) ), 0)} -> 0 | Q85: =P85/$P$4 -> 0 | R85: =SUM(P85,N85,L85,J85,H85,D85,B85) -> 8596.9042 | S85: =R85/$R$4 -> 2.5708445
A86: =IFERROR(__xludf.DUMMYFUNCTION("""COMPUTED_VALUE"""),"ZETHAMAXX EVO") -> ZETHAMAXX EVO | B86: {=IFERROR( SUM( IF( 'PORTIFÓLIO'!$C$4:$C$564=$A86, N(INDEX('PORTIFÓLIO'!$J$4:$Q$564,,MATCH(B$2,'PORTIFÓLIO'!$J$3:$Q$3,0))) * N('PORTIFÓLIO'!$S$4:$S$564), 0 ) ), 0)} -> 0 | C86: =B86/$B$4 -> 0 | D86: {=IFERROR( SUM( IF( 'PORTIFÓLIO'!$C$4:$C$564=$A86, N(INDEX('PORTIFÓLIO'!$J$4:$Q$564,,MATCH(D$2,'PORTIFÓLIO'!$J$3:$Q$3,0))) * N('PORTIFÓLIO'!$S$4:$S$564), 0 ) ), 0)} -> 0 | E86: =D86/$D$4 -> 0 | F86: {=IFERROR( SUM( IF( 'PORTIFÓLIO'!$C$4:$C$564=$A86, N(INDEX('PORTIFÓLIO'!$J$4:$Q$564,,MATCH(F$2,'PORTIFÓLIO'!$J$3:$Q$3,0))) * N('PORTIFÓLIO'!$S$4:$S$564), 0 ) ), 0)} -> 0 | G86: =F86/$F$4 -> 0 | H86: {=IFERROR( SUM( IF( 'PORTIFÓLIO'!$C$4:$C$564=$A86, N(INDEX('PORTIFÓLIO'!$J$4:$Q$564,,MATCH(H$2,'PORTIFÓLIO'!$J$3:$Q$3,0))) * N('PORTIFÓLIO'!$S$4:$S$564), 0 ) ), 0)} -> 0 | I86: =H86/$H$4 -> 0 | J86: {=IFERROR( SUM( IF( 'PORTIFÓLIO'!$C$4:$C$564=$A86, N(INDEX('PORTIFÓLIO'!$J$4:$Q$564,,MATCH(J$2,'PORTIFÓLIO'!$J$3:$Q$3,0))) * N('PORTIFÓLIO'!$S$4:$S$564), 0 ) ), 0)} -> 0 | K86: =J86/$J$4 -> 0 | L86: {=IFERROR( SUM( IF( 'PORTIFÓLIO'!$C$4:$C$564=$A86, N(INDEX('PORTIFÓLIO'!$J$4:$Q$564,,MATCH(L$2,'PORTIFÓLIO'!$J$3:$Q$3,0))) * N('PORTIFÓLIO'!$S$4:$S$564), 0 ) ), 0)} -> 0 | M86: =L86/$L$4 -> 0 | N86: {=IFERROR( SUM( IF( 'PORTIFÓLIO'!$C$4:$C$564=$A86, N(INDEX('PORTIFÓLIO'!$J$4:$Q$564,,MATCH(N$2,'PORTIFÓLIO'!$J$3:$Q$3,0))) * N('PORTIFÓLIO'!$S$4:$S$564), 0 ) ), 0)} -> 0 | O86: =N86/$N$4 -> 0 | P86: {=IFERROR( SUM( IF( 'PORTIFÓLIO'!$C$4:$C$564=$A86, N(INDEX('PORTIFÓLIO'!$J$4:$Q$564,,MATCH(P$2,'PORTIFÓLIO'!$J$3:$Q$3,0))) * N('PORTIFÓLIO'!$S$4:$S$564), 0 ) ), 0)} -> 0 | Q86: =P86/$P$4 -> 0 | R86: =SUM(P86,N86,L86,J86,H86,D86,B86) -> 0 | S86: =R86/$R$4 -> 0
A87: =IFERROR(__xludf.DUMMYFUNCTION("""COMPUTED_VALUE"""),"CALARIS") -> CALARIS | B87: {=IFERROR( SUM( IF( 'PORTIFÓLIO'!$C$4:$C$564=$A87, N(INDEX('PORTIFÓLIO'!$J$4:$Q$564,,MATCH(B$2,'PORTIFÓLIO'!$J$3:$Q$3,0))) * N('PORTIFÓLIO'!$S$4:$S$564), 0 ) ), 0)} -> 0 | C87: =B87/$B$4 -> 0 | D87: {=IFERROR( SUM( IF( 'PORTIFÓLIO'!$C$4:$C$564=$A87, N(INDEX('PORTIFÓLIO'!$J$4:$Q$564,,MATCH(D$2,'PORTIFÓLIO'!$J$3:$Q$3,0))) * N('PORTIFÓLIO'!$S$4:$S$564), 0 ) ), 0)} -> 0 | E87: =D87/$D$4 -> 0 | F87: {=IFERROR( SUM( IF( 'PORTIFÓLIO'!$C$4:$C$564=$A87, N(INDEX('PORTIFÓLIO'!$J$4:$Q$564,,MATCH(F$2,'PORTIFÓLIO'!$J$3:$Q$3,0))) * N('PORTIFÓLIO'!$S$4:$S$564), 0 ) ), 0)} -> 0 | G87: =F87/$F$4 -> 0 | H87: {=IFERROR( SUM( IF( 'PORTIFÓLIO'!$C$4:$C$564=$A87, N(INDEX('PORTIFÓLIO'!$J$4:$Q$564,,MATCH(H$2,'PORTIFÓLIO'!$J$3:$Q$3,0))) * N('PORTIFÓLIO'!$S$4:$S$564), 0 ) ), 0)} -> 0 | I87: =H87/$H$4 -> 0 | J87: {=IFERROR( SUM( IF( 'PORTIFÓLIO'!$C$4:$C$564=$A87, N(INDEX('PORTIFÓLIO'!$J$4:$Q$564,,MATCH(J$2,'PORTIFÓLIO'!$J$3:$Q$3,0))) * N('PORTIFÓLIO'!$S$4:$S$564), 0 ) ), 0)} -> 0 | K87: =J87/$J$4 -> 0 | L87: {=IFERROR( SUM( IF( 'PORTIFÓLIO'!$C$4:$C$564=$A87, N(INDEX('PORTIFÓLIO'!$J$4:$Q$564,,MATCH(L$2,'PORTIFÓLIO'!$J$3:$Q$3,0))) * N('PORTIFÓLIO'!$S$4:$S$564), 0 ) ), 0)} -> 0 | M87: =L87/$L$4 -> 0 | N87: {=IFERROR( SUM( IF( 'PORTIFÓLIO'!$C$4:$C$564=$A87, N(INDEX('PORTIFÓLIO'!$J$4:$Q$564,,MATCH(N$2,'PORTIFÓLIO'!$J$3:$Q$3,0))) * N('PORTIFÓLIO'!$S$4:$S$564), 0 ) ), 0)} -> 0 | O87: =N87/$N$4 -> 0 | P87: {=IFERROR( SUM( IF( 'PORTIFÓLIO'!$C$4:$C$564=$A87, N(INDEX('PORTIFÓLIO'!$J$4:$Q$564,,MATCH(P$2,'PORTIFÓLIO'!$J$3:$Q$3,0))) * N('PORTIFÓLIO'!$S$4:$S$564), 0 ) ), 0)} -> 0 | Q87: =P87/$P$4 -> 0 | R87: =SUM(P87,N87,L87,J87,H87,D87,B87) -> 0 | S87: =R87/$R$4 -> 0
A88: =IFERROR(__xludf.DUMMYFUNCTION("""COMPUTED_VALUE"""),"DUAL GOLD") -> DUAL GOLD | B88: {=IFERROR( SUM( IF( 'PORTIFÓLIO'!$C$4:$C$564=$A88, N(INDEX('PORTIFÓLIO'!$J$4:$Q$564,,MATCH(B$2,'PORTIFÓLIO'!$J$3:$Q$3,0))) * N('PORTIFÓLIO'!$S$4:$S$564), 0 ) ), 0)} -> 0 | C88: =B88/$B$4 -> 0 | D88: {=IFERROR( SUM( IF( 'PORTIFÓLIO'!$C$4:$C$564=$A88, N(INDEX('PORTIFÓLIO'!$J$4:$Q$564,,MATCH(D$2,'PORTIFÓLIO'!$J$3:$Q$3,0))) * N('PORTIFÓLIO'!$S$4:$S$564), 0 ) ), 0)} -> 8738.19 | E88: =D88/$D$4 -> 29.1273 | F88: {=IFERROR( SUM( IF( 'PORTIFÓLIO'!$C$4:$C$564=$A88, N(INDEX('PORTIFÓLIO'!$J$4:$Q$564,,MATCH(F$2,'PORTIFÓLIO'!$J$3:$Q$3,0))) * N('PORTIFÓLIO'!$S$4:$S$564), 0 ) ), 0)} -> 6408.006 | G88: =F88/$F$4 -> 29.1273 | H88: {=IFERROR( SUM( IF( 'PORTIFÓLIO'!$C$4:$C$564=$A88, N(INDEX('PORTIFÓLIO'!$J$4:$Q$564,,MATCH(H$2,'PORTIFÓLIO'!$J$3:$Q$3,0))) * N('PORTIFÓLIO'!$S$4:$S$564), 0 ) ), 0)} -> 6990.552 | I88: =H88/$H$4 -> 34.95276 | J88: {=IFERROR( SUM( IF( 'PORTIFÓLIO'!$C$4:$C$564=$A88, N(INDEX('PORTIFÓLIO'!$J$4:$Q$564,,MATCH(J$2,'PORTIFÓLIO'!$J$3:$Q$3,0))) * N('PORTIFÓLIO'!$S$4:$S$564), 0 ) ), 0)} -> 13142.238 | K88: =J88/$J$4 -> 34.95276 | L88: {=IFERROR( SUM( IF( 'PORTIFÓLIO'!$C$4:$C$564=$A88, N(INDEX('PORTIFÓLIO'!$J$4:$Q$564,,MATCH(L$2,'PORTIFÓLIO'!$J$3:$Q$3,0))) * N('PORTIFÓLIO'!$S$4:$S$564), 0 ) ), 0)} -> 6408.006 | M88: =L88/$L$4 -> 29.1273 | N88: {=IFERROR( SUM( IF( 'PORTIFÓLIO'!$C$4:$C$564=$A88, N(INDEX('PORTIFÓLIO'!$J$4:$Q$564,,MATCH(N$2,'PORTIFÓLIO'!$J$3:$Q$3,0))) * N('PORTIFÓLIO'!$S$4:$S$564), 0 ) ), 0)} -> 35477.051 | O88: =N88/$N$4 -> 29.1273 | P88: {=IFERROR( SUM( IF( 'PORTIFÓLIO'!$C$4:$C$564=$A88, N(INDEX('PORTIFÓLIO'!$J$4:$Q$564,,MATCH(P$2,'PORTIFÓLIO'!$J$3:$Q$3,0))) * N('PORTIFÓLIO'!$S$4:$S$564), 0 ) ), 0)} -> 9320.736 | Q88: =P88/$P$4 -> 29.1273 | R88: =SUM(P88,N88,L88,J88,H88,D88,B88) -> 80076.773 | S88: =R88/$R$4 -> 23.946403
